Workbook

Sheet 摘要
A1: 一頁摘要 — 結論、與市場的差異、現價隱含什麼、驗證點（全部依輸入連動）
A2: ="模型端＝目前情境：" & CHOOSE(輸入與假設!$C$5,"保守 4.2 GW","基準 5.6 GW","積極 8 GW") & "（預設＝基準）；共識＝data/consensus_crwv_20260925.json（2026-09-25）" -> 模型端＝目前情境：基準 5.6 GW（預設＝基準）；共識＝data/consensus_crwv_20260925.json（2026-09-25）
A4: 1｜結論
A5: 結論｜評等代碼（1＝買進、0＝中立、−1＝賣出） | C5: =損益與評價!C71 -> -1
A6: 結論｜評等 | C6: =CHOOSE(C5+2,"賣出","中立","買進") -> 賣出
A7: 結論｜點位（加權目標價） | B7: US$ | C7: =損益與評價!C63 -> 45.50115
A8: 結論｜現價 | B8: US$ | C8: =輸入與假設!$C$88 -> 90.13
A9: 結論｜空間 | B9: % | C9: =C7/C8-1 -> -0.49516088
A10: 結論｜情境區間（下緣／上緣） | B10: US$ | C10: =損益與評價!C76 -> 30.953266 | D10: =損益與評價!D76 -> 69.741657
A11: 結論｜方法區間（下緣／上緣） | B11: US$ | C11: =損益與評價!C78 -> 29.475228 | D11: =損益與評價!D78 -> 45.50115
A12: 結論｜賣出門檻價 | B12: US$ | C12: =損益與評價!$C$72 -> 76.6105
A13: 結論｜點位 − 賣出門檻 | B13: US$ | C13: =C7-C12 -> -31.10935
A14: 結論｜結論句 | C14: =C6&"：點位 $"&TEXT(C7,"0.0")&"，較現價 $"&TEXT(C8,"0.00")&" "&IF(C9>=0,"高","低")&" "&TEXT(ABS(C9)*100,"0")&"%；情境區間 $"&TEXT(C10,"0.0")&"–$"&TEXT(D10,"0.0")&"，方法區間 $"&TEXT(C11,"0.0")&"–$"&TEXT(D11,"0.0")&"；點位"&IF(C13<0,"低於","高於")&"賣出門檻 $"&TEXT(C12,"0.0")&" 達 $"&TEXT(ABS(C13),"0.0")&"。" -> 賣出：點位 $45.5，較現價 $90.13 低 50%；情境區間 $31.0–$69.7，方法區間 $29.5–$45.5；點位低於賣出門檻 $76.6 達 $31.1。
A15: 結論｜情境判斷句 | C15: =損益與評價!C84 -> 情境區間上緣 $69.7 低於現價 $90.13：賣出在三個擴張情境下都成立。
A16: 2｜與市場的差異（模型：目前情境 vs 共識；FY26–FY28）
A17: 差異｜營收｜模型 | B17: US$bn | C17: =損益與評價!C16 -> 13.066 | D17: =損益與評價!D16 -> 26.1275 | E17: =損益與評價!E16 -> 36.669415
A18: 差異｜營收｜共識 | B18: US$bn | C18: =輸入與假設!$C$142 -> 12.882 | D18: =輸入與假設!$D$142 -> 26.376 | E18: =輸入與假設!$E$142 -> 42.55
A19: 差異｜營收｜差距 | B19: % | C19: =C17/C18-1 -> 0.014283496 | D19: =D17/D18-1 -> -0.0094214437 | E19: =E17/E18-1 -> -0.1382041
A20: 差異｜調整後 EBITDA｜模型 | B20: US$bn | C20: =輸入與假設!$C$131+損益與評價!C11 -> 7.63067 | D20: =損益與評價!D19 -> 15.807137 | E20: =損益與評價!E19 -> 22.735038
A21: 差異｜調整後 EBITDA｜共識 | B21: US$bn | C21: =輸入與假設!$C$143 -> 7.574 | D21: =輸入與假設!$D$143 -> 16.656 | E21: =輸入與假設!$E$143 -> 28.857
A22: 差異｜調整後 EBITDA｜差距 | B22: % | C22: =C20/C21-1 -> 0.0074821759 | D22: =D20/D21-1 -> -0.050964367 | E22: =E20/E21-1 -> -0.21214826
A23: 差異｜調整後 EBITDA｜差距（金額） | B23: US$bn | C23: =C20-C21 -> 0.05667 | D23: =D20-D21 -> -0.8488625 | E23: =E20-E21 -> -6.1219624
A24: 差異｜EBITDA 率｜模型 | B24: % | C24: =C20/C17 -> 0.58400964 | D24: =D20/D17 -> 0.605 | E24: =E20/E17 -> 0.62
A25: 差異｜EBITDA 率｜共識 | B25: % | C25: =輸入與假設!$C$144 -> 0.588 | D25: =輸入與假設!$D$144 -> 0.632 | E25: =輸入與假設!$E$144 -> 0.678
A26: 差異｜EBITDA 率｜差距（百分點） | B26: pt | C26: =C24-C25 -> -0.0039903567 | D26: =D24-D25 -> -0.027 | E26: =E24-E25 -> -0.058
A27: 差異｜CapEx（毛額）｜模型 | B27: US$bn | C27: =輸入與假設!$C$122+輸入與假設!C$63 -> 36.975 | D27: =輸入與假設!D$63 -> 38.335 | E27: =輸入與假設!E$63 -> 29.41
A28: 差異｜CapEx（毛額）｜共識 | B28: US$bn | C28: =輸入與假設!$C$145 -> 35.953 | D28: =輸入與假設!$D$145 -> 46.476 | E28: =輸入與假設!$E$145 -> 50.129
A29: 差異｜CapEx（毛額）｜差距 | B29: % | C29: =C27/C28-1 -> 0.028426001 | D29: =D27/D28-1 -> -0.17516568 | E29: =E27/E28-1 -> -0.41331365
A30: 差異｜淨負債｜模型 | B30: US$bn | C30: =收支與融資!C135 -> 45.392496 | D30: =收支與融資!D135 -> 71.885337 | E30: =收支與融資!E135 -> 84.30991
A31: 差異｜淨負債｜共識 | B31: US$bn | C31: =輸入與假設!$C$146 -> 46.442 | D31: =輸入與假設!$D$146 -> 74.707 | E31: =輸入與假設!$E$146 -> 96.039
A32: 差異｜淨負債｜差距 | B32: % | C32: =C30/C31-1 -> -0.022598169 | D32: =D30/D31-1 -> -0.037769723 | E32: =E30/E31-1 -> -0.12212841
A33: 差異｜淨負債｜差距（金額） | B33: US$bn | C33: =C30-C31 -> -1.0495042 | D33: =D30-D31 -> -2.8216627 | E33: =E30-E31 -> -11.72909
A34: 差異｜分歧項目（超過門檻者） | C34: =MID(IF(ABS(C19)>輸入與假設!$C$150,"、營收 "&IF(C19<0,"−","+")&TEXT(ABS(C19)*100,"0.0")&"%","")&IF(ABS(C22)>輸入與假設!$C$150,"、EBITDA "&IF(C23<0,"−","+")&"$"&TEXT(ABS(C23),"#,##0.00")&"bn"&"／"&IF(C26<0,"−","+")&TEXT(ABS(C26)*100,"0.0")&"pt","")&IF(ABS(C29)>輸入與假設!$C$150,"、CapEx "&IF(C29<0,"−","+")&TEXT(ABS(C29)*100,"0.0")&"%",""),2,999) | D34: =MID(IF(ABS(D19)>輸入與假設!$C$150,"、營收 "&IF(D19<0,"−","+")&TEXT(ABS(D19)*100,"0.0")&"%","")&IF(ABS(D22)>輸入與假設!$C$150,"、EBITDA "&IF(D23<0,"−","+")&"$"&TEXT(ABS(D23),"#,##0.00")&"bn"&"／"&IF(D26<0,"−","+")&TEXT(ABS(D26)*100,"0.0")&"pt","")&IF(ABS(D29)>輸入與假設!$C$150,"、CapEx "&IF(D29<0,"−","+")&TEXT(ABS(D29)*100,"0.0")&"%",""),2,999) -> EBITDA −$0.85bn／−2.7pt、CapEx −17.5% | E34: =MID(IF(ABS(E19)>輸入與假設!$C$150,"、營收 "&IF(E19<0,"−","+")&TEXT(ABS(E19)*100,"0.0")&"%","")&IF(ABS(E22)>輸入與假設!$C$150,"、EBITDA "&IF(E23<0,"−","+")&"$"&TEXT(ABS(E23),"#,##0.00")&"bn"&"／"&IF(E26<0,"−","+")&TEXT(ABS(E26)*100,"0.0")&"pt","")&IF(ABS(E29)>輸入與假設!$C$150,"、CapEx "&IF(E29<0,"−","+")&TEXT(ABS(E29)*100,"0.0")&"%",""),2,999) -> 營收 −13.8%、EBITDA −$6.12bn／−5.8pt、CapEx −41.3%
A35: 差異｜分歧起始年（1＝FY26…3＝FY28；0＝無） | C35: =IF(C34<>"",1,IF(D34<>"",2,IF(E34<>"",3,0))) -> 2
A36: 差異｜判斷句 | C36: =CHOOSE(C35+1,"FY26–FY28 營收、EBITDA、CapEx 與共識差距皆在 "&IF(ROUND(ABS(輸入與假設!$C$150)*100,4)=INT(ROUND(ABS(輸入與假設!$C$150)*100,4)),TEXT(ROUND(ABS(輸入與假設!$C$150)*100,4),"0"),TEXT(ROUND(ABS(輸入與假設!$C$150)*100,4),"0.0"))&"%"&" 以內。","分歧始於 FY26（"&C34&"）"&"；FY27 "&IF(D34="","回到 "&IF(ROUND(ABS(輸入與假設!$C$150)*100,4)=INT(ROUND(ABS(輸入與假設!$C$150)*100,4)),TEXT(ROUND(ABS(輸入與假設!$C$150)*100,4),"0"),TEXT(ROUND(ABS(輸入與假設!$C$150)*100,4),"0.0"))&"%"&" 以內",D34)&"；FY28 "&IF(E34="","回到 "&IF(ROUND(ABS(輸入與假設!$C$150)*100,4)=INT(ROUND(ABS(輸入與假設!$C$150)*100,4)),TEXT(ROUND(ABS(輸入與假設!$C$150)*100,4),"0"),TEXT(ROUND(ABS(輸入與假設!$C$150)*100,4),"0.0"))&"%"&" 以內",E34)&"。","FY26 營收、EBITDA、CapEx 與共識差距在 "&IF(ROUND(ABS(輸入與假設!$C$150)*100,4)=INT(ROUND(ABS(輸入與假設!$C$150)*100,4)),TEXT(ROUND(ABS(輸入與假設!$C$150)*100,4),"0"),TEXT(ROUND(ABS(輸入與假設!$C$150)*100,4),"0.0"))&"%"&" 以內；分歧始於 FY27（"&D34&"）"&"；FY28 "&IF(E34="","回到 "&IF(ROUND(ABS(輸入與假設!$C$150)*100,4)=INT(ROUND(ABS(輸入與假設!$C$150)*100,4)),TEXT(ROUND(ABS(輸入與假設!$C$150)*100,4),"0"),TEXT(ROUND(ABS(輸入與假設!$C$150)*100,4),"0.0"))&"%"&" 以內",E34)&"。","FY26–FY27 營收、EBITDA、CapEx 與共識差距在 "&IF(ROUND(ABS(輸入與假設!$C$150)*100,4)=INT(ROUND(ABS(輸入與假設!$C$150)*100,4)),TEXT(ROUND(ABS(輸入與假設!$C$150)*100,4),"0"),TEXT(ROUND(ABS(輸入與假設!$C$150)*100,4),"0.0"))&"%"&" 以內；分歧始於 FY28（"&E34&"）。") -> FY26 營收、EBITDA、CapEx 與共識差距在 5% 以內；分歧始於 FY27（EBITDA −$0.85bn／−2.7pt、CapEx −17.5%）；FY28 營收 −13.8%、EBITDA −$6.12bn／−5.8pt、CapEx −41.3%。
A37: 差異原因｜FY26｜淨負債 | C37: =IF(ABS(C32)>輸入與假設!$C$150,"觀點","") | D37: =IF(ABS(C32)>輸入與假設!$C$150,"淨負債隨 CapEx 與融資需求而定（模型 CapEx 差距 "&IF((C29)<0,"−","+")&TEXT(ABS((C29))*100,"#,##0.0")&"%"&"）；共識淨負債不含租賃、口徑未揭露","")
A38: 差異原因｜FY27｜EBITDA | C38: =IF(ABS(D26)>輸入與假設!$C$151,"觀點","") -> 觀點 | D38: =IF(ABS(D26)>輸入與假設!$C$151,"EBITDA 率 "&IF((D24)<0,"−","")&TEXT(ABS((D24))*100,"#,##0.0")&"%"&" 對共識 "&IF((D25)<0,"−","")&TEXT(ABS((D25))*100,"#,##0.0")&"%"&"：模型由 "&IF((輸入與假設!$C$32)<0,"−","")&TEXT(ABS((輸入與假設!$C$32))*100,"#,##0")&"%"&" 線性爬升至 FY30 穩態 "&IF((輸入與假設!$C$33)<0,"−","")&TEXT(ABS((輸入與假設!$C$33))*100,"#,##0")&"%"&"；營收差距 "&IF((D19)<0,"−","+")&TEXT(ABS((D19))*100,"#,##0.0")&"%","") -> EBITDA 率 60.5% 對共識 63.2%：模型由 59% 線性爬升至 FY30 穩態 65%；營收差距 −0.9%
A39: 差異原因｜FY27｜CapEx | C39: =IF(ABS(D29)>輸入與假設!$C$150,"觀點","") -> 觀點 | D39: =IF(ABS(D29)>輸入與假設!$C$150,"CapEx 依新增 MW 計算：新增 "&IF((輸入與假設!D$57)<0,"−","")&TEXT(ABS((輸入與假設!D$57)),"#,##0")&" MW × 每 MW $"&IF((輸入與假設!D$49)<0,"−","")&TEXT(ABS((輸入與假設!D$49)),"#,##0")&"m（含次年預建）；共識口徑未揭露","") -> CapEx 依新增 MW 計算：新增 1,250 MW × 每 MW $34m（含次年預建）；共識口徑未揭露
A40: 差異原因｜FY27｜淨負債 | C40: =IF(ABS(D32)>輸入與假設!$C$150,"觀點","") | D40: =IF(ABS(D32)>輸入與假設!$C$150,"淨負債隨 CapEx 與融資需求而定（模型 CapEx 差距 "&IF((D29)<0,"−","+")&TEXT(ABS((D29))*100,"#,##0.0")&"%"&"）；共識淨負債不含租賃、口徑未揭露","")
A41: 差異原因｜FY28｜營收 | C41: =IF(ABS(E19)>輸入與假設!$C$150,"觀點","") -> 觀點 | D41: =IF(ABS(E19)>輸入與假設!$C$150,"營收由模型 MW 路徑決定：FY28 年底 Accepted "&IF((輸入與假設!E$23)<0,"−","")&TEXT(ABS((輸入與假設!E$23)),"#,##0")&" MW（目前情境）；共識未揭露 MW 假設","") -> 營收由模型 MW 路徑決定：FY28 年底 Accepted 4,000 MW（目前情境）；共識未揭露 MW 假設
A42: 差異原因｜FY28｜EBITDA | C42: =IF(ABS(E26)>輸入與假設!$C$151,"觀點","") -> 觀點 | D42: =IF(ABS(E26)>輸入與假設!$C$151,"營收差距 "&IF((E19)<0,"−","+")&TEXT(ABS((E19))*100,"#,##0.0")&"%"&"，加上 EBITDA 率 "&IF((E24)<0,"−","")&TEXT(ABS((E24))*100,"#,##0.0")&"%"&" 對共識 "&IF((E25)<0,"−","")&TEXT(ABS((E25))*100,"#,##0.0")&"%","") -> 營收差距 −13.8%，加上 EBITDA 率 62.0% 對共識 67.8%
A43: 差異原因｜FY28｜CapEx | C43: =IF(ABS(E29)>輸入與假設!$C$150,"觀點","") -> 觀點 | D43: =IF(ABS(E29)>輸入與假設!$C$150,"CapEx 依新增 MW 計算：新增 "&IF((輸入與假設!E$57)<0,"−","")&TEXT(ABS((輸入與假設!E$57)),"#,##0")&" MW × 每 MW $"&IF((輸入與假設!E$49)<0,"−","")&TEXT(ABS((輸入與假設!E$49)),"#,##0")&"m（含次年預建）；共識口徑未揭露","") -> CapEx 依新增 MW 計算：新增 900 MW × 每 MW $34m（含次年預建）；共識口徑未揭露
A44: 差異原因｜FY28｜淨負債 | C44: =IF(ABS(E32)>輸入與假設!$C$150,"觀點","") -> 觀點 | D44: =IF(ABS(E32)>輸入與假設!$C$150,"淨負債隨 CapEx 與融資需求而定（模型 CapEx 差距 "&IF((E29)<0,"−","+")&TEXT(ABS((E29))*100,"#,##0.0")&"%"&"）；共識淨負債不含租賃、口徑未揭露","") -> 淨負債隨 CapEx 與融資需求而定（模型 CapEx 差距 −41.3%）；共識淨負債不含租賃、口徑未揭露
A45: 差異｜需附原因項數 | C45: =SUMPRODUCT(--(ABS(C19:E19)>輸入與假設!$C$150))+SUMPRODUCT(--(ABS(C26:E26)>輸入與假設!$C$151))+SUMPRODUCT(--(ABS(C29:E29)>輸入與假設!$C$150))+SUMPRODUCT(--(ABS(C32:E32)>輸入與假設!$C$150)) -> 6
A46: 差異｜差異原因摘要 | C46: =IF(C45=0,"","需附原因的 "&C45&" 項差距："&MID(IF((COUNTIF(C37,"觀點")+COUNTIF(C38,"觀點")+COUNTIF(C39,"觀點")+COUNTIF(C40,"觀點")+COUNTIF(C41,"觀點")+COUNTIF(C42,"觀點")+COUNTIF(C43,"觀點")+COUNTIF(C44,"觀點"))>0,"、觀點 "&(COUNTIF(C37,"觀點")+COUNTIF(C38,"觀點")+COUNTIF(C39,"觀點")+COUNTIF(C40,"觀點")+COUNTIF(C41,"觀點")+COUNTIF(C42,"觀點")+COUNTIF(C43,"觀點")+COUNTIF(C44,"觀點"))&" 項","")&IF((COUNTIF(C37,"拆法")+COUNTIF(C38,"拆法")+COUNTIF(C39,"拆法")+COUNTIF(C40,"拆法")+COUNTIF(C41,"拆法")+COUNTIF(C42,"拆法")+COUNTIF(C43,"拆法")+COUNTIF(C44,"拆法"))>0,"、拆法 "&(COUNTIF(C37,"拆法")+COUNTIF(C38,"拆法")+COUNTIF(C39,"拆法")+COUNTIF(C40,"拆法")+COUNTIF(C41,"拆法")+COUNTIF(C42,"拆法")+COUNTIF(C43,"拆法")+COUNTIF(C44,"拆法"))&" 項","")&IF((COUNTIF(C37,"已知限制")+COUNTIF(C38,"已知限制")+COUNTIF(C39,"已知限制")+COUNTIF(C40,"已知限制")+COUNTIF(C41,"已知限制")+COUNTIF(C42,"已知限制")+COUNTIF(C43,"已知限制")+COUNTIF(C44,"已知限制"))>0,"、已知限制 "&(COUNTIF(C37,"已知限制")+COUNTIF(C38,"已知限制")+COUNTIF(C39,"已知限制")+COUNTIF(C40,"已知限制")+COUNTIF(C41,"已知限制")+COUNTIF(C42,"已知限制")+COUNTIF(C43,"已知限制")+COUNTIF(C44,"已知限制"))&" 項","")&IF((C45-((COUNTIF(C37,"觀點")+COUNTIF(C38,"觀點")+COUNTIF(C39,"觀點")+COUNTIF(C40,"觀點")+COUNTIF(C41,"觀點")+COUNTIF(C42,"觀點")+COUNTIF(C43,"觀點")+COUNTIF(C44,"觀點"))+(COUNTIF(C37,"拆法")+COUNTIF(C38,"拆法")+COUNTIF(C39,"拆法")+COUNTIF(C40,"拆法")+COUNTIF(C41,"拆法")+COUNTIF(C42,"拆法")+COUNTIF(C43,"拆法")+COUNTIF(C44,"拆法"))+(COUNTIF(C37,"已知限制")+COUNTIF(C38,"已知限制")+COUNTIF(C39,"已知限制")+COUNTIF(C40,"已知限制")+COUNTIF(C41,"已知限制")+COUNTIF(C42,"已知限制")+COUNTIF(C43,"已知限制")+COUNTIF(C44,"已知限制"))))>0,"、未歸類 "&(C45-((COUNTIF(C37,"觀點")+COUNTIF(C38,"觀點")+COUNTIF(C39,"觀點")+COUNTIF(C40,"觀點")+COUNTIF(C41,"觀點")+COUNTIF(C42,"觀點")+COUNTIF(C43,"觀點")+COUNTIF(C44,"觀點"))+(COUNTIF(C37,"拆法")+COUNTIF(C38,"拆法")+COUNTIF(C39,"拆法")+COUNTIF(C40,"拆法")+COUNTIF(C41,"拆法")+COUNTIF(C42,"拆法")+COUNTIF(C43,"拆法")+COUNTIF(C44,"拆法"))+(COUNTIF(C37,"已知限制")+COUNTIF(C38,"已知限制")+COUNTIF(C39,"已知限制")+COUNTIF(C40,"已知限制")+COUNTIF(C41,"已知限制")+COUNTIF(C42,"已知限制")+COUNTIF(C43,"已知限制")+COUNTIF(C44,"已知限制"))))&" 項",""),2,999)&"；原因見「損益與評價 → 市場共識」。") -> 需附原因的 6 項差距：觀點 6 項；原因見「損益與評價 → 市場共識」。
A47: 3｜現價隱含什麼
A48: 隱含｜共識平均目標價隱含 FY28 EV/EBITDA | B48: x | C48: =(輸入與假設!$C$138*輸入與假設!$C$89+輸入與假設!$E$146)/輸入與假設!$E$143 -> 6.1924133
A49: 隱含｜現價隱含 FY28 EV/EBITDA | B49: x | C49: =(輸入與假設!$C$88*輸入與假設!$C$89+輸入與假設!$E$146)/輸入與假設!$E$143 -> 5.1614967
A50: 隱含｜模型方法區間上緣 | B50: x | C50: =MAX(輸入與假設!$C$101,輸入與假設!$C$102) -> 6
A51: 隱含｜隱含倍數句 | C51: ="共識平均目標價 $"&TEXT(輸入與假設!$C$138,"0.00")&" 隱含 FY28 EV/EBITDA "&TEXT(C48,"0.0")&"x，"&IF(ROUND(C48,1)>C50,"高於",IF(ROUND(C48,1)<C50,"低於","等於"))&"模型方法區間上緣 "&IF(C50=INT(C50),TEXT(C50,"0"),TEXT(C50,"0.0"))&"x；現價 $"&TEXT(輸入與假設!$C$88,"0.00")&" 隱含 "&TEXT(C49,"0.0")&"x。" -> 共識平均目標價 $140.81 隱含 FY28 EV/EBITDA 6.2x，高於模型方法區間上緣 6x；現價 $90.13 隱含 5.2x。
A52: 反向 DCF｜FY30 每 MW 年收入（目前／隱含／變動） | C52: =損益與評價!B129 -> 10.5 | D52: =損益與評價!C129 -> 14.0989 | E52: =損益與評價!D129 -> 0.3428
A53: 反向 DCF｜每 MW 建置成本（目前／隱含／變動） | C53: =損益與評價!B130 -> 34 | D53: =損益與評價!C130 -> 20.2994 | E53: =損益與評價!D130 -> -0.403
A54: 反向 DCF｜穩態 EBITDA 率（目前／隱含／變動 pt） | C54: =損益與評價!B131 -> 0.65 | D54: =損益與評價!C131 -> 0.8566 | E54: =損益與評價!D131 -> 0.2066
A55: 反向 DCF｜加權目標價＝現價所需每 MW 年收入（目前／隱含／變動） | C55: =損益與評價!B132 -> 10.5 | D55: =損益與評價!C132 -> 12.3908 | E55: =損益與評價!D132 -> 0.1801
A56: 4｜驗證點與市場看法（賣方與管理層數字標記 Interested-party）
A57: 驗證｜焦點季 | C57: =季度追蹤!C11 -> Q3'26
A58: 驗證｜營收（模型／共識／指引低／指引高／實際） | B58: US$bn | C58: =季度追蹤!C5 -> 3.6626667 | D58: =季度追蹤!D5 -> 3.541 | E58: =季度追蹤!F5 -> 3.45 | F58: =季度追蹤!G5 -> 3.6 | G58: =季度追蹤!I5 -> 待公布
A59: 驗證｜營收｜句 | C59: =INDEX(季度追蹤!$C$137:$H$137,輸入與假設!$C$154) -> 營收：模型 $3.66bn｜共識 $3.54bn（+3.4%）｜指引 $3.45–3.60bn（中點 +3.9%，高於上緣）〔觀點〕
A60: 驗證｜調整後營業利益（模型／共識／指引低／指引高／實際） | B60: US$bn | C60: =季度追蹤!C8 -> -0.013413743 | D60: =季度追蹤!D8 -> 不適用 | E60: =季度追蹤!F8 -> 0.2 | F60: =季度追蹤!G8 -> 0.26 | G60: =季度追蹤!I8 -> 待公布
A61: 驗證｜調整後營業利益｜句 | C61: =INDEX(季度追蹤!$C$140:$H$140,輸入與假設!$C$154) -> 調整後營業利益：模型 −$0.01bn｜指引 $0.20–0.26bn（中點 −$0.24bn／−6.9pt，低於下緣）〔已知限制〕
A62: 驗證｜CapEx（毛額）（模型／共識／指引低／指引高／實際） | B62: US$bn | C62: =季度追蹤!C9 -> 12.5 | D62: =季度追蹤!D9 -> 不適用 | E62: =季度追蹤!F9 -> 11.5 | F62: =季度追蹤!G9 -> 13.5 | G62: =季度追蹤!I9 -> 待公布
A63: 驗證｜CapEx（毛額）｜句 | C63: =INDEX(季度追蹤!$C$141:$H$141,輸入與假設!$C$154) -> CapEx（毛額）：模型 $12.50bn｜指引 $11.50–13.50bn（中點 +0.0%，區間上半部）
A64: 驗證｜目標價（平均／中位數／最低／最高） | B64: US$ | C64: =輸入與假設!$C$138 -> 140.81 | D64: =輸入與假設!$C$139 -> 140 | E64: =輸入與假設!$C$140 -> 39 | F64: =輸入與假設!$C$141 -> 317
A66: 連動檢查 — 恆等式與口徑
A67: 客戶集中：A 36%、B 26%、C 10%（Q2 2026 10-Q）[Verified]
A68: 檢查項目 | B68: 實際值 | C68: 標準 | D68: 結果 | E68: 說明
A69: RPO 桶權重合計 | B69: =SUM(輸入與假設!C22:G22) -> 0.84 | C69: =輸入與假設!$C$16 -> 0.84 | D69: =IF(ABS(B69-C69)<0.0001,"通過","不一致") -> 通過 | E69: 10-Q 桶 41／39／20 線性分攤後應為 84%
A70: 現金橋差異 | B70: =收支與融資!C81 -> -2.5757174e-14 | C70: =0 -> 0 | D70: =IF(ABS(B70)<0.01,"通過","不一致") -> 通過 | E70: 期初＋營運缺口＋股權＋額度−還本 ＝ 期末
A71: FY28 起收入是否依賴未簽約 | B71: =SUM(產能與收入!E18:G18)/SUM(產能與收入!E19:G19) -> 0.40729557 | C71: <50% 較穩健 | D71: =IF(B71<0.5,"通過","觀察") -> 通過 | E71: FY28–30 新簽約收入 ÷ 同期總算力收入。高＝8 GW 敘事的風險集中點

Sheet 輸入與假設
A1: 輸入（依類別排序；點左側 ＋／− 展開或收合。藍字可改；黃底為最關鍵假設）
A2: A 情境 → B 產能與收入 → C 利潤率 → D 支出（CapEx／折舊／租賃／JV）→ E 融資 → F 評價 → G 參考：1H26 實際 → H 情境區間運算表 → I 市場共識 → J 季度追蹤輸入。灰底『▸』為明細子區，預設收合
A4: A｜情境與規模（管理層擴張力道）
A5: 情境選擇（1＝保守 4.2 GW、2＝基準 5.6 GW、3＝積極 8 GW） | C5: 2 | D5: =CHOOSE(C5,"保守 4.2 GW","基準 5.6 GW","積極 8 GW") -> 基準 5.6 GW
A6: 保守 4.2 GW | B6: MW | C6: 1850 | D6: 3100 | E6: 3800 | F6: 4200 | G6: 4200 | I6: 0
A7: 基準 5.6 GW | B7: MW | C7: 1850 | D7: 3100 | E7: 4000 | F7: 4800 | G7: 5600 | I7: 500
A8: 積極 8 GW | B8: MW | C8: 1850 | D8: 3100 | E8: 4600 | F8: 6300 | G8: 8000 | I8: 1000
A9: Billable／Accepted 爬坡比例 | B9: % | C9: 0.91891892 | D9: 0.93548387 | E9: 0.93478261 | F9: 0.93650794 | G9: 0.9375
A10: 表外現金租金（積極路徑） | B10: US$bn | C10: 0.3 | D10: 1.6 | E10: 3 | F10: 4 | G10: 4.6
A11: 表外租金起算 MW | B11: MW | C11: 1500
A12: B｜產能與收入（RPO、MW、利用率、單價、簽約、信用）
A13: 6/30 RPO | B13: US$bn | C13: 103.7
A14: Q3 初新增承諾 | B14: US$bn | C14: 25
A15: 五期認列比例（至 2030 末） | B15: % | C15: 0.84
A16: RPO 桶權重合計 | B16: % | C16: 0.84
A17: 2025-12-31 主動電力 | B17: MW | C17: 850
A18: 6/30 Billable MW | B18: MW | C18: 1350
A19: 收入用平均在役 MW（1=是） | C19: 1
A20: 每 MW 年收入倍數（整體） | B20: % | C20: 1
A21: 模型期長度（年） | C21: 0.5 | D21: 1 | E21: 1 | F21: 1 | G21: 1
A22: RPO 桶權重 | B22: % | C22: 0.1025 | D22: 0.205 | E22: 0.2 | F22: 0.195 | G22: 0.1375 | H22: =SUM(C22:G22) -> 0.84
A23: Accepted MW（期末主動電力） | B23: MW | C23: =CHOOSE(輸入與假設!$C$5,C6,C7,C8) -> 1850 | D23: =CHOOSE(輸入與假設!$C$5,D6,D7,D8) -> 3100 | E23: =CHOOSE(輸入與假設!$C$5,E6,E7,E8) -> 4000 | F23: =CHOOSE(輸入與假設!$C$5,F6,F7,F8) -> 4800 | G23: =CHOOSE(輸入與假設!$C$5,G6,G7,G8) -> 5600
A24: Billable MW | B24: MW | C24: =ROUND(C23*C9,0) -> 1700 | D24: =ROUND(D23*D9,0) -> 2900 | E24: =ROUND(E23*E9,0) -> 3739 | F24: =ROUND(F23*F9,0) -> 4495 | G24: =ROUND(G23*G9,0) -> 5250
A25: 利用率 | B25: % | C25: 0.95 | D25: 0.95 | E25: 0.94 | F25: 0.93 | G25: 0.92
A26: 每 MW 年收入 | B26: US$bn/MW | C26: 0.0112 | D26: 0.0115 | E26: 0.0115 | F26: 0.011 | G26: 0.0105
A27: 新產能簽約率 | B27: % | C27: 1 | D27: 1 | E27: 0.9 | F27: 0.85 | G27: 0.8
A28: 客戶違約率 | B28: % | C28: 0.005 | D28: 0.01 | E28: 0.015 | F28: 0.02 | G28: 0.025
A29: 回收率 | B29: % | C29: 0.5 | D29: 0.5 | E29: 0.5 | F29: 0.5 | G29: 0.5
A30: 非算力服務營收 | B30: US$bn | C30: 0.3 | D30: 1 | E30: 1.8 | F30: 2.8 | G30: 3.8
A31: C｜利潤率（EBITDA 率單一來源；損益與資金共用）
A32: 起始 EBITDA 率（FY26） | B32: % | C32: 0.59
A33: 穩態 EBITDA 率（FY30） | B33: % | C33: 0.65
A34: EBITDA 率 | B34: % | C34: =輸入與假設!$C$32+(輸入與假設!$C$33-輸入與假設!$C$32)*0/4 -> 0.59 | D34: =輸入與假設!$C$32+(輸入與假設!$C$33-輸入與假設!$C$32)*1/4 -> 0.605 | E34: =輸入與假設!$C$32+(輸入與假設!$C$33-輸入與假設!$C$32)*2/4 -> 0.62 | F34: =輸入與假設!$C$32+(輸入與假設!$C$33-輸入與假設!$C$32)*3/4 -> 0.635 | G34: =輸入與假設!$C$32+(輸入與假設!$C$33-輸入與假設!$C$32)*4/4 -> 0.65
A35: 非算力服務現金 | B35: US$bn | C35: =輸入與假設!C$30*產能與收入!C24 -> 0.22478319 | D35: =輸入與假設!D$30*產能與收入!D24 -> 0.75576069 | E35: =輸入與假設!E$30*產能與收入!E24 -> 1.3479546 | F35: =輸入與假設!F$30*產能與收入!F24 -> 2.1166 | G35: =輸入與假設!G$30*產能與收入!G24 -> 2.9083713
A36: 電力／維護 overlay（1=開） | C36: 0
A37: 電價 | B37: $/MWh | C37: 60 | D37: 62 | E37: 64 | F37: 66 | G37: 68
A38: PUE | C38: 1.25 | D38: 1.24 | E38: 1.22 | F38: 1.2 | G38: 1.2
A39: 維護成本 | B39: US$m/MW | C39: 0.15 | D39: 0.15 | E39: 0.16 | F39: 0.16 | G39: 0.17
A40: D｜支出（CapEx、車隊折舊、租賃、JV）
A41: 提前支出比例 λ | B41: % | C41: 0.35
A42: FY31 新增 MW（FY30 預建用） | B42: MW | C42: =CHOOSE(輸入與假設!$C$5,I6,I7,I8) -> 500
A43: FY26 CapEx 下限（已承諾） | B43: US$bn | C43: 35
A44: GPU 經濟壽命（年） | B44: 年 | C44: 6
A45: 2023 年底主動電力 | B45: MW | C45: 100
A46: 2024 年底主動電力 | B46: MW | C46: 360
A47: 6/30 毛 PP&E | B47: US$bn | C47: 46.736
A48: 每 MW 建置成本倍數（整體） | B48: % | C48: 1
A49: 每 MW 建置成本 | B49: US$m/MW | C49: 34 | D49: 34 | E49: 34 | F49: 34 | G49: 34
A50: 客戶預付占毛 CapEx | B50: % | C50: 0.08 | D50: 0.08 | E50: 0.08 | F50: 0.08 | G50: 0.08
A51: 在帳現金租金（10-Q 到期表） | B51: US$bn | C51: 1.04 | D51: 2.339 | E51: 2.306 | F51: 2.373 | G51: 2.289
A52: 表外現金租金（未起租） | B52: US$bn | C52: =C10*MAX(0,C23-輸入與假設!$C$11)/(C8-輸入與假設!$C$11) -> 0.3 | D52: =D10*MAX(0,D23-輸入與假設!$C$11)/(D8-輸入與假設!$C$11) -> 1.6 | E52: =E10*MAX(0,E23-輸入與假設!$C$11)/(E8-輸入與假設!$C$11) -> 2.4193548 | F52: =F10*MAX(0,F23-輸入與假設!$C$11)/(F8-輸入與假設!$C$11) -> 2.75 | G52: =G10*MAX(0,G23-輸入與假設!$C$11)/(G8-輸入與假設!$C$11) -> 2.9015385
A53: JV 已承諾餘額出資 | B53: US$bn | C53: 1.15 | D53: 0 | E53: 0 | F53: 0 | G53: 0
A54: JV 後續增資＋策略投資 | B54: US$bn | C54: 0.1 | D54: 0.4 | E54: 0.3 | F54: 0.2 | G54: 0.2
A55: JV／策略投資出資 | B55: US$bn | C55: =C53+C54 -> 1.25 | D55: =D53+D54 -> 0.4 | E55: =E53+E54 -> 0.3 | F55: =F53+F54 -> 0.2 | G55: =G53+G54 -> 0.2
A56: 期初主動電力 | B56: MW | C56: =輸入與假設!$C$17 -> 850 | D56: =C23 -> 1850 | E56: =D23 -> 3100 | F56: =E23 -> 4000 | G56: =F23 -> 4800
A57: 本期新增 MW | B57: MW | C57: =C23-C56 -> 1000 | D57: =D23-D56 -> 1250 | E57: =E23-E56 -> 900 | F57: =F23-F56 -> 800 | G57: =G23-G56 -> 800
A58: 次期新增 MW | B58: MW | C58: =D23-C23 -> 1250 | D58: =E23-D23 -> 900 | E58: =F23-E23 -> 800 | F58: =G23-F23 -> 800 | G58: =輸入與假設!$C$42 -> 500
A59: 全年毛 CapEx（公式） | B59: US$bn | C59: =(C57*(1-輸入與假設!$C$41)+C58*輸入與假設!$C$41)*C49*輸入與假設!$C$48/1000 -> 36.975 | D59: =(D57*(1-輸入與假設!$C$41)+D58*輸入與假設!$C$41)*D49*輸入與假設!$C$48/1000 -> 38.335 | E59: =(E57*(1-輸入與假設!$C$41)+E58*輸入與假設!$C$41)*E49*輸入與假設!$C$48/1000 -> 29.41 | F59: =(F57*(1-輸入與假設!$C$41)+F58*輸入與假設!$C$41)*F49*輸入與假設!$C$48/1000 -> 27.2 | G59: =(G57*(1-輸入與假設!$C$41)+G58*輸入與假設!$C$41)*G49*輸入與假設!$C$48/1000 -> 23.63
A60: 成長型 CapEx（模型期） | B60: US$bn | C60: =MAX(C59,輸入與假設!$C$43)-輸入與假設!$C$122 -> 20.836 | D60: =D59 -> 38.335 | E60: =E59 -> 29.41 | F60: =F59 -> 27.2 | G60: =G59 -> 23.63
A61: GPU 汰換 CapEx | B61: US$bn | C61: =IF(2026-輸入與假設!$C$44=2023,輸入與假設!$C$45,IF(2026-輸入與假設!$C$44=2024,輸入與假設!$C$46-輸入與假設!$C$45,IF(2026-輸入與假設!$C$44=2025,輸入與假設!$C$17-輸入與假設!$C$46,0)))*C49*輸入與假設!$C$48/1000 -> 0 | D61: =IF(2027-輸入與假設!$C$44=2023,輸入與假設!$C$45,IF(2027-輸入與假設!$C$44=2024,輸入與假設!$C$46-輸入與假設!$C$45,IF(2027-輸入與假設!$C$44=2025,輸入與假設!$C$17-輸入與假設!$C$46,0)))*D49*輸入與假設!$C$48/1000 -> 0 | E61: =IF(2028-輸入與假設!$C$44=2023,輸入與假設!$C$45,IF(2028-輸入與假設!$C$44=2024,輸入與假設!$C$46-輸入與假設!$C$45,IF(2028-輸入與假設!$C$44=2025,輸入與假設!$C$17-輸入與假設!$C$46,0)))*E49*輸入與假設!$C$48/1000 -> 0 | F61: =IF(2029-輸入與假設!$C$44=2023,輸入與假設!$C$45,IF(2029-輸入與假設!$C$44=2024,輸入與假設!$C$46-輸入與假設!$C$45,IF(2029-輸入與假設!$C$44=2025,輸入與假設!$C$17-輸入與假設!$C$46,0)))*F49*輸入與假設!$C$48/1000 -> 3.4 | G61: =IF(2030-輸入與假設!$C$44=2023,輸入與假設!$C$45,IF(2030-輸入與假設!$C$44=2024,輸入與假設!$C$46-輸入與假設!$C$45,IF(2030-輸入與假設!$C$44=2025,輸入與假設!$C$17-輸入與假設!$C$46,0)))*G49*輸入與假設!$C$48/1000 -> 8.84
A62: 期初毛 PP&E | B62: US$bn | C62: =輸入與假設!$C$47 -> 46.736 | D62: =C62+C60 -> 67.572 | E62: =D62+D60 -> 105.907 | F62: =E62+E60 -> 135.317 | G62: =F62+F60 -> 162.517
A63: 毛 CapEx（模型期，下游引用此列） | B63: US$bn | C63: =C60+C61 -> 20.836 | D63: =D60+D61 -> 38.335 | E63: =E60+E61 -> 29.41 | F63: =F60+F61 -> 30.6 | G63: =G60+G61 -> 32.47
A64: D&A（車隊折舊） | B64: US$bn | C64: =(C62+0.5*C60)/輸入與假設!$C$44*C21 -> 4.7628333 | D64: =(D62+0.5*D60)/輸入與假設!$C$44*D21 -> 14.456583 | E64: =(E62+0.5*E60)/輸入與假設!$C$44*E21 -> 20.102 | F64: =(F62+0.5*F60)/輸入與假設!$C$44*F21 -> 24.8195 | G64: =(G62+0.5*G60)/輸入與假設!$C$44*G21 -> 29.055333
A65: E｜融資（期初現金、既有債務、瀑布參數）
A66: 期初現金（2026-06-30） | B66: US$bn | C66: 5.5
A67: 股權／可轉債金額 | B67: US$bn | C67: 6.2
A68: 計入股權／可轉債（1=是） | C68: 1
A69: 未動用信用額度 | B69: US$bn | C69: 10
A70: 瀑布可動用未動用額度（1=是） | C70: 1
A71: 債務排程攤還（1=開） | C71: 1
A72: 債務／backlog 上限 | B72: x | C72: 1
A73: 新簽合約年期 | B73: 年 | C73: 5
A74: 最低現金 | B74: US$bn | C74: 2
A75: 股權發行價 | B75: US$ | C75: 90.13
A76: 股權發行折價 | B76: % | C76: 0.1
A77: 每年股權吸收上限（占現市值） | B77: % | C77: 0.2
A78: 股權上限的股數基礎 | B78: bn | C78: 0.5865
A79: 高息債利率（股權上限溢出） | B79: % | C79: 0.12
A80: CDS 中價 | B80: bps | C80: 720
A81: CDS 傳入新債利率（1=開） | C81: 0
A82: CDS 傳入門檻 | B82: bps | C82: 450
A83: CDS 傳入比例 | B83: % | C83: 0.4
A84: 排程還本（10-Q 本金表） | B84: US$bn | C84: 4.413 | D84: 6.184 | E84: 4.416 | F84: 2.421 | G84: 3.221
A85: 新債利率 | B85: % | C85: 0.09 | D85: 0.09 | E85: 0.09 | F85: 0.09 | G85: 0.09
A86: 存量債務利息（下游引用此列） | B86: US$bn | C86: =收支與融資!C115 -> 1.8058963 | D86: =收支與融資!D115 -> 2.4660068 | E86: =收支與融資!E115 -> 2.0200947 | F86: =收支與融資!F115 -> 1.7324815 | G86: =收支與融資!G115 -> 1.4951385
A87: F｜評價（價格、股數、折現、倍數、權重）
A88: 現價（2026-09-24 收盤） | B88: US$ | C88: 90.13
A89: 股數（含 ATM 上限） | B89: bn | C89: 0.587
A90: 淨負債（6/30） | B90: US$bn | C90: 30
A91: WACC | B91: % | C91: 0.11
A92: 永續成長 g | B92: % | C92: 0.03
A93: 終值維持性 CapEx 占 D&A | B93: % | C93: 0.8
A94: 稅率 | B94: % | C94: 0.21
A95: 期初 NOL（虧損扣抵） | B95: US$bn | C95: 4
A96: NOL 每年可抵用比例 | B96: % | C96: 0.8
A97: 營運資金占營收增量 | B97: % | C97: 0.02
A98: EV/EBITDA 倍數 | B98: x | C98: 6
A99: EV/EBITDA 錨定年度（1＝FY27、2＝FY28、3＝FY29、4＝FY30） | C99: 3
A100: 權重：DCF | B100: % | C100: 0.45
A101: 方法區間倍數：下端 | B101: x | C101: 5
...

Sheet 收支與融資
A1: 支出與資金 — 五層支出、四層來源、現金橋
A2: FY26 欄＝1H 實際（10-Q 現金流量表口徑）＋下半年模型；FY27 以後為純模型。瀑布以「融資前現金」決定需求並直接由各支出列加總，因此沒有循環參照
A4: 項目 | B4: 單位 | C4: FY26 | D4: FY27 | E4: FY28 | F4: FY29 | G4: FY30
A5: 支出（五層）
A6: 客戶預付率 | B6: % | C6: =輸入與假設!C$50 -> 0.08 | D6: =輸入與假設!D$50 -> 0.08 | E6: =輸入與假設!E$50 -> 0.08 | F6: =輸入與假設!F$50 -> 0.08 | G6: =輸入與假設!G$50 -> 0.08
A7: 客戶預付金額（抵減，2H 起） | B7: US$bn | C7: =輸入與假設!C$63*C6 -> 1.66688 | D7: =輸入與假設!D$63*D6 -> 3.0668 | E7: =輸入與假設!E$63*E6 -> 2.3528 | F7: =輸入與假設!F$63*F6 -> 2.448 | G7: =輸入與假設!G$63*G6 -> 2.5976
A8: ① CapEx（用途用：1H 現金／2H 毛額） | B8: US$bn | C8: =輸入與假設!$C$121+輸入與假設!C$63 -> 34.953 | D8: =輸入與假設!D$63 -> 38.335 | E8: =輸入與假設!E$63 -> 29.41 | F8: =輸入與假設!F$63 -> 30.6 | G8: =輸入與假設!G$63 -> 32.47
A9: ② 在帳現金租金（備忘，1H 已含在 CFO） | B9: US$bn | C9: =輸入與假設!C$51 -> 1.04 | D9: =輸入與假設!D$51 -> 2.339 | E9: =輸入與假設!E$51 -> 2.306 | F9: =輸入與假設!F$51 -> 2.373 | G9: =輸入與假設!G$51 -> 2.289
A10: ② 表外現金租金（未起租） | B10: US$bn | C10: =輸入與假設!C$52 -> 0.3 | D10: =輸入與假設!D$52 -> 1.6 | E10: =輸入與假設!E$52 -> 2.4193548 | F10: =輸入與假設!F$52 -> 2.75 | G10: =輸入與假設!G$52 -> 2.9015385
A11: 租金合計 | B11: US$bn | C11: =C9+C10 -> 1.34 | D11: =D9+D10 -> 3.939 | E11: =E9+E10 -> 4.7253548 | F11: =F9+F10 -> 5.123 | G11: =G9+G10 -> 5.1905385
A12: ③ 存量債務利息（備忘，1H 已含在 CFO） | B12: US$bn | C12: =輸入與假設!C$86 -> 1.8058963 | D12: =輸入與假設!D$86 -> 2.4660068 | E12: =輸入與假設!E$86 -> 2.0200947 | F12: =輸入與假設!F$86 -> 1.7324815 | G12: =輸入與假設!G$86 -> 1.4951385 | I12: ="6/30 債務餘額的利息。FY26 全年利息＝1H 實際 1.176＋2H "&TEXT(C12,"0.0")&"＝"&TEXT(1.176+C12,"0.00")&"（見下方備忘）" -> 6/30 債務餘額的利息。FY26 全年利息＝1H 實際 1.176＋2H 1.8＝2.98（見下方備忘）
A13: 期初累積現金 | B13: US$bn | C13: =輸入與假設!$C$119 -> 3.127 | D13: =C40 -> 2 | E13: =D40 -> 2 | F13: =E40 -> 2 | G13: =F40 -> 2
A14: 新債利率 | B14: % | C14: =IF(輸入與假設!$C$81=1,輸入與假設!C$85+MAX(0,輸入與假設!$C$80-450)/100*0.004,輸入與假設!C$85) -> 0.09 | D14: =IF(輸入與假設!$C$81=1,輸入與假設!D$85+MAX(0,輸入與假設!$C$80-450)/100*0.004,輸入與假設!D$85) -> 0.09 | E14: =IF(輸入與假設!$C$81=1,輸入與假設!E$85+MAX(0,輸入與假設!$C$80-450)/100*0.004,輸入與假設!E$85) -> 0.09 | F14: =IF(輸入與假設!$C$81=1,輸入與假設!F$85+MAX(0,輸入與假設!$C$80-450)/100*0.004,輸入與假設!F$85) -> 0.09 | G14: =IF(輸入與假設!$C$81=1,輸入與假設!G$85+MAX(0,輸入與假設!$C$80-450)/100*0.004,輸入與假設!G$85) -> 0.09
A15: ③ 新債利息（瀑布） | B15: US$bn | C15: =C61 -> 0.56495231 | D15: =D61 -> 4.0708204 | E15: =E61 -> 5.5864719 | F15: =F61 -> 5.8690106 | G15: =G61 -> 6.515096
A16: 利息合計 | B16: US$bn | C16: =C12+C15 -> 2.3708486 | D16: =D12+D15 -> 6.5368271 | E16: =E12+E15 -> 7.6065666 | F16: =F12+F15 -> 7.6014921 | G16: =G12+G15 -> 8.0102346
A17: ④ JV／策略投資出資 | B17: US$bn | C17: =輸入與假設!$C$123+輸入與假設!C$55 -> 1.938 | D17: =輸入與假設!D$55 -> 0.4 | E17: =輸入與假設!E$55 -> 0.3 | F17: =輸入與假設!F$55 -> 0.2 | G17: =輸入與假設!G$55 -> 0.2
A18: 電力（overlay） | B18: US$bn | C18: =IF(輸入與假設!$C$36=1,產能與收入!C7*8760*輸入與假設!C$38*輸入與假設!C$37/1000000000*產能與收入!C5,0) -> 0 | D18: =IF(輸入與假設!$C$36=1,產能與收入!D7*8760*輸入與假設!D$38*輸入與假設!D$37/1000000000*產能與收入!D5,0) -> 0 | E18: =IF(輸入與假設!$C$36=1,產能與收入!E7*8760*輸入與假設!E$38*輸入與假設!E$37/1000000000*產能與收入!E5,0) -> 0 | F18: =IF(輸入與假設!$C$36=1,產能與收入!F7*8760*輸入與假設!F$38*輸入與假設!F$37/1000000000*產能與收入!F5,0) -> 0 | G18: =IF(輸入與假設!$C$36=1,產能與收入!G7*8760*輸入與假設!G$38*輸入與假設!G$37/1000000000*產能與收入!G5,0) -> 0
A19: 維護（overlay） | B19: US$bn | C19: =IF(輸入與假設!$C$36=1,產能與收入!C7*輸入與假設!C$39/1000*產能與收入!C5,0) -> 0 | D19: =IF(輸入與假設!$C$36=1,產能與收入!D7*輸入與假設!D$39/1000*產能與收入!D5,0) -> 0 | E19: =IF(輸入與假設!$C$36=1,產能與收入!E7*輸入與假設!E$39/1000*產能與收入!E5,0) -> 0 | F19: =IF(輸入與假設!$C$36=1,產能與收入!F7*輸入與假設!F$39/1000*產能與收入!F5,0) -> 0 | G19: =IF(輸入與假設!$C$36=1,產能與收入!G7*輸入與假設!G$39/1000*產能與收入!G5,0) -> 0
A20: ⑤ 排程還本（10-Q 本金表） | B20: US$bn | C20: =輸入與假設!$C$125+IF(輸入與假設!$C$71=1,輸入與假設!C$84,0) -> 9.632 | D20: =IF(輸入與假設!$C$71=1,輸入與假設!D$84,0) -> 6.184 | E20: =IF(輸入與假設!$C$71=1,輸入與假設!E$84,0) -> 4.416 | F20: =IF(輸入與假設!$C$71=1,輸入與假設!F$84,0) -> 2.421 | G20: =IF(輸入與假設!$C$71=1,輸入與假設!G$84,0) -> 3.221
A21: ⑥ capped call 支出（1H 實際） | B21: US$bn | C21: =輸入與假設!$C$126 -> 0.492 | D21: =0 -> 0 | E21: =0 -> 0 | F21: =0 -> 0 | G21: =0 -> 0
A22: 用途合計（現金口徑） | B22: US$bn | C22: =C8+C11+C16+C17+C18+C19+C20+C21 -> 50.725849 | D22: =D8+D11+D16+D17+D18+D19+D20+D21 -> 55.394827 | E22: =E8+E11+E16+E17+E18+E19+E20+E21 -> 46.457921 | F22: =F8+F11+F16+F17+F18+F19+F20+F21 -> 45.945492 | G22: =G8+G11+G16+G17+G18+G19+G20+G21 -> 49.091773
A23: 來源（四層）
A24: Ⓐ0 1H26 實際營運現金流（CFO） | B24: US$bn | C24: =輸入與假設!$C$120 -> 3.663 | D24: =0 -> 0 | E24: =0 -> 0 | F24: =0 -> 0 | G24: =0 -> 0
A25: Ⓐ RPO 現金（2H 起） | B25: US$bn | C25: =產能與收入!C25 -> 6.0636896 | D25: =產能與收入!D25 -> 18.895425 | E25: =產能與收入!E25 -> 19.131182 | F25: =產能與收入!F25 -> 18.78145 | G25: =產能與收入!G25 -> 13.374717
A26: Ⓑ 新簽約現金 | B26: US$bn | C26: =產能與收入!C26 -> 0 | D26: =產能與收入!D26 -> 0 | E26: =產能與收入!E26 -> 6.7854123 | F26: =產能與收入!F26 -> 10.826919 | G26: =產能與收入!G26 -> 17.759402
A27: Ⓒ 非算力服務現金 | B27: US$bn | C27: =輸入與假設!C$35 -> 0.22478319 | D27: =輸入與假設!D$35 -> 0.75576069 | E27: =輸入與假設!E$35 -> 1.3479546 | F27: =輸入與假設!F$35 -> 2.1166 | G27: =輸入與假設!G$35 -> 2.9083713
A28: Ⓓ 客戶預付（2H 起） | B28: US$bn | C28: =C7 -> 1.66688 | D28: =D7 -> 3.0668 | E28: =E7 -> 2.3528 | F28: =F7 -> 2.448 | G28: =G7 -> 2.5976
A29: 營運來源合計 | B29: US$bn | C29: =C24+C25+C26+C27+C28 -> 11.618353 | D29: =D24+D25+D26+D27+D28 -> 22.717986 | E29: =E24+E25+E26+E27+E28 -> 29.617349 | F29: =F24+F25+F26+F27+F28 -> 34.172969 | G29: =G24+G25+G26+G27+G28 -> 36.64009
A30: Ⓔ 股權／可轉債（融資） | B30: US$bn | C30: =輸入與假設!$C$127+IF(輸入與假設!$C$68=1,輸入與假設!$C$67,0) -> 9.182 | D30: =0 -> 0 | E30: =0 -> 0 | F30: =0 -> 0 | G30: =0 -> 0
A31: Ⓕ 1H26 實際借款（融資） | B31: US$bn | C31: =輸入與假設!$C$124 -> 16.747 | D31: =0 -> 0 | E31: =0 -> 0 | F31: =0 -> 0 | G31: =0 -> 0
A32: Ⓖ 瀑布：新債（額度＋資產層） | B32: US$bn | C32: =C56 -> 12.554496 | D32: =D56 -> 32.676842 | E32: =E56 -> 16.840572 | F32: =F56 -> 3.1393189 | G32: =G56 -> 7.1787275
A33: Ⓗ 瀑布：股權募資 | B33: US$bn | C33: =C59 -> 0 | D33: =D59 -> 0 | E33: =E59 -> 0 | F33: =F59 -> 8.6332038 | G33: =G59 -> 5.2729553
A34: Ⓘ 瀑布：高息債（股權上限溢出） | B34: US$bn | C34: =C60 -> 0 | D34: =D60 -> 0 | E34: =E60 -> 0 | F34: =F60 -> 0 | G34: =G60 -> 0
A35: 總來源（含融資） | B35: US$bn | C35: =C29+C30+C31+C32+C33+C34 -> 50.101849 | D35: =D29+D30+D31+D32+D33+D34 -> 55.394827 | E35: =E29+E30+E31+E32+E33+E34 -> 46.457921 | F35: =F29+F30+F31+F32+F33+F34 -> 45.945492 | G35: =G29+G30+G31+G32+G33+G34 -> 49.091773
A36: 缺口與現金橋
A37: 1H 其他／受限現金調節 | B37: US$bn | C37: =輸入與假設!$C$66-(輸入與假設!$C$119+輸入與假設!$C$120+輸入與假設!$C$124+輸入與假設!$C$127-輸入與假設!$C$121-輸入與假設!$C$123-輸入與假設!$C$125-輸入與假設!$C$126) -> -0.503 | D37: =0 -> 0 | E37: =0 -> 0 | F37: =0 -> 0 | G37: =0 -> 0
A38: 營運缺口（不含融資、不含還本） | B38: US$bn | C38: =C29-(C22-C20-C21) -> -28.983496 | D38: =D29-(D22-D20-D21) -> -26.492842 | E38: =E29-(E22-E20-E21) -> -12.424572 | F38: =F29-(F22-F20-F21) -> -9.3515227 | G38: =G29-(G22-G20-G21) -> -9.2306828
A39: 期間缺口（含融資） | B39: US$bn | C39: =C35-C22+C37 -> -1.127 | D39: =D35-D22+D37 -> 0 | E39: =E35-E22+E37 -> 0 | F39: =F35-F22+F37 -> 0 | G39: =G35-G22+G37 -> 0
A40: 期末累積現金 | B40: US$bn | C40: =C13+C39 -> 2 | D40: =D13+D39 -> 2 | E40: =E13+E39 -> 2 | F40: =F13+F39 -> 2 | G40: =G13+G39 -> 2
A41: 期前融資瀑布（缺口在需要前一期先融好：額度 → 資產層新債 → 股權）
A42: 用途（不含新債利息） | B42: US$bn | C42: =C8+C11+C12+C17+C18+C19+C20+C21 -> 50.160896 | D42: =D8+D11+D12+D17+D18+D19+D20+D21 -> 51.324007 | E42: =E8+E11+E12+E17+E18+E19+E20+E21 -> 40.87145 | F42: =F8+F11+F12+F17+F18+F19+F20+F21 -> 40.076481 | G42: =G8+G11+G12+G17+G18+G19+G20+G21 -> 42.576677
A43: 新債期初餘額 | B43: US$bn | C43: =0 -> 0 | D43: =C65 -> 12.554496 | E43: =D65 -> 45.231337 | F43: =E65 -> 62.07191 | G43: =F65 -> 65.211229
A44: 新債利率 × 期間長度 | B44: % | C44: =C14*產能與收入!C5 -> 0.045 | D44: =D14*產能與收入!D5 -> 0.09 | E44: =E14*產能與收入!E5 -> 0.09 | F44: =F14*產能與收入!F5 -> 0.09 | G44: =G14*產能與收入!G5 -> 0.09
A45: 高息債期初餘額 | B45: US$bn | C45: =0 -> 0 | D45: =C67 -> 0 | E45: =D67 -> 0 | F45: =E67 -> 0 | G45: =F67 -> 0
A46: 高息債利率 × 期間長度 | B46: % | C46: =(輸入與假設!$C$79+IF(輸入與假設!$C$81=1,MAX(0,輸入與假設!$C$80-輸入與假設!$C$82)/10000*輸入與假設!$C$83,0))*產能與收入!C5 -> 0.06 | D46: =(輸入與假設!$C$79+IF(輸入與假設!$C$81=1,MAX(0,輸入與假設!$C$80-輸入與假設!$C$82)/10000*輸入與假設!$C$83,0))*產能與收入!D5 -> 0.12 | E46: =(輸入與假設!$C$79+IF(輸入與假設!$C$81=1,MAX(0,輸入與假設!$C$80-輸入與假設!$C$82)/10000*輸入與假設!$C$83,0))*產能與收入!E5 -> 0.12 | F46: =(輸入與假設!$C$79+IF(輸入與假設!$C$81=1,MAX(0,輸入與假設!$C$80-輸入與假設!$C$82)/10000*輸入與假設!$C$83,0))*產能與收入!F5 -> 0.12 | G46: =(輸入與假設!$C$79+IF(輸入與假設!$C$81=1,MAX(0,輸入與假設!$C$80-輸入與假設!$C$82)/10000*輸入與假設!$C$83,0))*產能與收入!G5 -> 0.12
A47: 融資前現金（扣既有新債利息） | B47: US$bn | C47: =C13+C29+C30+C31+C37-C42-C44*C43-C46*C45 -> -9.9895435 | D47: =D13+D29+D30+D31+D37-D42-D44*D43-D46*D45 -> -27.735926 | E47: =E13+E29+E30+E31+E37-E42-E44*E43-E46*E45 -> -13.324921 | F47: =F13+F29+F30+F31+F37-F42-F44*F43-F46*F45 -> -9.489984 | G47: =G13+G29+G30+G31+G37-G42-G44*G43-G46*G45 -> -9.8055974
A48: 融資需求（補足至最低現金） | B48: US$bn | C48: =MAX(0,輸入與假設!$C$74-C47) -> 11.989544 | D48: =MAX(0,輸入與假設!$C$74-D47) -> 29.735926 | E48: =MAX(0,輸入與假設!$C$74-E47) -> 15.324921 | F48: =MAX(0,輸入與假設!$C$74-F47) -> 11.489984 | G48: =MAX(0,輸入與假設!$C$74-G47) -> 11.805597
A49: 期初 backlog | B49: US$bn | C49: =輸入與假設!$C$13+輸入與假設!$C$14 -> 128.7 | D49: =C51 -> 115.50825 | E49: =D51 -> 89.12475 | F49: =E51 -> 99.902412 | G49: =F51 -> 87.028228
A50: 新簽合約增量（年化增量×年期） | B50: US$bn | C50: =MAX(0,產能與收入!C18/產能與收入!C5-0)*輸入與假設!$C$73 -> 0 | D50: =MAX(0,產能與收入!D18/產能與收入!D5-產能與收入!C18/產能與收入!C5)*輸入與假設!$C$73 -> 0 | E50: =MAX(0,產能與收入!E18/產能與收入!E5-產能與收入!D18/產能與收入!D5)*輸入與假設!$C$73 -> 45.647078 | F50: =MAX(0,產能與收入!F18/產能與收入!F5-產能與收入!E18/產能與收入!E5)*輸入與假設!$C$73 -> 26.689665 | G50: =MAX(0,產能與收入!G18/產能與收入!G5-產能與收入!F18/產能與收入!F5)*輸入與假設!$C$73 -> 45.151657
A51: 期末 backlog | B51: US$bn | C51: =C49-產能與收入!C13-產能與收入!C18+C50 -> 115.50825 | D51: =D49-產能與收入!D13-產能與收入!D18+D50 -> 89.12475 | E51: =E49-產能與收入!E13-產能與收入!E18+E50 -> 99.902412 | F51: =F49-產能與收入!F13-產能與收入!F18+F50 -> 87.028228 | G51: =G49-產能與收入!G13-產能與收入!G18+G50 -> 90.985956
A52: 既有債務＋9/17 可轉債（期末） | B52: US$bn | C52: =IF(輸入與假設!$C$71=1,收支與融資!C110,35.551)+3.7 -> 34.838 | D52: =IF(輸入與假設!$C$71=1,收支與融資!D110,35.551)+3.7 -> 28.654 | E52: =IF(輸入與假設!$C$71=1,收支與融資!E110,35.551)+3.7 -> 24.238 | F52: =IF(輸入與假設!$C$71=1,收支與融資!F110,35.551)+3.7 -> 21.817 | G52: =IF(輸入與假設!$C$71=1,收支與融資!G110,35.551)+3.7 -> 18.596
A53: 債務上限（債務／backlog × 期末 backlog） | B53: US$bn | C53: =輸入與假設!$C$72*C51 -> 115.50825 | D53: =輸入與假設!$C$72*D51 -> 89.12475 | E53: =輸入與假設!$C$72*E51 -> 99.902412 | F53: =輸入與假設!$C$72*F51 -> 87.028228 | G53: =輸入與假設!$C$72*G51 -> 90.985956
A54: 未動用額度（期初） | B54: US$bn | C54: =IF(輸入與假設!$C$70=1,輸入與假設!$C$69,0) -> 10 | D54: =C66 -> 0 | E54: =D66 -> 0 | F54: =E66 -> 0 | G54: =F66 -> 0
A55: 新債可借上限 | B55: US$bn | C55: =MAX(0,C53-(C52+C43),C54) -> 80.67025 | D55: =MAX(0,D53-(D52+D43),D54) -> 47.916254 | E55: =MAX(0,E53-(E52+E43),E54) -> 30.433075 | F55: =MAX(0,F53-(F52+F43),F54) -> 3.1393189 | G55: =MAX(0,G53-(G52+G43),G54) -> 7.1787275
A56: 新債舉借 | B56: US$bn | C56: =MIN(C55,C48/(1-C44)) -> 12.554496 | D56: =MIN(D55,D48/(1-D44)) -> 32.676842 | E56: =MIN(E55,E48/(1-E44)) -> 16.840572 | F56: =MIN(F55,F48/(1-F44)) -> 3.1393189 | G56: =MIN(G55,G48/(1-G44)) -> 7.1787275
A57: 債務後剩餘需求 | B57: US$bn | C57: =MAX(0,C48+C44*C56-C56) -> 0 | D57: =MAX(0,D48+D44*D56-D56) -> 0 | E57: =MAX(0,E48+E44*E56-E56) -> 0 | F57: =MAX(0,F48+F44*F56-F56) -> 8.6332038 | G57: =MAX(0,G48+G44*G56-G56) -> 5.2729553
A58: 每年股權吸收上限 | B58: US$bn | C58: =IF(輸入與假設!$C$77>=9,1E+099,輸入與假設!$C$77*輸入與假設!$C$75*輸入與假設!$C$78*產能與收入!C5) -> 5.2861245 | D58: =IF(輸入與假設!$C$77>=9,1E+099,輸入與假設!$C$77*輸入與假設!$C$75*輸入與假設!$C$78*產能與收入!D5) -> 10.572249 | E58: =IF(輸入與假設!$C$77>=9,1E+099,輸入與假設!$C$77*輸入與假設!$C$75*輸入與假設!$C$78*產能與收入!E5) -> 10.572249 | F58: =IF(輸入與假設!$C$77>=9,1E+099,輸入與假設!$C$77*輸入與假設!$C$75*輸入與假設!$C$78*產能與收入!F5) -> 10.572249 | G58: =IF(輸入與假設!$C$77>=9,1E+099,輸入與假設!$C$77*輸入與假設!$C$75*輸入與假設!$C$78*產能與收入!G5) -> 10.572249
A59: 股權募資 | B59: US$bn | C59: =MIN(C57,C58) -> 0 | D59: =MIN(D57,D58) -> 0 | E59: =MIN(E57,E58) -> 0 | F59: =MIN(F57,F58) -> 8.6332038 | G59: =MIN(G57,G58) -> 5.2729553
A60: 高息債舉借（溢出） | B60: US$bn | C60: =(C57-C59)/(1-C46) -> 0 | D60: =(D57-D59)/(1-D46) -> 0 | E60: =(E57-E59)/(1-E46) -> 0 | F60: =(F57-F59)/(1-F46) -> 0 | G60: =(G57-G59)/(1-G46) -> 0
A61: 新債＋高息債利息（期初餘額＋本期舉借） | B61: US$bn | C61: =C44*(C43+C56)+C46*(C45+C60) -> 0.56495231 | D61: =D44*(D43+D56)+D46*(D45+D60) -> 4.0708204 | E61: =E44*(E43+E56)+E46*(E45+E60) -> 5.5864719 | F61: =F44*(F43+F56)+F46*(F45+F60) -> 5.8690106 | G61: =G44*(G43+G56)+G46*(G45+G60) -> 6.515096
A62: 發行價（現價×(1−折價)） | B62: US$ | C62: =輸入與假設!$C$75*(1-輸入與假設!$C$76) -> 81.117 | D62: =輸入與假設!$C$75*(1-輸入與假設!$C$76) -> 81.117 | E62: =輸入與假設!$C$75*(1-輸入與假設!$C$76) -> 81.117 | F62: =輸入與假設!$C$75*(1-輸入與假設!$C$76) -> 81.117 | G62: =輸入與假設!$C$75*(1-輸入與假設!$C$76) -> 81.117
A63: 新發行股數 | B63: bn | C63: =C59/C62 -> 0 | D63: =D59/D62 -> 0 | E63: =E59/E62 -> 0 | F63: =F59/F62 -> 0.10642903 | G63: =G59/G62 -> 0.065004319
A64: 累計新股 | B64: bn | C64: =C63 -> 0 | D64: =C64+D63 -> 0 | E64: =D64+E63 -> 0 | F64: =E64+F63 -> 0.10642903 | G64: =F64+G63 -> 0.17143335
A65: 新債期末餘額 | B65: US$bn | C65: =C43+C56 -> 12.554496 | D65: =D43+D56 -> 45.231337 | E65: =E43+E56 -> 62.07191 | F65: =F43+F56 -> 65.211229 | G65: =G43+G56 -> 72.389956
A66: 未動用額度（期末） | B66: US$bn | C66: =C54-MIN(C54,C56) -> 0 | D66: =D54-MIN(D54,D56) -> 0 | E66: =E54-MIN(E54,E56) -> 0 | F66: =F54-MIN(F54,F56) -> 0 | G66: =G54-MIN(G54,G56) -> 0
A67: 高息債期末餘額 | B67: US$bn | C67: =C45+C60 -> 0 | D67: =D45+D60 -> 0 | E67: =E45+E60 -> 0 | F67: =F45+F60 -> 0 | G67: =G45+G60 -> 0
A68: 期末總債務（既有＋可轉債＋新債＋高息債） | B68: US$bn | C68: =C52+C65+C67 -> 47.392496 | D68: =D52+D65+D67 -> 73.885337 | E68: =E52+E65+E67 -> 86.30991 | F68: =F52+F65+F67 -> 87.028228 | G68: =G52+G65+G67 -> 90.985956
A69: 融資前累積現金 | B69: US$bn | C69: =C13+C29+C30+C31+C37-C42 -> -9.9895435 | D69: =C69+D29+D30-D42 -> -38.595565 | E69: =D69+E29+E30-E42 -> -49.849665 | F69: =E69+F29+F30-F42 -> -55.753177 | G69: =F69+G29+G30-G42 -> -61.689764
A70: 四層橋（驗算）
A71: 期初現金（2025-12-31） | C71: =輸入與假設!$C$119 -> 3.127
A72: ＋ 營運缺口合計 | C72: =SUM(C38:G38) -> -86.483115
A73: ＋ 股權／可轉債合計 | C73: =SUM(C30:G30) -> 9.182
A74: ＋ 1H 實際借款 | C74: =SUM(C31:G31) -> 16.747
A75: − capped call（1H） | C75: =-SUM(C21:G21) -> -0.492
A76: ＋ 1H 其他／受限現金調節 | C76: =SUM(C37:G37) -> -0.503
A77: ＋ 瀑布新債＋股權＋高息債合計 | C77: =SUM(C32:G32)+SUM(C33:G33)+SUM(C34:G34) -> 86.296115
A78: − 排程還本合計 | C78: =-SUM(C20:G20) -> -25.874
A79: ＝ 期末現金（橋算） | C79: =SUM(C71:C78) -> 2
A80: 對照：期末累積現金（表算） | C80: =G40 -> 2
A81: 差異（應為 0） | C81: =C79-C80 -> -2.5757174e-14
A82: FY26 全年備忘（對照公司指引）
A84: 債務明細 — 10-Q Note 10（2026-06-30）逐筆＋存量利息推導
A85: 有效利率為 10-Q 揭露值（含折價攤銷，四捨五入至整數 %）。本頁算出的存量利息連回『輸入』頁，再進入支出與資金頁
A87: 工具 | B87: 類別 | C87: 到期 | D87: 有效利率 | E87: 6/30 本金 | F87: 年化利息
A88: DDTL 1.0 | B88: 追索 | C88: 2028-03 | D88: 0.15 | E88: 1.3 | F88: =D88*E88 -> 0.195
A89: DDTL 2.0 | B89: 追索 | C89: 2030-08 | D89: 0.11 | E89: 3.19 | F89: =D89*E89 -> 0.3509
A90: DDTL 2.1 | B90: 追索 | C90: 2031-03 | D90: 0.09 | E90: 3 | F90: =D90*E90 -> 0.27
A91: DDTL 3.0 | B91: 追索 | C91: 2030-08 | D91: 0.09 | E91: 2.215 | F91: =D91*E91 -> 0.19935
A92: DDTL 5.0 | B92: 追索 | C92: 2031-11 | D92: 0.09 | E92: 1.101 | F92: =D92*E92 -> 0.09909
A93: 2030 Senior Notes | B93: 追索 | C93: 2030-06 | D93: 0.1 | E93: 2 | F93: =D93*E93 -> 0.2
A94: 2031 9.00% Senior Notes | B94: 追索 | C94: 2031-02 | D94: 0.1 | E94: 1.75 | F94: =D94*E94 -> 0.175
A95: 2031 9.75% Senior Notes | B95: 追索 | C95: 2031-10 | D95: 0.1 | E95: 2.75 | F95: =D95*E95 -> 0.275
A96: 2032 9.625% Senior Notes | B96: 追索 | C96: 2032-07 | D96: 0.1 | E96: 1.25 | F96: =D96*E96 -> 0.125
A97: 2032 EUR Senior Notes（€2.0bn） | B97: 追索 | C97: 2032-07 | D97: 0.09 | E97: 2.279 | F97: =D97*E97 -> 0.20511
A98: 2031 可轉債 | B98: 追索 | C98: 2031-12 | D98: 0.02 | E98: 2.588 | F98: =D98*E98 -> 0.05176
A99: 2032 可轉債 | B99: 追索 | C99: 2032-10 | D99: 0.02 | E99: 4 | F99: =D99*E99 -> 0.08
... A103: OEM 融資（非追索） | B103: 非追索 | C103: 2026-08～2028-08 | D103: 0.09 | E103: 0.882 | F103: =D103*E103 -> 0.07938
A104: 合計（6/30） | E104: =SUM(E88:E103) -> 35.551 | F104: =SUM(F88:F103) -> 2.99106
A105: 加權有效利率 | D105: =F104/E104 -> 0.084134342
A106: 9/17 期後：2033 可轉債 | D106: 0.02875 | E106: 3.7 | F106: =D106*E106 -> 0.106375
...

Sheet 季度追蹤
A1: 季度追蹤 — 焦點季的模型／共識／指引／實際與差距（由年度模型拆分；只用於追蹤，不影響年度數字與目標價）
A2: 設定與實際數在『輸入與假設』J 區，共識在 I 區；缺資料顯示「不適用」，實際數空白＝待公布。差距超過門檻的項目附差異原因（拆法＝所屬期間合計差距在門檻內）。第 2 區為 6 季路徑與拆分明細（預設收合）。
A4: 1｜焦點季（『輸入與假設』J 區選擇）：模型／共識／指引／實際與差距
A5: 焦點｜營收 | B5: US$bn | C5: =INDEX($C$20:$H$20,輸入與假設!$C$154) -> 3.6626667 | D5: =INDEX($C$39:$H$39,輸入與假設!$C$154) -> 3.541 | E5: =INDEX($C$49:$H$49,輸入與假設!$C$154) -> 0.034359409 | F5: =IF(ISNUMBER(INDEX($C$29:$H$29,輸入與假設!$C$154)),INDEX($C$29:$H$29,輸入與假設!$C$154),"不適用") -> 3.45 | G5: =INDEX($C$30:$H$30,輸入與假設!$C$154) -> 3.6 | H5: =INDEX($C$50:$H$50,輸入與假設!$C$154) -> 0.039054374 | I5: =IF(ISNUMBER(INDEX($C$43:$H$43,輸入與假設!$C$154)),INDEX($C$43:$H$43,輸入與假設!$C$154),"待公布") -> 待公布 | J5: =INDEX($C$51:$H$51,輸入與假設!$C$154) | K5: =INDEX($C$52:$H$52,輸入與假設!$C$154) | L5: =INDEX($C$53:$H$53,輸入與假設!$C$154)
A6: 焦點｜調整後 EBITDA | B6: US$bn | C6: =INDEX($C$26:$H$26,輸入與假設!$C$154) -> 2.1509613 | D6: =INDEX($C$40:$H$40,輸入與假設!$C$154) -> 2.047 | E6: =INDEX($C$54:$H$54,輸入與假設!$C$154) -> 0.10396126 | F6: 不適用 | G6: 不適用 | H6: =INDEX($C$55:$H$55,輸入與假設!$C$154) -> 不適用 | I6: =IF(ISNUMBER(INDEX($C$44:$H$44,輸入與假設!$C$154)),INDEX($C$44:$H$44,輸入與假設!$C$154),"待公布") -> 待公布 | J6: =INDEX($C$56:$H$56,輸入與假設!$C$154) | K6: =INDEX($C$57:$H$57,輸入與假設!$C$154) | L6: =INDEX($C$58:$H$58,輸入與假設!$C$154) | M6: =INDEX($C$59:$H$59,輸入與假設!$C$154) -> 0.009181165 | N6: =INDEX($C$60:$H$60,輸入與假設!$C$154) -> 不適用 | O6: =INDEX($C$61:$H$61,輸入與假設!$C$154) | P6: =INDEX($C$62:$H$62,輸入與假設!$C$154) | Q6: =INDEX($C$63:$H$63,輸入與假設!$C$154)
A7: 焦點｜EBITDA 率 | B7: % | C7: =INDEX($C$25:$H$25,輸入與假設!$C$154) -> 0.58726645 | D7: =INDEX($C$41:$H$41,輸入與假設!$C$154) -> 0.57808529 | E7: =INDEX($C$64:$H$64,輸入與假設!$C$154) -> 0.009181165 | F7: 不適用 | G7: 不適用 | H7: =INDEX($C$65:$H$65,輸入與假設!$C$154) -> 不適用 | I7: =IF(ISNUMBER(INDEX($C$45:$H$45,輸入與假設!$C$154)),INDEX($C$45:$H$45,輸入與假設!$C$154),"待公布") -> 待公布 | J7: =INDEX($C$66:$H$66,輸入與假設!$C$154) | K7: =INDEX($C$67:$H$67,輸入與假設!$C$154) | L7: =INDEX($C$68:$H$68,輸入與假設!$C$154)
A8: 焦點｜調整後營業利益 | B8: US$bn | C8: =INDEX($C$28:$H$28,輸入與假設!$C$154) -> -0.013413743 | D8: 不適用 | E8: =INDEX($C$69:$H$69,輸入與假設!$C$154) -> 不適用 | F8: =IF(ISNUMBER(INDEX($C$31:$H$31,輸入與假設!$C$154)),INDEX($C$31:$H$31,輸入與假設!$C$154),IF(INDEX($C$33:$H$33,輸入與假設!$C$154)<>"",INDEX($C$33:$H$33,輸入與假設!$C$154),"不適用")) -> 0.2 | G8: =INDEX($C$32:$H$32,輸入與假設!$C$154) -> 0.26 | H8: =INDEX($C$70:$H$70,輸入與假設!$C$154) -> -0.24341374 | I8: =IF(ISNUMBER(INDEX($C$46:$H$46,輸入與假設!$C$154)),INDEX($C$46:$H$46,輸入與假設!$C$154),"待公布") -> 待公布 | J8: =INDEX($C$71:$H$71,輸入與假設!$C$154) | K8: =INDEX($C$72:$H$72,輸入與假設!$C$154) | L8: =INDEX($C$73:$H$73,輸入與假設!$C$154) | M8: =INDEX($C$74:$H$74,輸入與假設!$C$154) -> 不適用 | N8: =INDEX($C$75:$H$75,輸入與假設!$C$154) -> -0.068910516 | O8: =INDEX($C$76:$H$76,輸入與假設!$C$154) | P8: =INDEX($C$77:$H$77,輸入與假設!$C$154) | Q8: =INDEX($C$78:$H$78,輸入與假設!$C$154)
A9: 焦點｜CapEx（毛額） | B9: US$bn | C9: =INDEX($C$38:$H$38,輸入與假設!$C$154) -> 12.5 | D9: 不適用 | E9: =INDEX($C$79:$H$79,輸入與假設!$C$154) -> 不適用 | F9: =IF(ISNUMBER(INDEX($C$34:$H$34,輸入與假設!$C$154)),INDEX($C$34:$H$34,輸入與假設!$C$154),"不適用") -> 11.5 | G9: =INDEX($C$35:$H$35,輸入與假設!$C$154) -> 13.5 | H9: =INDEX($C$80:$H$80,輸入與假設!$C$154) -> 0 | I9: =IF(ISNUMBER(INDEX($C$47:$H$47,輸入與假設!$C$154)),INDEX($C$47:$H$47,輸入與假設!$C$154),"待公布") -> 待公布 | J9: =INDEX($C$81:$H$81,輸入與假設!$C$154) | K9: =INDEX($C$82:$H$82,輸入與假設!$C$154) | L9: =INDEX($C$83:$H$83,輸入與假設!$C$154)
A10: 焦點｜季末 Accepted MW | B10: MW | C10: =INDEX($C$17:$H$17,輸入與假設!$C$154) -> 1675 | D10: 不適用 | E10: =INDEX($C$84:$H$84,輸入與假設!$C$154) -> 不適用 | F10: 不適用 | G10: 不適用 | H10: =INDEX($C$85:$H$85,輸入與假設!$C$154) -> 不適用 | I10: =IF(ISNUMBER(INDEX($C$48:$H$48,輸入與假設!$C$154)),INDEX($C$48:$H$48,輸入與假設!$C$154),"待公布") -> 待公布 | J10: =INDEX($C$86:$H$86,輸入與假設!$C$154) | K10: =INDEX($C$87:$H$87,輸入與假設!$C$154) | L10: =INDEX($C$88:$H$88,輸入與假設!$C$154)
A11: 焦點｜季度 | C11: =INDEX($C$14:$H$14,輸入與假設!$C$154) -> Q3'26
A12: 焦點｜差異原因 | C12: =IF(INDEX($C$131:$H$131,輸入與假設!$C$154)="","無（差距皆在 "&IF(ROUND(ABS(輸入與假設!$C$150)*100,4)=INT(ROUND(ABS(輸入與假設!$C$150)*100,4)),TEXT(ROUND(ABS(輸入與假設!$C$150)*100,4),"0"),TEXT(ROUND(ABS(輸入與假設!$C$150)*100,4),"0.0"))&"%"&" 以內）",INDEX($C$131:$H$131,輸入與假設!$C$154)) -> 營收 vs 指引中點 +3.9%：觀點（水準 +$0.115bn（2H26 模型 $8.413bn，指引隱含 $8.147bn）；分配 +$0.023bn）；調整後營業利益 vs 指引中點 −$0.24bn／−6.9pt：已知限制（對照指引隱含折舊 1.82（＝共識 EBITDA 2.05 − 指引中點 0.23，Derived），模型折舊 2.16；缺口 −0.24 ≈ 折舊 −0.35 ＋ EBITDA +0.10；待辦 6 修正折舊）
A13: 2｜6 季路徑、共識、指引、實際與差距（明細；第 1 區以焦點季引用本區）
A14: 項目 | B14: 單位 | C14: Q3'26 | D14: Q4'26 | E14: Q1'27 | F14: Q2'27 | G14: Q3'27 | H14: Q4'27
A15: 所屬期間 | C15: =輸入與假設!C$153 -> 1 | D15: =輸入與假設!D$153 -> 1 | E15: =輸入與假設!E$153 -> 2 | F15: =輸入與假設!F$153 -> 2 | G15: =輸入與假設!G$153 -> 2 | H15: =輸入與假設!H$153 -> 2
A16: 季序 | C16: 1 | D16: 2 | E16: 3 | F16: 4 | G16: 5 | H16: 6
A17: 季末 Accepted MW（模型） | B17: MW | C17: =輸入與假設!$C$156+(輸入與假設!C$23-輸入與假設!$C$156)*1/2 -> 1675 | D17: =輸入與假設!$C$156+(輸入與假設!C$23-輸入與假設!$C$156)*2/2 -> 1850 | E17: =輸入與假設!C$23+(輸入與假設!D$23-輸入與假設!C$23)*1/4 -> 2162.5 | F17: =輸入與假設!C$23+(輸入與假設!D$23-輸入與假設!C$23)*2/4 -> 2475 | G17: =輸入與假設!C$23+(輸入與假設!D$23-輸入與假設!C$23)*3/4 -> 2787.5 | H17: =輸入與假設!C$23+(輸入與假設!D$23-輸入與假設!C$23)*4/4 -> 3100
A18: 平均在役 MW（Billable，拆分依據） | B18: MW | C18: =輸入與假設!$C$18+(輸入與假設!C$24-輸入與假設!$C$18)*1/4 -> 1437.5 | D18: =輸入與假設!$C$18+(輸入與假設!C$24-輸入與假設!$C$18)*3/4 -> 1612.5 | E18: =輸入與假設!C$24+(輸入與假設!D$24-輸入與假設!C$24)*1/8 -> 1850 | F18: =輸入與假設!C$24+(輸入與假設!D$24-輸入與假設!C$24)*3/8 -> 2150 | G18: =輸入與假設!C$24+(輸入與假設!D$24-輸入與假設!C$24)*5/8 -> 2450 | H18: =輸入與假設!C$24+(輸入與假設!D$24-輸入與假設!C$24)*7/8 -> 2750
A19: 季內新增 Accepted MW | B19: MW | C19: =C17-輸入與假設!$C$156 -> 175 | D19: =D17-C17 -> 175 | E19: =E17-輸入與假設!C$23 -> 312.5 | F19: =F17-E17 -> 312.5 | G19: =G17-F17 -> 312.5 | H19: =H17-G17 -> 312.5
A20: 營收（模型） | B20: US$bn | C20: =輸入與假設!$C$155+1*(損益與評價!C8-2*輸入與假設!$C$155)/3 -> 3.6626667 | D20: =輸入與假設!$C$155+2*(損益與評價!C8-2*輸入與假設!$C$155)/3 -> 4.7503333 | E20: =損益與評價!D8*E18/(E18+F18+G18+H18) -> 5.2538995 | F20: =損益與評價!D8*F18/(E18+F18+G18+H18) -> 6.1058832 | G20: =損益與評價!D8*G18/(E18+F18+G18+H18) -> 6.9578668 | H20: =損益與評價!D8*H18/(E18+F18+G18+H18) -> 7.8098505
A21: EBITDA 率直線｜各期營收合計 S | C21: =C20+D20 -> 8.413 | D21: =E20+F20+G20+H20 -> 26.1275
A22: EBITDA 率直線｜營收 × 季序合計 T | C22: =C20*C16+D20*D16 -> 13.163333 | D22: =E20*E16+F20*F16+G20*G16+H20*H16 -> 121.83367
A23: EBITDA 率直線｜年度 EBITDA E | C23: =損益與評價!C11 -> 4.96367 | D23: =損益與評價!D11 -> 15.807137
A24: EBITDA 率直線｜截距 a／斜率 b | C24: =(C23*D22-C22*D23)/(C21*D22-C22*D21) -> 0.58242525 | D24: =(C21*D23-D21*C23)/(C21*D22-C22*D21) -> 0.0048412061
A25: EBITDA 率（模型） | B25: % | C25: =$C$24+$D$24*C16 -> 0.58726645 | D25: =$C$24+$D$24*D16 -> 0.59210766 | E25: =$C$24+$D$24*E16 -> 0.59694886 | F25: =$C$24+$D$24*F16 -> 0.60179007 | G25: =$C$24+$D$24*G16 -> 0.60663128 | H25: =$C$24+$D$24*H16 -> 0.61147248
A26: 調整後 EBITDA（模型） | B26: US$bn | C26: =C20*C25 -> 2.1509613 | D26: =D20*D25 -> 2.8127087 | E26: =E20*E25 -> 3.1363093 | F26: =F20*F25 -> 3.6744598 | G26: =G20*G25 -> 4.2208596 | H26: =H20*H25 -> 4.7755087
A27: 車隊折舊（模型） | B27: US$bn | C27: =(輸入與假設!C$62+輸入與假設!C$60*1/4)/輸入與假設!$C$44*輸入與假設!C$21/2 -> 2.164375 | D27: =(輸入與假設!C$62+輸入與假設!C$60*3/4)/輸入與假設!$C$44*輸入與假設!C$21/2 -> 2.5984583 | E27: =(輸入與假設!D$62+輸入與假設!D$60*1/8)/輸入與假設!$C$44*輸入與假設!D$21/4 -> 3.0151615 | F27: =(輸入與假設!D$62+輸入與假設!D$60*3/8)/輸入與假設!$C$44*輸入與假設!D$21/4 -> 3.4144844 | G27: =(輸入與假設!D$62+輸入與假設!D$60*5/8)/輸入與假設!$C$44*輸入與假設!D$21/4 -> 3.8138073 | H27: =(輸入與假設!D$62+輸入與假設!D$60*7/8)/輸入與假設!$C$44*輸入與假設!D$21/4 -> 4.2131302
A28: 調整後營業利益（模型） | B28: US$bn | C28: =C26-C27 -> -0.013413743 | D28: =D26-D27 -> 0.21425041 | E28: =E26-E27 -> 0.12114785 | F28: =F26-F27 -> 0.25997547 | G28: =G26-G27 -> 0.40705235 | H28: =H26-H27 -> 0.56237849
A29: 指引｜營收（低） | B29: US$bn | C29: =IF(ISNUMBER(輸入與假設!C$162),輸入與假設!C$162,"不適用") -> 3.45 | D29: =IF(ISNUMBER(輸入與假設!D$162),輸入與假設!D$162,"不適用") -> 不適用 | E29: =IF(ISNUMBER(輸入與假設!E$162),輸入與假設!E$162,"不適用") -> 不適用 | F29: =IF(ISNUMBER(輸入與假設!F$162),輸入與假設!F$162,"不適用") -> 不適用 | G29: =IF(ISNUMBER(輸入與假設!G$162),輸入與假設!G$162,"不適用") -> 不適用 | H29: =IF(ISNUMBER(輸入與假設!H$162),輸入與假設!H$162,"不適用") -> 不適用
A30: 指引｜營收（高） | B30: US$bn | C30: =IF(ISNUMBER(輸入與假設!C$163),輸入與假設!C$163,"不適用") -> 3.6 | D30: =IF(ISNUMBER(輸入與假設!D$163),輸入與假設!D$163,"不適用") -> 不適用 | E30: =IF(ISNUMBER(輸入與假設!E$163),輸入與假設!E$163,"不適用") -> 不適用 | F30: =IF(ISNUMBER(輸入與假設!F$163),輸入與假設!F$163,"不適用") -> 不適用 | G30: =IF(ISNUMBER(輸入與假設!G$163),輸入與假設!G$163,"不適用") -> 不適用 | H30: =IF(ISNUMBER(輸入與假設!H$163),輸入與假設!H$163,"不適用") -> 不適用
A31: 指引｜調整後營業利益（低） | B31: US$bn | C31: =IF(ISNUMBER(輸入與假設!C$164),輸入與假設!C$164,"不適用") -> 0.2 | D31: =IF(ISNUMBER(輸入與假設!D$164),輸入與假設!D$164,"不適用") -> 不適用 | E31: =IF(ISNUMBER(輸入與假設!E$164),輸入與假設!E$164,"不適用") -> 不適用 | F31: =IF(ISNUMBER(輸入與假設!F$164),輸入與假設!F$164,"不適用") -> 不適用 | G31: =IF(ISNUMBER(輸入與假設!G$164),輸入與假設!G$164,"不適用") -> 不適用 | H31: =IF(ISNUMBER(輸入與假設!H$164),輸入與假設!H$164,"不適用") -> 不適用
A32: 指引｜調整後營業利益（高） | B32: US$bn | C32: =IF(ISNUMBER(輸入與假設!C$165),輸入與假設!C$165,"不適用") -> 0.26 | D32: =IF(ISNUMBER(輸入與假設!D$165),輸入與假設!D$165,"不適用") -> 不適用 | E32: =IF(ISNUMBER(輸入與假設!E$165),輸入與假設!E$165,"不適用") -> 不適用 | F32: =IF(ISNUMBER(輸入與假設!F$165),輸入與假設!F$165,"不適用") -> 不適用 | G32: =IF(ISNUMBER(輸入與假設!G$165),輸入與假設!G$165,"不適用") -> 不適用 | H32: =IF(ISNUMBER(輸入與假設!H$165),輸入與假設!H$165,"不適用") -> 不適用
A33: 指引（文字）｜調整後營業利益 | C33: =IF(ISTEXT(輸入與假設!C$168),輸入與假設!C$168,"") | D33: =IF(ISTEXT(輸入與假設!D$168),輸入與假設!D$168,"") -> 調整後營業利益率 low teens | E33: =IF(ISTEXT(輸入與假設!E$168),輸入與假設!E$168,"") | F33: =IF(ISTEXT(輸入與假設!F$168),輸入與假設!F$168,"") | G33: =IF(ISTEXT(輸入與假設!G$168),輸入與假設!G$168,"") | H33: =IF(ISTEXT(輸入與假設!H$168),輸入與假設!H$168,"")
A34: 指引｜CapEx（毛額）（低） | B34: US$bn | C34: =IF(ISNUMBER(輸入與假設!C$166),輸入與假設!C$166,"不適用") -> 11.5 | D34: =IF(ISNUMBER(輸入與假設!D$166),輸入與假設!D$166,"不適用") -> 不適用 | E34: =IF(ISNUMBER(輸入與假設!E$166),輸入與假設!E$166,"不適用") -> 不適用 | F34: =IF(ISNUMBER(輸入與假設!F$166),輸入與假設!F$166,"不適用") -> 不適用 | G34: =IF(ISNUMBER(輸入與假設!G$166),輸入與假設!G$166,"不適用") -> 不適用 | H34: =IF(ISNUMBER(輸入與假設!H$166),輸入與假設!H$166,"不適用") -> 不適用
A35: 指引｜CapEx（毛額）（高） | B35: US$bn | C35: =IF(ISNUMBER(輸入與假設!C$167),輸入與假設!C$167,"不適用") -> 13.5 | D35: =IF(ISNUMBER(輸入與假設!D$167),輸入與假設!D$167,"不適用") -> 不適用 | E35: =IF(ISNUMBER(輸入與假設!E$167),輸入與假設!E$167,"不適用") -> 不適用 | F35: =IF(ISNUMBER(輸入與假設!F$167),輸入與假設!F$167,"不適用") -> 不適用 | G35: =IF(ISNUMBER(輸入與假設!G$167),輸入與假設!G$167,"不適用") -> 不適用 | H35: =IF(ISNUMBER(輸入與假設!H$167),輸入與假設!H$167,"不適用") -> 不適用
A36: CapEx 指引錨定值 | B36: US$bn | C36: =IF(AND(ISNUMBER(C34),ISNUMBER(C35)),((C34+C35)/2),"") -> 12.5 | D36: =IF(AND(ISNUMBER(D34),ISNUMBER(D35)),((D34+D35)/2),"") | E36: =IF(AND(ISNUMBER(E34),ISNUMBER(E35)),((E34+E35)/2),"") | F36: =IF(AND(ISNUMBER(F34),ISNUMBER(F35)),((F34+F35)/2),"") | G36: =IF(AND(ISNUMBER(G34),ISNUMBER(G35)),((G34+G35)/2),"") | H36: =IF(AND(ISNUMBER(H34),ISNUMBER(H35)),((H34+H35)/2),"")
A37: CapEx 未錨定季的新增 MW | B37: MW | C37: =IF(ISNUMBER(C36),0,C19) -> 0 | D37: =IF(ISNUMBER(D36),0,D19) -> 175 | E37: =IF(ISNUMBER(E36),0,E19) -> 312.5 | F37: =IF(ISNUMBER(F36),0,F19) -> 312.5 | G37: =IF(ISNUMBER(G36),0,G19) -> 312.5 | H37: =IF(ISNUMBER(H36),0,H19) -> 312.5
A38: CapEx（毛額）（模型） | B38: US$bn | C38: =IF(ISNUMBER(C36),C36,IF((C37+D37)>0,(輸入與假設!C$63-SUM(C36,D36))*C37/(C37+D37),(輸入與假設!C$63-SUM(C36,D36))/(2-COUNT(C36,D36)))) -> 12.5 | D38: =IF(ISNUMBER(D36),D36,IF((C37+D37)>0,(輸入與假設!C$63-SUM(C36,D36))*D37/(C37+D37),(輸入與假設!C$63-SUM(C36,D36))/(2-COUNT(C36,D36)))) -> 8.336 | E38: =IF(ISNUMBER(E36),E36,IF((E37+F37+G37+H37)>0,(輸入與假設!D$63-SUM(E36,F36,G36,H36))*E37/(E37+F37+G37+H37),(輸入與假設!D$63-SUM(E36,F36,G36,H36))/(4-COUNT(E36,F36,G36,H36)))) -> 9.58375 | F38: =IF(ISNUMBER(F36),F36,IF((E37+F37+G37+H37)>0,(輸入與假設!D$63-SUM(E36,F36,G36,H36))*F37/(E37+F37+G37+H37),(輸入與假設!D$63-SUM(E36,F36,G36,H36))/(4-COUNT(E36,F36,G36,H36)))) -> 9.58375 | G38: =IF(ISNUMBER(G36),G36,IF((E37+F37+G37+H37)>0,(輸入與假設!D$63-SUM(E36,F36,G36,H36))*G37/(E37+F37+G37+H37),(輸入與假設!D$63-SUM(E36,F36,G36,H36))/(4-COUNT(E36,F36,G36,H36)))) -> 9.58375 | H38: =IF(ISNUMBER(H36),H36,IF((E37+F37+G37+H37)>0,(輸入與假設!D$63-SUM(E36,F36,G36,H36))*H37/(E37+F37+G37+H37),(輸入與假設!D$63-SUM(E36,F36,G36,H36))/(4-COUNT(E36,F36,G36,H36)))) -> 9.58375
A39: 共識｜營收 | B39: US$bn | C39: =IF(ISNUMBER(輸入與假設!$C$147),輸入與假設!$C$147,"不適用") -> 3.541 | D39: =IF(ISNUMBER(輸入與假設!$D$147),輸入與假設!$D$147,"不適用") -> 4.706 | E39: 不適用 | F39: 不適用 | G39: 不適用 | H39: 不適用
A40: 共識｜調整後 EBITDA | B40: US$bn | C40: =IF(ISNUMBER(輸入與假設!$C$148),輸入與假設!$C$148,"不適用") -> 2.047 | D40: =IF(ISNUMBER(輸入與假設!$D$148),輸入與假設!$D$148,"不適用") -> 2.897 | E40: 不適用 | F40: 不適用 | G40: 不適用 | H40: 不適用
A41: 共識｜EBITDA 率 [Derived] | B41: % | C41: =IF(AND(ISNUMBER(輸入與假設!$C$148),ISNUMBER(輸入與假設!$C$147)),輸入與假設!$C$148/輸入與假設!$C$147,"不適用") -> 0.57808529 | D41: =IF(AND(ISNUMBER(輸入與假設!$D$148),ISNUMBER(輸入與假設!$D$147)),輸入與假設!$D$148/輸入與假設!$D$147,"不適用") -> 0.61559711 | E41: 不適用 | F41: 不適用 | G41: 不適用 | H41: 不適用
A42: 共識 EBIT（口徑未揭露） | B42: US$bn | C42: =IF(ISNUMBER(輸入與假設!$C$149),輸入與假設!$C$149,"不適用") -> 0.2408 | D42: =IF(ISNUMBER(輸入與假設!$D$149),輸入與假設!$D$149,"不適用") -> 0.6805 | E42: 不適用 | F42: 不適用 | G42: 不適用 | H42: 不適用
A43: 實際｜營收 | B43: US$bn | C43: =IF(ISNUMBER(輸入與假設!C$157),輸入與假設!C$157,"") | D43: =IF(ISNUMBER(輸入與假設!D$157),輸入與假設!D$157,"") | E43: =IF(ISNUMBER(輸入與假設!E$157),輸入與假設!E$157,"") | F43: =IF(ISNUMBER(輸入與假設!F$157),輸入與假設!F$157,"") | G43: =IF(ISNUMBER(輸入與假設!G$157),輸入與假設!G$157,"") | H43: =IF(ISNUMBER(輸入與假設!H$157),輸入與假設!H$157,"")
A44: 實際｜調整後 EBITDA | B44: US$bn | C44: =IF(ISNUMBER(輸入與假設!C$158),輸入與假設!C$158,"") | D44: =IF(ISNUMBER(輸入與假設!D$158),輸入與假設!D$158,"") | E44: =IF(ISNUMBER(輸入與假設!E$158),輸入與假設!E$158,"") | F44: =IF(ISNUMBER(輸入與假設!F$158),輸入與假設!F$158,"") | G44: =IF(ISNUMBER(輸入與假設!G$158),輸入與假設!G$158,"") | H44: =IF(ISNUMBER(輸入與假設!H$158),輸入與假設!H$158,"")
A45: 實際｜EBITDA 率 | B45: % | C45: =IF(AND(ISNUMBER(輸入與假設!C$158),ISNUMBER(輸入與假設!C$157)),輸入與假設!C$158/輸入與假設!C$157,"") | D45: =IF(AND(ISNUMBER(輸入與假設!D$158),ISNUMBER(輸入與假設!D$157)),輸入與假設!D$158/輸入與假設!D$157,"") | E45: =IF(AND(ISNUMBER(輸入與假設!E$158),ISNUMBER(輸入與假設!E$157)),輸入與假設!E$158/輸入與假設!E$157,"") | F45: =IF(AND(ISNUMBER(輸入與假設!F$158),ISNUMBER(輸入與假設!F$157)),輸入與假設!F$158/輸入與假設!F$157,"") | G45: =IF(AND(ISNUMBER(輸入與假設!G$158),ISNUMBER(輸入與假設!G$157)),輸入與假設!G$158/輸入與假設!G$157,"") | H45: =IF(AND(ISNUMBER(輸入與假設!H$158),ISNUMBER(輸入與假設!H$157)),輸入與假設!H$158/輸入與假設!H$157,"")
A46: 實際｜調整後營業利益 | B46: US$bn | C46: =IF(ISNUMBER(輸入與假設!C$159),輸入與假設!C$159,"") | D46: =IF(ISNUMBER(輸入與假設!D$159),輸入與假設!D$159,"") | E46: =IF(ISNUMBER(輸入與假設!E$159),輸入與假設!E$159,"") | F46: =IF(ISNUMBER(輸入與假設!F$159),輸入與假設!F$159,"") | G46: =IF(ISNUMBER(輸入與假設!G$159),輸入與假設!G$159,"") | H46: =IF(ISNUMBER(輸入與假設!H$159),輸入與假設!H$159,"")
A47: 實際｜CapEx（毛額） | B47: US$bn | C47: =IF(ISNUMBER(輸入與假設!C$160),輸入與假設!C$160,"") | D47: =IF(ISNUMBER(輸入與假設!D$160),輸入與假設!D$160,"") | E47: =IF(ISNUMBER(輸入與假設!E$160),輸入與假設!E$160,"") | F47: =IF(ISNUMBER(輸入與假設!F$160),輸入與假設!F$160,"") | G47: =IF(ISNUMBER(輸入與假設!G$160),輸入與假設!G$160,"") | H47: =IF(ISNUMBER(輸入與假設!H$160),輸入與假設!H$160,"")
A48: 實際｜季末 active power | B48: MW | C48: =IF(ISNUMBER(輸入與假設!C$161),輸入與假設!C$161,"") | D48: =IF(ISNUMBER(輸入與假設!D$161),輸入與假設!D$161,"") | E48: =IF(ISNUMBER(輸入與假設!E$161),輸入與假設!E$161,"") | F48: =IF(ISNUMBER(輸入與假設!F$161),輸入與假設!F$161,"") | G48: =IF(ISNUMBER(輸入與假設!G$161),輸入與假設!G$161,"") | H48: =IF(ISNUMBER(輸入與假設!H$161),輸入與假設!H$161,"")
A49: 差距｜營收｜模型 vs 共識 | B49: % | C49: =IF(AND(ISNUMBER(C20),ISNUMBER(C39),C39<>0),C20/(C39)-1,"不適用") -> 0.034359409 | D49: =IF(AND(ISNUMBER(D20),ISNUMBER(D39),D39<>0),D20/(D39)-1,"不適用") -> 0.0094205978 | E49: =IF(AND(ISNUMBER(E20),ISNUMBER(E39),E39<>0),E20/(E39)-1,"不適用") -> 不適用 | F49: =IF(AND(ISNUMBER(F20),ISNUMBER(F39),F39<>0),F20/(F39)-1,"不適用") -> 不適用 | G49: =IF(AND(ISNUMBER(G20),ISNUMBER(G39),G39<>0),G20/(G39)-1,"不適用") -> 不適用 | H49: =IF(AND(ISNUMBER(H20),ISNUMBER(H39),H39<>0),H20/(H39)-1,"不適用") -> 不適用
A50: 差距｜營收｜模型 vs 指引中點 | B50: % | C50: =IF(AND(ISNUMBER(C20),ISNUMBER(C29),ISNUMBER(C30)),C20/(((C29+C30)/2))-1,"不適用") -> 0.039054374 | D50: =IF(AND(ISNUMBER(D20),ISNUMBER(D29),ISNUMBER(D30)),D20/(((D29+D30)/2))-1,"不適用") -> 不適用 | E50: =IF(AND(ISNUMBER(E20),ISNUMBER(E29),ISNUMBER(E30)),E20/(((E29+E30)/2))-1,"不適用") -> 不適用 | F50: =IF(AND(ISNUMBER(F20),ISNUMBER(F29),ISNUMBER(F30)),F20/(((F29+F30)/2))-1,"不適用") -> 不適用 | G50: =IF(AND(ISNUMBER(G20),ISNUMBER(G29),ISNUMBER(G30)),G20/(((G29+G30)/2))-1,"不適用") -> 不適用 | H50: =IF(AND(ISNUMBER(H20),ISNUMBER(H29),ISNUMBER(H30)),H20/(((H29+H30)/2))-1,"不適用") -> 不適用
A51: 差距｜營收｜實際 vs 模型 | B51: % | C51: =IF(ISNUMBER(C43),IF(AND(ISNUMBER(C20),C20<>0),C43/(C20)-1,"不適用"),"") | D51: =IF(ISNUMBER(D43),IF(AND(ISNUMBER(D20),D20<>0),D43/(D20)-1,"不適用"),"") | E51: =IF(ISNUMBER(E43),IF(AND(ISNUMBER(E20),E20<>0),E43/(E20)-1,"不適用"),"") | F51: =IF(ISNUMBER(F43),IF(AND(ISNUMBER(F20),F20<>0),F43/(F20)-1,"不適用"),"") | G51: =IF(ISNUMBER(G43),IF(AND(ISNUMBER(G20),G20<>0),G43/(G20)-1,"不適用"),"") | H51: =IF(ISNUMBER(H43),IF(AND(ISNUMBER(H20),H20<>0),H43/(H20)-1,"不適用"),"")
A52: 差距｜營收｜實際 vs 共識 | B52: % | C52: =IF(ISNUMBER(C43),IF(AND(ISNUMBER(C39),C39<>0),C43/(C39)-1,"不適用"),"") | D52: =IF(ISNUMBER(D43),IF(AND(ISNUMBER(D39),D39<>0),D43/(D39)-1,"不適用"),"") | E52: =IF(ISNUMBER(E43),IF(AND(ISNUMBER(E39),E39<>0),E43/(E39)-1,"不適用"),"") | F52: =IF(ISNUMBER(F43),IF(AND(ISNUMBER(F39),F39<>0),F43/(F39)-1,"不適用"),"") | G52: =IF(ISNUMBER(G43),IF(AND(ISNUMBER(G39),G39<>0),G43/(G39)-1,"不適用"),"") | H52: =IF(ISNUMBER(H43),IF(AND(ISNUMBER(H39),H39<>0),H43/(H39)-1,"不適用"),"")
A53: 差距｜營收｜實際 vs 指引中點 | B53: % | C53: =IF(ISNUMBER(C43),IF(AND(ISNUMBER(C29),ISNUMBER(C30)),C43/(((C29+C30)/2))-1,"不適用"),"") | D53: =IF(ISNUMBER(D43),IF(AND(ISNUMBER(D29),ISNUMBER(D30)),D43/(((D29+D30)/2))-1,"不適用"),"") | E53: =IF(ISNUMBER(E43),IF(AND(ISNUMBER(E29),ISNUMBER(E30)),E43/(((E29+E30)/2))-1,"不適用"),"") | F53: =IF(ISNUMBER(F43),IF(AND(ISNUMBER(F29),ISNUMBER(F30)),F43/(((F29+F30)/2))-1,"不適用"),"") | G53: =IF(ISNUMBER(G43),IF(AND(ISNUMBER(G29),ISNUMBER(G30)),G43/(((G29+G30)/2))-1,"不適用"),"") | H53: =IF(ISNUMBER(H43),IF(AND(ISNUMBER(H29),ISNUMBER(H30)),H43/(((H29+H30)/2))-1,"不適用"),"")
A54: 差距｜調整後 EBITDA｜模型 vs 共識 | B54: US$bn | C54: =IF(AND(ISNUMBER(C26),ISNUMBER(C40)),C26-(C40),"不適用") -> 0.10396126 | D54: =IF(AND(ISNUMBER(D26),ISNUMBER(D40)),D26-(D40),"不適用") -> -0.084291257 | E54: =IF(AND(ISNUMBER(E26),ISNUMBER(E40)),E26-(E40),"不適用") -> 不適用 | F54: =IF(AND(ISNUMBER(F26),ISNUMBER(F40)),F26-(F40),"不適用") -> 不適用 | G54: =IF(AND(ISNUMBER(G26),ISNUMBER(G40)),G26-(G40),"不適用") -> 不適用 | H54: =IF(AND(ISNUMBER(H26),ISNUMBER(H40)),H26-(H40),"不適用") -> 不適用
A55: 差距｜調整後 EBITDA｜模型 vs 指引中點 | B55: US$bn | C55: 不適用 | D55: 不適用 | E55: 不適用 | F55: 不適用 | G55: 不適用 | H55: 不適用
A56: 差距｜調整後 EBITDA｜實際 vs 模型 | B56: US$bn | C56: =IF(ISNUMBER(C44),IF(AND(ISNUMBER(C26)),C44-(C26),"不適用"),"") | D56: =IF(ISNUMBER(D44),IF(AND(ISNUMBER(D26)),D44-(D26),"不適用"),"") | E56: =IF(ISNUMBER(E44),IF(AND(ISNUMBER(E26)),E44-(E26),"不適用"),"") | F56: =IF(ISNUMBER(F44),IF(AND(ISNUMBER(F26)),F44-(F26),"不適用"),"") | G56: =IF(ISNUMBER(G44),IF(AND(ISNUMBER(G26)),G44-(G26),"不適用"),"") | H56: =IF(ISNUMBER(H44),IF(AND(ISNUMBER(H26)),H44-(H26),"不適用"),"")
A57: 差距｜調整後 EBITDA｜實際 vs 共識 | B57: US$bn | C57: =IF(ISNUMBER(C44),IF(AND(ISNUMBER(C40)),C44-(C40),"不適用"),"") | D57: =IF(ISNUMBER(D44),IF(AND(ISNUMBER(D40)),D44-(D40),"不適用"),"") | E57: =IF(ISNUMBER(E44),IF(AND(ISNUMBER(E40)),E44-(E40),"不適用"),"") | F57: =IF(ISNUMBER(F44),IF(AND(ISNUMBER(F40)),F44-(F40),"不適用"),"") | G57: =IF(ISNUMBER(G44),IF(AND(ISNUMBER(G40)),G44-(G40),"不適用"),"") | H57: =IF(ISNUMBER(H44),IF(AND(ISNUMBER(H40)),H44-(H40),"不適用"),"")
A58: 差距｜調整後 EBITDA｜實際 vs 指引中點 | B58: US$bn | C58: =IF(ISNUMBER(C44),"不適用","") | D58: =IF(ISNUMBER(D44),"不適用","") | E58: =IF(ISNUMBER(E44),"不適用","") | F58: =IF(ISNUMBER(F44),"不適用","") | G58: =IF(ISNUMBER(G44),"不適用","") | H58: =IF(ISNUMBER(H44),"不適用","")
A59: 差距｜調整後 EBITDA｜模型 vs 共識（利潤率 pt） | B59: pt | C59: =IF(AND(ISNUMBER(C26),ISNUMBER(C20),C20<>0,ISNUMBER(C40),ISNUMBER(C39),C39<>0),C26/C20-C40/C39,"不適用") -> 0.009181165 | D59: =IF(AND(ISNUMBER(D26),ISNUMBER(D20),D20<>0,ISNUMBER(D40),ISNUMBER(D39),D39<>0),D26/D20-D40/D39,"不適用") -> -0.023489452 | E59: =IF(AND(ISNUMBER(E26),ISNUMBER(E20),E20<>0,ISNUMBER(E40),ISNUMBER(E39),E39<>0),E26/E20-E40/E39,"不適用") -> 不適用 | F59: =IF(AND(ISNUMBER(F26),ISNUMBER(F20),F20<>0,ISNUMBER(F40),ISNUMBER(F39),F39<>0),F26/F20-F40/F39,"不適用") -> 不適用 | G59: =IF(AND(ISNUMBER(G26),ISNUMBER(G20),G20<>0,ISNUMBER(G40),ISNUMBER(G39),G39<>0),G26/G20-G40/G39,"不適用") -> 不適用 | H59: =IF(AND(ISNUMBER(H26),ISNUMBER(H20),H20<>0,ISNUMBER(H40),ISNUMBER(H39),H39<>0),H26/H20-H40/H39,"不適用") -> 不適用
A60: 差距｜調整後 EBITDA｜模型 vs 指引中點（利潤率 pt） | B60: pt | C60: 不適用 | D60: 不適用 | E60: 不適用 | F60: 不適用 | G60: 不適用 | H60: 不適用
A61: 差距｜調整後 EBITDA｜實際 vs 模型（利潤率 pt） | B61: pt | C61: =IF(ISNUMBER(C44),IF(AND(ISNUMBER(C44),ISNUMBER(C43),C43<>0,ISNUMBER(C26),ISNUMBER(C20),C20<>0),C44/C43-C26/C20,"不適用"),"") | D61: =IF(ISNUMBER(D44),IF(AND(ISNUMBER(D44),ISNUMBER(D43),D43<>0,ISNUMBER(D26),ISNUMBER(D20),D20<>0),D44/D43-D26/D20,"不適用"),"") | E61: =IF(ISNUMBER(E44),IF(AND(ISNUMBER(E44),ISNUMBER(E43),E43<>0,ISNUMBER(E26),ISNUMBER(E20),E20<>0),E44/E43-E26/E20,"不適用"),"") | F61: =IF(ISNUMBER(F44),IF(AND(ISNUMBER(F44),ISNUMBER(F43),F43<>0,ISNUMBER(F26),ISNUMBER(F20),F20<>0),F44/F43-F26/F20,"不適用"),"") | G61: =IF(ISNUMBER(G44),IF(AND(ISNUMBER(G44),ISNUMBER(G43),G43<>0,ISNUMBER(G26),ISNUMBER(G20),G20<>0),G44/G43-G26/G20,"不適用"),"") | H61: =IF(ISNUMBER(H44),IF(AND(ISNUMBER(H44),ISNUMBER(H43),H43<>0,ISNUMBER(H26),ISNUMBER(H20),H20<>0),H44/H43-H26/H20,"不適用"),"")
A62: 差距｜調整後 EBITDA｜實際 vs 共識（利潤率 pt） | B62: pt | C62: =IF(ISNUMBER(C44),IF(AND(ISNUMBER(C44),ISNUMBER(C43),C43<>0,ISNUMBER(C40),ISNUMBER(C39),C39<>0),C44/C43-C40/C39,"不適用"),"") | D62: =IF(ISNUMBER(D44),IF(AND(ISNUMBER(D44),ISNUMBER(D43),D43<>0,ISNUMBER(D40),ISNUMBER(D39),D39<>0),D44/D43-D40/D39,"不適用"),"") | E62: =IF(ISNUMBER(E44),IF(AND(ISNUMBER(E44),ISNUMBER(E43),E43<>0,ISNUMBER(E40),ISNUMBER(E39),E39<>0),E44/E43-E40/E39,"不適用"),"") | F62: =IF(ISNUMBER(F44),IF(AND(ISNUMBER(F44),ISNUMBER(F43),F43<>0,ISNUMBER(F40),ISNUMBER(F39),F39<>0),F44/F43-F40/F39,"不適用"),"") | G62: =IF(ISNUMBER(G44),IF(AND(ISNUMBER(G44),ISNUMBER(G43),G43<>0,ISNUMBER(G40),ISNUMBER(G39),G39<>0),G44/G43-G40/G39,"不適用"),"") | H62: =IF(ISNUMBER(H44),IF(AND(ISNUMBER(H44),ISNUMBER(H43),H43<>0,ISNUMBER(H40),ISNUMBER(H39),H39<>0),H44/H43-H40/H39,"不適用"),"")
A63: 差距｜調整後 EBITDA｜實際 vs 指引中點（利潤率 pt） | B63: pt | C63: =IF(ISNUMBER(C44),"不適用","") | D63: =IF(ISNUMBER(D44),"不適用","") | E63: =IF(ISNUMBER(E44),"不適用","") | F63: =IF(ISNUMBER(F44),"不適用","") | G63: =IF(ISNUMBER(G44),"不適用","") | H63: =IF(ISNUMBER(H44),"不適用","")
A64: 差距｜EBITDA 率｜模型 vs 共識 | B64: pt | C64: =IF(AND(ISNUMBER(C25),ISNUMBER(C41)),C25-(C41),"不適用") -> 0.009181165 | D64: =IF(AND(ISNUMBER(D25),ISNUMBER(D41)),D25-(D41),"不適用") -> -0.023489452 | E64: =IF(AND(ISNUMBER(E25),ISNUMBER(E41)),E25-(E41),"不適用") -> 不適用 | F64: =IF(AND(ISNUMBER(F25),ISNUMBER(F41)),F25-(F41),"不適用") -> 不適用 | G64: =IF(AND(ISNUMBER(G25),ISNUMBER(G41)),G25-(G41),"不適用") -> 不適用 | H64: =IF(AND(ISNUMBER(H25),ISNUMBER(H41)),H25-(H41),"不適用") -> 不適用
A65: 差距｜EBITDA 率｜模型 vs 指引中點 | B65: pt | C65: 不適用 | D65: 不適用 | E65: 不適用 | F65: 不適用 | G65: 不適用 | H65: 不適用
A66: 差距｜EBITDA 率｜實際 vs 模型 | B66: pt | C66: =IF(ISNUMBER(C45),IF(AND(ISNUMBER(C25)),C45-(C25),"不適用"),"") | D66: =IF(ISNUMBER(D45),IF(AND(ISNUMBER(D25)),D45-(D25),"不適用"),"") | E66: =IF(ISNUMBER(E45),IF(AND(ISNUMBER(E25)),E45-(E25),"不適用"),"") | F66: =IF(ISNUMBER(F45),IF(AND(ISNUMBER(F25)),F45-(F25),"不適用"),"") | G66: =IF(ISNUMBER(G45),IF(AND(ISNUMBER(G25)),G45-(G25),"不適用"),"") | H66: =IF(ISNUMBER(H45),IF(AND(ISNUMBER(H25)),H45-(H25),"不適用"),"")
A67: 差距｜EBITDA 率｜實際 vs 共識 | B67: pt | C67: =IF(ISNUMBER(C45),IF(AND(ISNUMBER(C41)),C45-(C41),"不適用"),"") | D67: =IF(ISNUMBER(D45),IF(AND(ISNUMBER(D41)),D45-(D41),"不適用"),"") | E67: =IF(ISNUMBER(E45),IF(AND(ISNUMBER(E41)),E45-(E41),"不適用"),"") | F67: =IF(ISNUMBER(F45),IF(AND(ISNUMBER(F41)),F45-(F41),"不適用"),"") | G67: =IF(ISNUMBER(G45),IF(AND(ISNUMBER(G41)),G45-(G41),"不適用"),"") | H67: =IF(ISNUMBER(H45),IF(AND(ISNUMBER(H41)),H45-(H41),"不適用"),"")
A68: 差距｜EBITDA 率｜實際 vs 指引中點 | B68: pt | C68: =IF(ISNUMBER(C45),"不適用","") | D68: =IF(ISNUMBER(D45),"不適用","") | E68: =IF(ISNUMBER(E45),"不適用","") | F68: =IF(ISNUMBER(F45),"不適用","") | G68: =IF(ISNUMBER(G45),"不適用","") | H68: =IF(ISNUMBER(H45),"不適用","")
A69: 差距｜調整後營業利益｜模型 vs 共識 | B69: US$bn | C69: 不適用 | D69: 不適用 | E69: 不適用 | F69: 不適用 | G69: 不適用 | H69: 不適用
A70: 差距｜調整後營業利益｜模型 vs 指引中點 | B70: US$bn | C70: =IF(AND(ISNUMBER(C28),ISNUMBER(C31),ISNUMBER(C32)),C28-(((C31+C32)/2)),"不適用") -> -0.24341374 | D70: =IF(AND(ISNUMBER(D28),ISNUMBER(D31),ISNUMBER(D32)),D28-(((D31+D32)/2)),"不適用") -> 不適用 | E70: =IF(AND(ISNUMBER(E28),ISNUMBER(E31),ISNUMBER(E32)),E28-(((E31+E32)/2)),"不適用") -> 不適用 | F70: =IF(AND(ISNUMBER(F28),ISNUMBER(F31),ISNUMBER(F32)),F28-(((F31+F32)/2)),"不適用") -> 不適用 | G70: =IF(AND(ISNUMBER(G28),ISNUMBER(G31),ISNUMBER(G32)),G28-(((G31+G32)/2)),"不適用") -> 不適用 | H70: =IF(AND(ISNUMBER(H28),ISNUMBER(H31),ISNUMBER(H32)),H28-(((H31+H32)/2)),"不適用") -> 不適用
A71: 差距｜調整後營業利益｜實際 vs 模型 | B71: US$bn | C71: =IF(ISNUMBER(C46),IF(AND(ISNUMBER(C28)),C46-(C28),"不適用"),"") | D71: =IF(ISNUMBER(D46),IF(AND(ISNUMBER(D28)),D46-(D28),"不適用"),"") | E71: =IF(ISNUMBER(E46),IF(AND(ISNUMBER(E28)),E46-(E28),"不適用"),"") | F71: =IF(ISNUMBER(F46),IF(AND(ISNUMBER(F28)),F46-(F28),"不適用"),"") | G71: =IF(ISNUMBER(G46),IF(AND(ISNUMBER(G28)),G46-(G28),"不適用"),"") | H71: =IF(ISNUMBER(H46),IF(AND(ISNUMBER(H28)),H46-(H28),"不適用"),"")
A72: 差距｜調整後營業利益｜實際 vs 共識 | B72: US$bn | C72: =IF(ISNUMBER(C46),"不適用","") | D72: =IF(ISNUMBER(D46),"不適用","") | E72: =IF(ISNUMBER(E46),"不適用","") | F72: =IF(ISNUMBER(F46),"不適用","") | G72: =IF(ISNUMBER(G46),"不適用","") | H72: =IF(ISNUMBER(H46),"不適用","")
A73: 差距｜調整後營業利益｜實際 vs 指引中點 | B73: US$bn | C73: =IF(ISNUMBER(C46),IF(AND(ISNUMBER(C31),ISNUMBER(C32)),C46-(((C31+C32)/2)),"不適用"),"") | D73: =IF(ISNUMBER(D46),IF(AND(ISNUMBER(D31),ISNUMBER(D32)),D46-(((D31+D32)/2)),"不適用"),"") | E73: =IF(ISNUMBER(E46),IF(AND(ISNUMBER(E31),ISNUMBER(E32)),E46-(((E31+E32)/2)),"不適用"),"") | F73: =IF(ISNUMBER(F46),IF(AND(ISNUMBER(F31),ISNUMBER(F32)),F46-(((F31+F32)/2)),"不適用"),"") | G73: =IF(ISNUMBER(G46),IF(AND(ISNUMBER(G31),ISNUMBER(G32)),G46-(((G31+G32)/2)),"不適用"),"") | H73: =IF(ISNUMBER(H46),IF(AND(ISNUMBER(H31),ISNUMBER(H32)),H46-(((H31+H32)/2)),"不適用"),"")
A74: 差距｜調整後營業利益｜模型 vs 共識（利潤率 pt） | B74: pt | C74: 不適用 | D74: 不適用 | E74: 不適用 | F74: 不適用 | G74: 不適用 | H74: 不適用
A75: 差距｜調整後營業利益｜模型 vs 指引中點（利潤率 pt） | B75: pt | C75: =IF(AND(ISNUMBER(C28),ISNUMBER(C20),C20<>0,ISNUMBER(C31),ISNUMBER(C32),ISNUMBER(C29),ISNUMBER(C30)),C28/C20-((C31+C32)/2)/((C29+C30)/2),"不適用") -> -0.068910516 | D75: =IF(AND(ISNUMBER(D28),ISNUMBER(D20),D20<>0,ISNUMBER(D31),ISNUMBER(D32),ISNUMBER(D29),ISNUMBER(D30)),D28/D20-((D31+D32)/2)/((D29+D30)/2),"不適用") -> 不適用 | E75: =IF(AND(ISNUMBER(E28),ISNUMBER(E20),E20<>0,ISNUMBER(E31),ISNUMBER(E32),ISNUMBER(E29),ISNUMBER(E30)),E28/E20-((E31+E32)/2)/((E29+E30)/2),"不適用") -> 不適用 | F75: =IF(AND(ISNUMBER(F28),ISNUMBER(F20),F20<>0,ISNUMBER(F31),ISNUMBER(F32),ISNUMBER(F29),ISNUMBER(F30)),F28/F20-((F31+F32)/2)/((F29+F30)/2),"不適用") -> 不適用 | G75: =IF(AND(ISNUMBER(G28),ISNUMBER(G20),G20<>0,ISNUMBER(G31),ISNUMBER(G32),ISNUMBER(G29),ISNUMBER(G30)),G28/G20-((G31+G32)/2)/((G29+G30)/2),"不適用") -> 不適用 | H75: =IF(AND(ISNUMBER(H28),ISNUMBER(H20),H20<>0,ISNUMBER(H31),ISNUMBER(H32),ISNUMBER(H29),ISNUMBER(H30)),H28/H20-((H31+H32)/2)/((H29+H30)/2),"不適用") -> 不適用
A76: 差距｜調整後營業利益｜實際 vs 模型（利潤率 pt） | B76: pt | C76: =IF(ISNUMBER(C46),IF(AND(ISNUMBER(C46),ISNUMBER(C43),C43<>0,ISNUMBER(C28),ISNUMBER(C20),C20<>0),C46/C43-C28/C20,"不適用"),"") | D76: =IF(ISNUMBER(D46),IF(AND(ISNUMBER(D46),ISNUMBER(D43),D43<>0,ISNUMBER(D28),ISNUMBER(D20),D20<>0),D46/D43-D28/D20,"不適用"),"") | E76: =IF(ISNUMBER(E46),IF(AND(ISNUMBER(E46),ISNUMBER(E43),E43<>0,ISNUMBER(E28),ISNUMBER(E20),E20<>0),E46/E43-E28/E20,"不適用"),"") | F76: =IF(ISNUMBER(F46),IF(AND(ISNUMBER(F46),ISNUMBER(F43),F43<>0,ISNUMBER(F28),ISNUMBER(F20),F20<>0),F46/F43-F28/F20,"不適用"),"") | G76: =IF(ISNUMBER(G46),IF(AND(ISNUMBER(G46),ISNUMBER(G43),G43<>0,ISNUMBER(G28),ISNUMBER(G20),G20<>0),G46/G43-G28/G20,"不適用"),"") | H76: =IF(ISNUMBER(H46),IF(AND(ISNUMBER(H46),ISNUMBER(H43),H43<>0,ISNUMBER(H28),ISNUMBER(H20),H20<>0),H46/H43-H28/H20,"不適用"),"")
A77: 差距｜調整後營業利益｜實際 vs 共識（利潤率 pt） | B77: pt | C77: =IF(ISNUMBER(C46),"不適用","") | D77: =IF(ISNUMBER(D46),"不適用","") | E77: =IF(ISNUMBER(E46),"不適用","") | F77: =IF(ISNUMBER(F46),"不適用","") | G77: =IF(ISNUMBER(G46),"不適用","") | H77: =IF(ISNUMBER(H46),"不適用","")
A78: 差距｜調整後營業利益｜實際 vs 指引中點（利潤率 pt） | B78: pt | C78: =IF(ISNUMBER(C46),IF(AND(ISNUMBER(C46),ISNUMBER(C43),C43<>0,ISNUMBER(C31),ISNUMBER(C32),ISNUMBER(C29),ISNUMBER(C30)),C46/C43-((C31+C32)/2)/((C29+C30)/2),"不適用"),"") | D78: =IF(ISNUMBER(D46),IF(AND(ISNUMBER(D46),ISNUMBER(D43),D43<>0,ISNUMBER(D31),ISNUMBER(D32),ISNUMBER(D29),ISNUMBER(D30)),D46/D43-((D31+D32)/2)/((D29+D30)/2),"不適用"),"") | E78: =IF(ISNUMBER(E46),IF(AND(ISNUMBER(E46),ISNUMBER(E43),E43<>0,ISNUMBER(E31),ISNUMBER(E32),ISNUMBER(E29),ISNUMBER(E30)),E46/E43-((E31+E32)/2)/((E29+E30)/2),"不適用"),"") | F78: =IF(ISNUMBER(F46),IF(AND(ISNUMBER(F46),ISNUMBER(F43),F43<>0,ISNUMBER(F31),ISNUMBER(F32),ISNUMBER(F29),ISNUMBER(F30)),F46/F43-((F31+F32)/2)/((F29+F30)/2),"不適用"),"") | G78: =IF(ISNUMBER(G46),IF(AND(ISNUMBER(G46),ISNUMBER(G43),G43<>0,ISNUMBER(G31),ISNUMBER(G32),ISNUMBER(G29),ISNUMBER(G30)),G46/G43-((G31+G32)/2)/((G29+G30)/2),"不適用"),"") | H78: =IF(ISNUMBER(H46),IF(AND(ISNUMBER(H46),ISNUMBER(H43),H43<>0,ISNUMBER(H31),ISNUMBER(H32),ISNUMBER(H29),ISNUMBER(H30)),H46/H43-((H31+H32)/2)/((H29+H30)/2),"不適用"),"")
A79: 差距｜CapEx（毛額）｜模型 vs 共識 | B79: % | C79: 不適用 | D79: 不適用 | E79: 不適用 | F79: 不適用 | G79: 不適用 | H79: 不適用
A80: 差距｜CapEx（毛額）｜模型 vs 指引中點 | B80: % | C80: =IF(AND(ISNUMBER(C38),ISNUMBER(C34),ISNUMBER(C35)),C38/(((C34+C35)/2))-1,"不適用") -> 0 | D80: =IF(AND(ISNUMBER(D38),ISNUMBER(D34),ISNUMBER(D35)),D38/(((D34+D35)/2))-1,"不適用") -> 不適用 | E80: =IF(AND(ISNUMBER(E38),ISNUMBER(E34),ISNUMBER(E35)),E38/(((E34+E35)/2))-1,"不適用") -> 不適用 | F80: =IF(AND(ISNUMBER(F38),ISNUMBER(F34),ISNUMBER(F35)),F38/(((F34+F35)/2))-1,"不適用") -> 不適用 | G80: =IF(AND(ISNUMBER(G38),ISNUMBER(G34),ISNUMBER(G35)),G38/(((G34+G35)/2))-1,"不適用") -> 不適用 | H80: =IF(AND(ISNUMBER(H38),ISNUMBER(H34),ISNUMBER(H35)),H38/(((H34+H35)/2))-1,"不適用") -> 不適用
A81: 差距｜CapEx（毛額）｜實際 vs 模型 | B81: % | C81: =IF(ISNUMBER(C47),IF(AND(ISNUMBER(C38),C38<>0),C47/(C38)-1,"不適用"),"") | D81: =IF(ISNUMBER(D47),IF(AND(ISNUMBER(D38),D38<>0),D47/(D38)-1,"不適用"),"") | E81: =IF(ISNUMBER(E47),IF(AND(ISNUMBER(E38),E38<>0),E47/(E38)-1,"不適用"),"") | F81: =IF(ISNUMBER(F47),IF(AND(ISNUMBER(F38),F38<>0),F47/(F38)-1,"不適用"),"") | G81: =IF(ISNUMBER(G47),IF(AND(ISNUMBER(G38),G38<>0),G47/(G38)-1,"不適用"),"") | H81: =IF(ISNUMBER(H47),IF(AND(ISNUMBER(H38),H38<>0),H47/(H38)-1,"不適用"),"")
A82: 差距｜CapEx（毛額）｜實際 vs 共識 | B82: % | C82: =IF(ISNUMBER(C47),"不適用","") | D82: =IF(ISNUMBER(D47),"不適用","") | E82: =IF(ISNUMBER(E47),"不適用","") | F82: =IF(ISNUMBER(F47),"不適用","") | G82: =IF(ISNUMBER(G47),"不適用","") | H82: =IF(ISNUMBER(H47),"不適用","")
A83: 差距｜CapEx（毛額）｜實際 vs 指引中點 | B83: % | C83: =IF(ISNUMBER(C47),IF(AND(ISNUMBER(C34),ISNUMBER(C35)),C47/(((C34+C35)/2))-1,"不適用"),"") | D83: =IF(ISNUMBER(D47),IF(AND(ISNUMBER(D34),ISNUMBER(D35)),D47/(((D34+D35)/2))-1,"不適用"),"") | E83: =IF(ISNUMBER(E47),IF(AND(ISNUMBER(E34),ISNUMBER(E35)),E47/(((E34+E35)/2))-1,"不適用"),"") | F83: =IF(ISNUMBER(F47),IF(AND(ISNUMBER(F34),ISNUMBER(F35)),F47/(((F34+F35)/2))-1,"不適用"),"") | G83: =IF(ISNUMBER(G47),IF(AND(ISNUMBER(G34),ISNUMBER(G35)),G47/(((G34+G35)/2))-1,"不適用"),"") | H83: =IF(ISNUMBER(H47),IF(AND(ISNUMBER(H34),ISNUMBER(H35)),H47/(((H34+H35)/2))-1,"不適用"),"")
A84: 差距｜季末 Accepted MW｜模型 vs 共識 | B84: MW | C84: 不適用 | D84: 不適用 | E84: 不適用 | F84: 不適用 | G84: 不適用 | H84: 不適用
A85: 差距｜季末 Accepted MW｜模型 vs 指引中點 | B85: MW | C85: 不適用 | D85: 不適用 | E85: 不適用 | F85: 不適用 | G85: 不適用 | H85: 不適用
A86: 差距｜季末 Accepted MW｜實際 vs 模型 | B86: MW | C86: =IF(ISNUMBER(C48),IF(AND(ISNUMBER(C17)),C48-(C17),"不適用"),"") | D86: =IF(ISNUMBER(D48),IF(AND(ISNUMBER(D17)),D48-(D17),"不適用"),"") | E86: =IF(ISNUMBER(E48),IF(AND(ISNUMBER(E17)),E48-(E17),"不適用"),"") | F86: =IF(ISNUMBER(F48),IF(AND(ISNUMBER(F17)),F48-(F17),"不適用"),"") | G86: =IF(ISNUMBER(G48),IF(AND(ISNUMBER(G17)),G48-(G17),"不適用"),"") | H86: =IF(ISNUMBER(H48),IF(AND(ISNUMBER(H17)),H48-(H17),"不適用"),"")
A87: 差距｜季末 Accepted MW｜實際 vs 共識 | B87: MW | C87: =IF(ISNUMBER(C48),"不適用","") | D87: =IF(ISNUMBER(D48),"不適用","") | E87: =IF(ISNUMBER(E48),"不適用","") | F87: =IF(ISNUMBER(F48),"不適用","") | G87: =IF(ISNUMBER(G48),"不適用","") | H87: =IF(ISNUMBER(H48),"不適用","")
A88: 差距｜季末 Accepted MW｜實際 vs 指引中點 | B88: MW | C88: =IF(ISNUMBER(C48),"不適用","") | D88: =IF(ISNUMBER(D48),"不適用","") | E88: =IF(ISNUMBER(E48),"不適用","") | F88: =IF(ISNUMBER(F48),"不適用","") | G88: =IF(ISNUMBER(G48),"不適用","") | H88: =IF(ISNUMBER(H48),"不適用","")
A89: 合計基準｜營收｜vs 共識 | B89: US$bn | C89: =IF(COUNT(C39,D39)=2,C39+D39,"不適用") -> 8.247 | D89: =IF(COUNT(C39,D39)=2,C39+D39,"不適用") -> 8.247 | E89: =IF(COUNT(E39,F39,G39,H39)=4,E39+F39+G39+H39,"不適用") -> 不適用 | F89: =IF(COUNT(E39,F39,G39,H39)=4,E39+F39+G39+H39,"不適用") -> 不適用 | G89: =IF(COUNT(E39,F39,G39,H39)=4,E39+F39+G39+H39,"不適用") -> 不適用 | H89: =IF(COUNT(E39,F39,G39,H39)=4,E39+F39+G39+H39,"不適用") -> 不適用
A90: 拆解｜營收｜vs 共識｜水準 | B90: US$bn | C90: =IF(AND(ISNUMBER(C89),C89<>0,ISNUMBER(C39),ISNUMBER(C20)),(損益與評價!C8-C89)*(C39)/C89,"不適用") -> 0.07127513 | D90: =IF(AND(ISNUMBER(D89),D89<>0,ISNUMBER(D39),ISNUMBER(D20)),(損益與評價!C8-D89)*(D39)/D89,"不適用") -> 0.09472487 | E90: =IF(AND(ISNUMBER(E89),E89<>0,ISNUMBER(E39),ISNUMBER(E20)),(損益與評價!D8-E89)*(E39)/E89,"不適用") -> 不適用 | F90: =IF(AND(ISNUMBER(F89),F89<>0,ISNUMBER(F39),ISNUMBER(F20)),(損益與評價!D8-F89)*(F39)/F89,"不適用") -> 不適用 | G90: =IF(AND(ISNUMBER(G89),G89<>0,ISNUMBER(G39),ISNUMBER(G20)),(損益與評價!D8-G89)*(G39)/G89,"不適用") -> 不適用 | H90: =IF(AND(ISNUMBER(H89),H89<>0,ISNUMBER(H39),ISNUMBER(H20)),(損益與評價!D8-H89)*(H39)/H89,"不適用") -> 不適用
A91: 拆解｜營收｜vs 共識｜分配 | B91: US$bn | C91: =IF(AND(ISNUMBER(C89),C89<>0,ISNUMBER(C39),ISNUMBER(C20)),(C20/損益與評價!C8-(C39)/C89)*損益與評價!C8,"不適用") -> 0.050391536 | D91: =IF(AND(ISNUMBER(D89),D89<>0,ISNUMBER(D39),ISNUMBER(D20)),(D20/損益與評價!C8-(D39)/D89)*損益與評價!C8,"不適用") -> -0.050391536 | E91: =IF(AND(ISNUMBER(E89),E89<>0,ISNUMBER(E39),ISNUMBER(E20)),(E20/損益與評價!D8-(E39)/E89)*損益與評價!D8,"不適用") -> 不適用 | F91: =IF(AND(ISNUMBER(F89),F89<>0,ISNUMBER(F39),ISNUMBER(F20)),(F20/損益與評價!D8-(F39)/F89)*損益與評價!D8,"不適用") -> 不適用 | G91: =IF(AND(ISNUMBER(G89),G89<>0,ISNUMBER(G39),ISNUMBER(G20)),(G20/損益與評價!D8-(G39)/G89)*損益與評價!D8,"不適用") -> 不適用 | H91: =IF(AND(ISNUMBER(H89),H89<>0,ISNUMBER(H39),ISNUMBER(H20)),(H20/損益與評價!D8-(H39)/H89)*損益與評價!D8,"不適用") -> 不適用
A92: 合計基準｜營收｜vs 指引 | B92: US$bn | C92: =(輸入與假設!$C$169+輸入與假設!$D$169)/2-輸入與假設!$E$169 -> 8.147 | D92: =(輸入與假設!$C$169+輸入與假設!$D$169)/2-輸入與假設!$E$169 -> 8.147 | E92: 不適用 | F92: 不適用 | G92: 不適用 | H92: 不適用
A93: 拆解｜營收｜vs 指引｜水準 | B93: US$bn | C93: =IF(AND(ISNUMBER(C92),C92<>0,ISNUMBER(((C29+C30)/2)),ISNUMBER(C20)),(損益與評價!C8-C92)*(((C29+C30)/2))/C92,"不適用") -> 0.11509144 | D93: =IF(AND(ISNUMBER(D92),D92<>0,ISNUMBER(((D29+D30)/2)),ISNUMBER(D20)),(損益與評價!C8-D92)*(((D29+D30)/2))/D92,"不適用") -> 不適用 | E93: =IF(AND(ISNUMBER(E92),E92<>0,ISNUMBER(((E29+E30)/2)),ISNUMBER(E20)),(損益與評價!D8-E92)*(((E29+E30)/2))/E92,"不適用") -> 不適用 | F93: =IF(AND(ISNUMBER(F92),F92<>0,ISNUMBER(((F29+F30)/2)),ISNUMBER(F20)),(損益與評價!D8-F92)*(((F29+F30)/2))/F92,"不適用") -> 不適用 | G93: =IF(AND(ISNUMBER(G92),G92<>0,ISNUMBER(((G29+G30)/2)),ISNUMBER(G20)),(損益與評價!D8-G92)*(((G29+G30)/2))/G92,"不適用") -> 不適用 | H93: =IF(AND(ISNUMBER(H92),H92<>0,ISNUMBER(((H29+H30)/2)),ISNUMBER(H20)),(損益與評價!D8-H92)*(((H29+H30)/2))/H92,"不適用") -> 不適用
A94: 拆解｜營收｜vs 指引｜分配 | B94: US$bn | C94: =IF(AND(ISNUMBER(C92),C92<>0,ISNUMBER(((C29+C30)/2)),ISNUMBER(C20)),(C20/損益與評價!C8-(((C29+C30)/2))/C92)*損益與評價!C8,"不適用") -> 0.022575222 | D94: =IF(AND(ISNUMBER(D92),D92<>0,ISNUMBER(((D29+D30)/2)),ISNUMBER(D20)),(D20/損益與評價!C8-(((D29+D30)/2))/D92)*損益與評價!C8,"不適用") -> 不適用 | E94: =IF(AND(ISNUMBER(E92),E92<>0,ISNUMBER(((E29+E30)/2)),ISNUMBER(E20)),(E20/損益與評價!D8-(((E29+E30)/2))/E92)*損益與評價!D8,"不適用") -> 不適用 | F94: =IF(AND(ISNUMBER(F92),F92<>0,ISNUMBER(((F29+F30)/2)),ISNUMBER(F20)),(F20/損益與評價!D8-(((F29+F30)/2))/F92)*損益與評價!D8,"不適用") -> 不適用 | G94: =IF(AND(ISNUMBER(G92),G92<>0,ISNUMBER(((G29+G30)/2)),ISNUMBER(G20)),(G20/損益與評價!D8-(((G29+G30)/2))/G92)*損益與評價!D8,"不適用") -> 不適用 | H94: =IF(AND(ISNUMBER(H92),H92<>0,ISNUMBER(((H29+H30)/2)),ISNUMBER(H20)),(H20/損益與評價!D8-(((H29+H30)/2))/H92)*損益與評價!D8,"不適用") -> 不適用
A95: 原因｜營收｜vs 共識 | C95: =IF(ISNUMBER(C49),IF(ABS(C49)>輸入與假設!$C$150,IF(ISNUMBER(C90),IF(ABS(C91)>ABS(C90),"營收 vs 共識 "&IF(C49<0,"−","+")&TEXT(ABS(C49)*100,"#,##0.0")&"%"&"：拆法（分配 "&IF(C91<0,"−","+")&IF(ABS(C91)<0,"−","")&"$"&TEXT(ABS(ABS(C91)),"#,##0.000")&"bn"&"（Q3'26 占 2H26 "&TEXT((C20/損益與評價!C8)*100,"#,##0.0")&"%"&"，共識合計 "&TEXT(((C39)/C89)*100,"#,##0.0")&"%"&"）；水準 "&IF(C90<0,"−","+")&IF(ABS(C90)<0,"−","")&"$"&TEXT(ABS(ABS(C90)),"#,##0.000")&"bn"&"）","營收 vs 共識 "&IF(C49<0,"−","+")&TEXT(ABS(C49)*100,"#,##0.0")&"%"&"：觀點（水準 "&IF(C90<0,"−","+")&IF(ABS(C90)<0,"−","")&"$"&TEXT(ABS(ABS(C90)),"#,##0.000")&"bn"&"（2H26 模型 "&IF(損益與評價!C8<0,"−","")&"$"&TEXT(ABS(損益與評價!C8),"#,##0.000")&"bn"&"，共識合計 "&IF(C89<0,"−","")&"$"&TEXT(ABS(C89),"#,##0.000")&"bn"&"）；分配 "&IF(C91<0,"−","+")&IF(ABS(C91)<0,"−","")&"$"&TEXT(ABS(ABS(C91)),"#,##0.000")&"bn"&"）"),"營收 vs 共識 "&IF(C49<0,"−","+")&TEXT(ABS(C49)*100,"#,##0.0")&"%"&"：未歸類（差異原因待補）"),""),"") | D95: =IF(ISNUMBER(D49),IF(ABS(D49)>輸入與假設!$C$150,IF(ISNUMBER(D90),IF(ABS(D91)>ABS(D90),"營收 vs 共識 "&IF(D49<0,"−","+")&TEXT(ABS(D49)*100,"#,##0.0")&"%"&"：拆法（分配 "&IF(D91<0,"−","+")&IF(ABS(D91)<0,"−","")&"$"&TEXT(ABS(ABS(D91)),"#,##0.000")&"bn"&"（Q4'26 占 2H26 "&TEXT((D20/損益與評價!C8)*100,"#,##0.0")&"%"&"，共識合計 "&TEXT(((D39)/D89)*100,"#,##0.0")&"%"&"）；水準 "&IF(D90<0,"−","+")&IF(ABS(D90)<0,"−","")&"$"&TEXT(ABS(ABS(D90)),"#,##0.000")&"bn"&"）","營收 vs 共識 "&IF(D49<0,"−","+")&TEXT(ABS(D49)*100,"#,##0.0")&"%"&"：觀點（水準 "&IF(D90<0,"−","+")&IF(ABS(D90)<0,"−","")&"$"&TEXT(ABS(ABS(D90)),"#,##0.000")&"bn"&"（2H26 模型 "&IF(損益與評價!C8<0,"−","")&"$"&TEXT(ABS(損益與評價!C8),"#,##0.000")&"bn"&"，共識合計 "&IF(D89<0,"−","")&"$"&TEXT(ABS(D89),"#,##0.000")&"bn"&"）；分配 "&IF(D91<0,"−","+")&IF(ABS(D91)<0,"−","")&"$"&TEXT(ABS(ABS(D91)),"#,##0.000")&"bn"&"）"),"營收 vs 共識 "&IF(D49<0,"−","+")&TEXT(ABS(D49)*100,"#,##0.0")&"%"&"：未歸類（差異原因待補）"),""),"") | E95: =IF(ISNUMBER(E49),IF(ABS(E49)>輸入與假設!$C$150,IF(ISNUMBER(E90),IF(ABS(E91)>ABS(E90),"營收 vs 共識 "&IF(E49<0,"−","+")&TEXT(ABS(E49)*100,"#,##0.0")&"%"&"：拆法（分配 "&IF(E91<0,"−","+")&IF(ABS(E91)<0,"−","")&"$"&TEXT(ABS(ABS(E91)),"#,##0.000")&"bn"&"（Q1'27 占 FY27 "&TEXT((E20/損益與評價!D8)*100,"#,##0.0")&"%"&"，共識合計 "&TEXT(((E39)/E89)*100,"#,##0.0")&"%"&"）；水準 "&IF(E90<0,"−","+")&IF(ABS(E90)<0,"−","")&"$"&TEXT(ABS(ABS(E90)),"#,##0.000")&"bn"&"）","營收 vs 共識 "&IF(E49<0,"−","+")&TEXT(ABS(E49)*100,"#,##0.0")&"%"&"：觀點（水準 "&IF(E90<0,"−","+")&IF(ABS(E90)<0,"−","")&"$"&TEXT(ABS(ABS(E90)),"#,##0.000")&"bn"&"（FY27 模型 "&IF(損益與評價!D8<0,"−","")&"$"&TEXT(ABS(損益與評價!D8),"#,##0.000")&"bn"&"，共識合計 "&IF(E89<0,"−","")&"$"&TEXT(ABS(E89),"#,##0.000")&"bn"&"）；分配 "&IF(E91<0,"−","+")&IF(ABS(E91)<0,"−","")&"$"&TEXT(ABS(ABS(E91)),"#,##0.000")&"bn"&"）"),"營收 vs 共識 "&IF(E49<0,"−","+")&TEXT(ABS(E49)*100,"#,##0.0")&"%"&"：未歸類（差異原因待補）"),""),"") | F95: =IF(ISNUMBER(F49),IF(ABS(F49)>輸入與假設!$C$150,IF(ISNUMBER(F90),IF(ABS(F91)>ABS(F90),"營收 vs 共識 "&IF(F49<0,"−","+")&TEXT(ABS(F49)*100,"#,##0.0")&"%"&"：拆法（分配 "&IF(F91<0,"−","+")&IF(ABS(F91)<0,"−","")&"$"&TEXT(ABS(ABS(F91)),"#,##0.000")&"bn"&"（Q2'27 占 FY27 "&TEXT((F20/損益與評價!D8)*100,"#,##0.0")&"%"&"，共識合計 "&TEXT(((F39)/F89)*100,"#,##0.0")&"%"&"）；水準 "&IF(F90<0,"−","+")&IF(ABS(F90)<0,"−","")&"$"&TEXT(ABS(ABS(F90)),"#,##0.000")&"bn"&"）","營收 vs 共識 "&IF(F49<0,"−","+")&TEXT(ABS(F49)*100,"#,##0.0")&"%"&"：觀點（水準 "&IF(F90<0,"−","+")&IF(ABS(F90)<0,"−","")&"$"&TEXT(ABS(ABS(F90)),"#,##0.000")&"bn"&"（FY27 模型 "&IF(損益與評價!D8<0,"−","")&"$"&TEXT(ABS(損益與評價!D8),"#,##0.000")&"bn"&"，共識合計 "&IF(F89<0,"−","")&"$"&TEXT(ABS(F89),"#,##0.000")&"bn"&"）；分配 "&IF(F91<0,"−","+")&IF(ABS(F91)<0,"−","")&"$"&TEXT(ABS(ABS(F91)),"#,##0.000")&"bn"&"）"),"營收 vs 共識 "&IF(F49<0,"−","+")&TEXT(ABS(F49)*100,"#,##0.0")&"%"&"：未歸類（差異原因待補）"),""),"") | G95: =IF(ISNUMBER(G49),IF(ABS(G49)>輸入與假設!$C$150,IF(ISNUMBER(G90),IF(ABS(G91)>ABS(G90),"營收 vs 共識 "&IF(G49<0,"−","+")&TEXT(ABS(G49)*100,"#,##0.0")&"%"&"：拆法（分配 "&IF(G91<0,"−","+")&IF(ABS(G91)<0,"−","")&"$"&TEXT(ABS(ABS(G91)),"#,##0.000")&"bn"&"（Q3'27 占 FY27 "&TEXT((G20/損益與評價!D8)*100,"#,##0.0")&"%"&"，共識合計 "&TEXT(((G39)/G89)*100,"#,##0.0")&"%"&"）；水準 "&IF(G90<0,"−","+")&IF(ABS(G90)<0,"−","")&"$"&TEXT(ABS(ABS(G90)),"#,##0.000")&"bn"&"）","營收 vs 共識 "&IF(G49<0,"−","+")&TEXT(ABS(G49)*100,"#,##0.0")&"%"&"：觀點（水準 "&IF(G90<0,"−","+")&IF(ABS(G90)<0,"−","")&"$"&TEXT(ABS(ABS(G90)),"#,##0.000")&"bn"&"（FY27 模型 "&IF(損益與評價!D8<0,"−","")&"$"&TEXT(ABS(損益與評價!D8),"#,##0.000")&"bn"&"，共識合計 "&IF(G89<0,"−","")&"$"&TEXT(ABS(G89),"#,##0.000")&"bn"&"）；分配 "&IF(G91<0,"−","+")&IF(ABS(G91)<0,"−","")&"$"&TEXT(ABS(ABS(G91)),"#,##0.000")&"bn"&"）"),"營收 vs 共識 "&IF(G49<0,"−","+")&TEXT(ABS(G49)*100,"#,##0.0")&"%"&"：未歸類（差異原因待補）"),""),"") | H95: =IF(ISNUMBER(H49),IF(ABS(H49)>輸入與假設!$C$150,IF(ISNUMBER(H90),IF(ABS(H91)>ABS(H90),"營收 vs 共識 "&IF(H49<0,"−","+")&TEXT(ABS(H49)*100,"#,##0.0")&"%"&"：拆法（分配 "&IF(H91<0,"−","+")&IF(ABS(H91)<0,"−","")&"$"&TEXT(ABS(ABS(H91)),"#,##0.000")&"bn"&"（Q4'27 占 FY27 "&TEXT((H20/損益與評價!D8)*100,"#,##0.0")&"%"&"，共識合計 "&TEXT(((H39)/H89)*100,"#,##0.0")&"%"&"）；水準 "&IF(H90<0,"−","+")&IF(ABS(H90)<0,"−","")&"$"&TEXT(ABS(ABS(H90)),"#,##0.000")&"bn"&"）","營收 vs 共識 "&IF(H49<0,"−","+")&TEXT(ABS(H49)*100,"#,##0.0")&"%"&"：觀點（水準 "&IF(H90<0,"−","+")&IF(ABS(H90)<0,"−","")&"$"&TEXT(ABS(ABS(H90)),"#,##0.000")&"bn"&"（FY27 模型 "&IF(損益與評價!D8<0,"−","")&"$"&TEXT(ABS(損益與評價!D8),"#,##0.000")&"bn"&"，共識合計 "&IF(H89<0,"−","")&"$"&TEXT(ABS(H89),"#,##0.000")&"bn"&"）；分配 "&IF(H91<0,"−","+")&IF(ABS(H91)<0,"−","")&"$"&TEXT(ABS(ABS(H91)),"#,##0.000")&"bn"&"）"),"營收 vs 共識 "&IF(H49<0,"−","+")&TEXT(ABS(H49)*100,"#,##0.0")&"%"&"：未歸類（差異原因待補）"),""),"")
A96: 原因類型｜營收｜vs 共識 | C96: =IF(ISNUMBER(C49),IF(ABS(C49)>輸入與假設!$C$150,IF(ISNUMBER(C90),IF(ABS(C91)>ABS(C90),"拆法","觀點"),"未歸類"),""),"") | D96: =IF(ISNUMBER(D49),IF(ABS(D49)>輸入與假設!$C$150,IF(ISNUMBER(D90),IF(ABS(D91)>ABS(D90),"拆法","觀點"),"未歸類"),""),"") | E96: =IF(ISNUMBER(E49),IF(ABS(E49)>輸入與假設!$C$150,IF(ISNUMBER(E90),IF(ABS(E91)>ABS(E90),"拆法","觀點"),"未歸類"),""),"") | F96: =IF(ISNUMBER(F49),IF(ABS(F49)>輸入與假設!$C$150,IF(ISNUMBER(F90),IF(ABS(F91)>ABS(F90),"拆法","觀點"),"未歸類"),""),"") | G96: =IF(ISNUMBER(G49),IF(ABS(G49)>輸入與假設!$C$150,IF(ISNUMBER(G90),IF(ABS(G91)>ABS(G90),"拆法","觀點"),"未歸類"),""),"") | H96: =IF(ISNUMBER(H49),IF(ABS(H49)>輸入與假設!$C$150,IF(ISNUMBER(H90),IF(ABS(H91)>ABS(H90),"拆法","觀點"),"未歸類"),""),"")
A97: 原因｜營收｜vs 指引中點 | C97: =IF(ISNUMBER(C50),IF(OR(ABS(C50)>輸入與假設!$C$150,C20>C30,C20<C29),IF(ISNUMBER(C93),IF(ABS(C94)>ABS(C93),"營收 vs 指引中點 "&IF(C50<0,"−","+")&TEXT(ABS(C50)*100,"#,##0.0")&"%"&"：拆法（分配 "&IF(C94<0,"−","+")&IF(ABS(C94)<0,"−","")&"$"&TEXT(ABS(ABS(C94)),"#,##0.000")&"bn"&"（Q3'26 占 2H26 "&TEXT((C20/損益與評價!C8)*100,"#,##0.0")&"%"&"，指引隱含 "&TEXT(((((C29+C30)/2))/C92)*100,"#,##0.0")&"%"&"）；水準 "&IF(C93<0,"−","+")&IF(ABS(C93)<0,"−","")&"$"&TEXT(ABS(ABS(C93)),"#,##0.000")&"bn"&"）","營收 vs 指引中點 "&IF(C50<0,"−","+")&TEXT(ABS(C50)*100,"#,##0.0")&"%"&"：觀點（水準 "&IF(C93<0,"−","+")&IF(ABS(C93)<0,"−","")&"$"&TEXT(ABS(ABS(C93)),"#,##0.000")&"bn"&"（2H26 模型 "&IF(損益與評價!C8<0,"−","")&"$"&TEXT(ABS(損益與評價!C8),"#,##0.000")&"bn"&"，指引隱含 "&IF(C92<0,"−","")&"$"&TEXT(ABS(C92),"#,##0.000")&"bn"&"）；分配 "&IF(C94<0,"−","+")&IF(ABS(C94)<0,"−","")&"$"&TEXT(ABS(ABS(C94)),"#,##0.000")&"bn"&"）"),"營收 vs 指引中點 "&IF(C50<0,"−","+")&TEXT(ABS(C50)*100,"#,##0.0")&"%"&"：未歸類（差異原因待補）"),""),"") -> 營收 vs 指引中點 +3.9%：觀點（水準 +$0.115bn（2H26 模型 $8.413bn，指引隱含 $8.147bn）；分配 +$0.023bn） | D97: =IF(ISNUMBER(D50),IF(OR(ABS(D50)>輸入與假設!$C$150,D20>D30,D20<D29),IF(ISNUMBER(D93),IF(ABS(D94)>ABS(D93),"營收 vs 指引中點 "&IF(D50<0,"−","+")&TEXT(ABS(D50)*100,"#,##0.0")&"%"&"：拆法（分配 "&IF(D94<0,"−","+")&IF(ABS(D94)<0,"−","")&"$"&TEXT(ABS(ABS(D94)),"#,##0.000")&"bn"&"（Q4'26 占 2H26 "&TEXT((D20/損益與評價!C8)*100,"#,##0.0")&"%"&"，指引隱含 "&TEXT(((((D29+D30)/2))/D92)*100,"#,##0.0")&"%"&"）；水準 "&IF(D93<0,"−","+")&IF(ABS(D93)<0,"−","")&"$"&TEXT(ABS(ABS(D93)),"#,##0.000")&"bn"&"）","營收 vs 指引中點 "&IF(D50<0,"−","+")&TEXT(ABS(D50)*100,"#,##0.0")&"%"&"：觀點（水準 "&IF(D93<0,"−","+")&IF(ABS(D93)<0,"−","")&"$"&TEXT(ABS(ABS(D93)),"#,##0.000")&"bn"&"（2H26 模型 "&IF(損益與評價!C8<0,"−","")&"$"&TEXT(ABS(損益與評價!C8),"#,##0.000")&"bn"&"，指引隱含 "&IF(D92<0,"−","")&"$"&TEXT(ABS(D92),"#,##0.000")&"bn"&"）；分配 "&IF(D94<0,"−","+")&IF(ABS(D94)<0,"−","")&"$"&TEXT(ABS(ABS(D94)),"#,##0.000")&"bn"&"）"),"營收 vs 指引中點 "&IF(D50<0,"−","+")&TEXT(ABS(D50)*100,"#,##0.0")&"%"&"：未歸類（差異原因待補）"),""),"") | E97: =IF(ISNUMBER(E50),IF(OR(ABS(E50)>輸入與假設!$C$150,E20>E30,E20<E29),IF(ISNUMBER(E93),IF(ABS(E94)>ABS(E93),"營收 vs 指引中點 "&IF(E50<0,"−","+")&TEXT(ABS(E50)*100,"#,##0.0")&"%"&"：拆法（分配 "&IF(E94<0,"−","+")&IF(ABS(E94)<0,"−","")&"$"&TEXT(ABS(ABS(E94)),"#,##0.000")&"bn"&"（Q1'27 占 FY27 "&TEXT((E20/損益與評價!D8)*100,"#,##0.0")&"%"&"，指引隱含 "&TEXT(((((E29+E30)/2))/E92)*100,"#,##0.0")&"%"&"）；水準 "&IF(E93<0,"−","+")&IF(ABS(E93)<0,"−","")&"$"&TEXT(ABS(ABS(E93)),"#,##0.000")&"bn"&"）","營收 vs 指引中點 "&IF(E50<0,"−","+")&TEXT(ABS(E50)*100,"#,##0.0")&"%"&"：觀點（水準 "&IF(E93<0,"−","+")&IF(ABS(E93)<0,"−","")&"$"&TEXT(ABS(ABS(E93)),"#,##0.000")&"bn"&"（FY27 模型 "&IF(損益與評價!D8<0,"−","")&"$"&TEXT(ABS(損益與評價!D8),"#,##0.000")&"bn"&"，指引隱含 "&IF(E92<0,"−","")&"$"&TEXT(ABS(E92),"#,##0.000")&"bn"&"）；分配 "&IF(E94<0,"−","+")&IF(ABS(E94)<0,"−","")&"$"&TEXT(ABS(ABS(E94)),"#,##0.000")&"bn"&"）"),"營收 vs 指引中點 "&IF(E50<0,"−","+")&TEXT(ABS(E50)*100,"#,##0.0")&"%"&"：未歸類（差異原因待補）"),""),"") | F97: =IF(ISNUMBER(F50),IF(OR(ABS(F50)>輸入與假設!$C$150,F20>F30,F20<F29),IF(ISNUMBER(F93),IF(ABS(F94)>ABS(F93),"營收 vs 指引中點 "&IF(F50<0,"−","+")&TEXT(ABS(F50)*100,"#,##0.0")&"%"&"：拆法（分配 "&IF(F94<0,"−","+")&IF(ABS(F94)<0,"−","")&"$"&TEXT(ABS(ABS(F94)),"#,##0.000")&"bn"&"（Q2'27 占 FY27 "&TEXT((F20/損益與評價!D8)*100,"#,##0.0")&"%"&"，指引隱含 "&TEXT(((((F29+F30)/2))/F92)*100,"#,##0.0")&"%"&"）；水準 "&IF(F93<0,"−","+")&IF(ABS(F93)<0,"−","")&"$"&TEXT(ABS(ABS(F93)),"#,##0.000")&"bn"&"）","營收 vs 指引中點 "&IF(F50<0,"−","+")&TEXT(ABS(F50)*100,"#,##0.0")&"%"&"：觀點（水準 "&IF(F93<0,"−","+")&IF(ABS(F93)<0,"−","")&"$"&TEXT(ABS(ABS(F93)),"#,##0.000")&"bn"&"（FY27 模型 "&IF(損益與評價!D8<0,"−","")&"$"&TEXT(ABS(損益與評價!D8),"#,##0.000")&"bn"&"，指引隱含 "&IF(F92<0,"−","")&"$"&TEXT(ABS(F92),"#,##0.000")&"bn"&"）；分配 "&IF(F94<0,"−","+")&IF(ABS(F94)<0,"−","")&"$"&TEXT(ABS(ABS(F94)),"#,##0.000")&"bn"&"）"),"營收 vs 指引中點 "&IF(F50<0,"−","+")&TEXT(ABS(F50)*100,"#,##0.0")&"%"&"：未歸類（差異原因待補）"),""),"") | G97: =IF(ISNUMBER(G50),IF(OR(ABS(G50)>輸入與假設!$C$150,G20>G30,G20<G29),IF(ISNUMBER(G93),IF(ABS(G94)>ABS(G93),"營收 vs 指引中點 "&IF(G50<0,"−","+")&TEXT(ABS(G50)*100,"#,##0.0")&"%"&"：拆法（分配 "&IF(G94<0,"−","+")&IF(ABS(G94)<0,"−","")&"$"&TEXT(ABS(ABS(G94)),"#,##0.000")&"bn"&"（Q3'27 占 FY27 "&TEXT((G20/損益與評價!D8)*100,"#,##0.0")&"%"&"，指引隱含 "&TEXT(((((G29+G30)/2))/G92)*100,"#,##0.0")&"%"&"）；水準 "&IF(G93<0,"−","+")&IF(ABS(G93)<0,"−","")&"$"&TEXT(ABS(ABS(G93)),"#,##0.000")&"bn"&"）","營收 vs 指引中點 "&IF(G50<0,"−","+")&TEXT(ABS(G50)*100,"#,##0.0")&"%"&"：觀點（水準 "&IF(G93<0,"−","+")&IF(ABS(G93)<0,"−","")&"$"&TEXT(ABS(ABS(G93)),"#,##0.000")&"bn"&"（FY27 模型 "&IF(損益與評價!D8<0,"−","")&"$"&TEXT(ABS(損益與評價!D8),"#,##0.000")&"bn"&"，指引隱含 "&IF(G92<0,"−","")&"$"&TEXT(ABS(G92),"#,##0.000")&"bn"&"）；分配 "&IF(G94<0,"−","+")&IF(ABS(G94)<0,"−","")&"$"&TEXT(ABS(ABS(G94)),"#,##0.000")&"bn"&"）"),"營收 vs 指引中點 "&IF(G50<0,"−","+")&TEXT(ABS(G50)*100,"#,##0.0")&"%"&"：未歸類（差異原因待補）"),""),"") | H97: =IF(ISNUMBER(H50),IF(OR(ABS(H50)>輸入與假設!$C$150,H20>H30,H20<H29),IF(ISNUMBER(H93),IF(ABS(H94)>ABS(H93),"營收 vs 指引中點 "&IF(H50<0,"−","+")&TEXT(ABS(H50)*100,"#,##0.0")&"%"&"：拆法（分配 "&IF(H94<0,"−","+")&IF(ABS(H94)<0,"−","")&"$"&TEXT(ABS(ABS(H94)),"#,##0.000")&"bn"&"（Q4'27 占 FY27 "&TEXT((H20/損益與評價!D8)*100,"#,##0.0")&"%"&"，指引隱含 "&TEXT(((((H29+H30)/2))/H92)*100,"#,##0.0")&"%"&"）；水準 "&IF(H93<0,"−","+")&IF(ABS(H93)<0,"−","")&"$"&TEXT(ABS(ABS(H93)),"#,##0.000")&"bn"&"）","營收 vs 指引中點 "&IF(H50<0,"−","+")&TEXT(ABS(H50)*100,"#,##0.0")&"%"&"：觀點（水準 "&IF(H93<0,"−","+")&IF(ABS(H93)<0,"−","")&"$"&TEXT(ABS(ABS(H93)),"#,##0.000")&"bn"&"（FY27 模型 "&IF(損益與評價!D8<0,"−","")&"$"&TEXT(ABS(損益與評價!D8),"#,##0.000")&"bn"&"，指引隱含 "&IF(H92<0,"−","")&"$"&TEXT(ABS(H92),"#,##0.000")&"bn"&"）；分配 "&IF(H94<0,"−","+")&IF(ABS(H94)<0,"−","")&"$"&TEXT(ABS(ABS(H94)),"#,##0.000")&"bn"&"）"),"營收 vs 指引中點 "&IF(H50<0,"−","+")&TEXT(ABS(H50)*100,"#,##0.0")&"%"&"：未歸類（差異原因待補）"),""),"")
A98: 原因類型｜營收｜vs 指引中點 | C98: =IF(ISNUMBER(C50),IF(OR(ABS(C50)>輸入與假設!$C$150,C20>C30,C20<C29),IF(ISNUMBER(C93),IF(ABS(C94)>ABS(C93),"拆法","觀點"),"未歸類"),""),"") -> 觀點 | D98: =IF(ISNUMBER(D50),IF(OR(ABS(D50)>輸入與假設!$C$150,D20>D30,D20<D29),IF(ISNUMBER(D93),IF(ABS(D94)>ABS(D93),"拆法","觀點"),"未歸類"),""),"") | E98: =IF(ISNUMBER(E50),IF(OR(ABS(E50)>輸入與假設!$C$150,E20>E30,E20<E29),IF(ISNUMBER(E93),IF(ABS(E94)>ABS(E93),"拆法","觀點"),"未歸類"),""),"") | F98: =IF(ISNUMBER(F50),IF(OR(ABS(F50)>輸入與假設!$C$150,F20>F30,F20<F29),IF(ISNUMBER(F93),IF(ABS(F94)>ABS(F93),"拆法","觀點"),"未歸類"),""),"") | G98: =IF(ISNUMBER(G50),IF(OR(ABS(G50)>輸入與假設!$C$150,G20>G30,G20<G29),IF(ISNUMBER(G93),IF(ABS(G94)>ABS(G93),"拆法","觀點"),"未歸類"),""),"") | H98: =IF(ISNUMBER(H50),IF(OR(ABS(H50)>輸入與假設!$C$150,H20>H30,H20<H29),IF(ISNUMBER(H93),IF(ABS(H94)>ABS(H93),"拆法","觀點"),"未歸類"),""),"")
A99: 原因｜營收｜實際 vs 模型
A100: 原因類型｜營收｜實際 vs 模型
A101: 合計基準｜調整後 EBITDA｜vs 共識 | B101: US$bn | C101: =IF(COUNT(C40,D40)=2,C40+D40,"不適用") -> 4.944 | D101: =IF(COUNT(C40,D40)=2,C40+D40,"不適用") -> 4.944 | E101: =IF(COUNT(E40,F40,G40,H40)=4,E40+F40+G40+H40,"不適用") -> 不適用 | F101: =IF(COUNT(E40,F40,G40,H40)=4,E40+F40+G40+H40,"不適用") -> 不適用 | G101: =IF(COUNT(E40,F40,G40,H40)=4,E40+F40+G40+H40,"不適用") -> 不適用 | H101: =IF(COUNT(E40,F40,G40,H40)=4,E40+F40+G40+H40,"不適用") -> 不適用
...

Sheet 產能與收入
A1: 產能與收入 — 合約排程 vs 機房產能
A2: 兩條線獨立產生後相減：排程>容量→瓶頸（收不到）；容量>排程→剩餘產能（要靠新簽約賣掉）
A3: FY26 欄口徑：MW 為年底存量；標示「（模型期）」的收入列只含 2026 下半年——RPO 桶自 2026-06-30 起算，1H 收入已實現、不再受產能約束。1H 實際單列，兩者相加即 FY26 全年（見本頁「FY26 全年」列）。
A5: 模型期長度（年） | C5: =輸入與假設!C$21 -> 0.5 | D5: =輸入與假設!D$21 -> 1 | E5: =輸入與假設!E$21 -> 1 | F5: =輸入與假設!F$21 -> 1 | G5: =輸入與假設!G$21 -> 1
A6: （A）機房：容量上限
A7: Accepted MW（已驗收，單調不減） | B7: MW | C7: =MAX(0,輸入與假設!C$23) -> 1850 | D7: =MAX(輸入與假設!D$23,C7) -> 3100 | E7: =MAX(輸入與假設!E$23,D7) -> 4000 | F7: =MAX(輸入與假設!F$23,E7) -> 4800 | G7: =MAX(輸入與假設!G$23,F7) -> 5600
A8: Billable MW（上限為 Accepted） | B8: MW | C8: =MIN(MAX(0,輸入與假設!C$24),C7) -> 1700 | D8: =MIN(MAX(0,輸入與假設!D$24),D7) -> 2900 | E8: =MIN(MAX(0,輸入與假設!E$24),E7) -> 3739 | F8: =MIN(MAX(0,輸入與假設!F$24),F7) -> 4495 | G8: =MIN(MAX(0,輸入與假設!G$24),G7) -> 5250
A9: 期初在役 MW | B9: MW | C9: =輸入與假設!$C$18 -> 1350 | D9: =C8 -> 1700 | E9: =D8 -> 2900 | F9: =E8 -> 3739 | G9: =F8 -> 4495
A10: 平均在役 MW（FY26 欄為下半年平均） | B10: MW | C10: =IF(輸入與假設!$C$19=1,(C9+C8)/2,C8) -> 1525 | D10: =IF(輸入與假設!$C$19=1,(D9+D8)/2,D8) -> 2300 | E10: =IF(輸入與假設!$C$19=1,(E9+E8)/2,E8) -> 3319.5 | F10: =IF(輸入與假設!$C$19=1,(F9+F8)/2,F8) -> 4117 | G10: =IF(輸入與假設!$C$19=1,(G9+G8)/2,G8) -> 4872.5
A11: 容量上限（模型期最多能交付的收入） | B11: US$bn | C11: =C10*輸入與假設!C$26*輸入與假設!$C$20*輸入與假設!C$25*C5 -> 8.113 | D11: =D10*輸入與假設!D$26*輸入與假設!$C$20*輸入與假設!D$25*D5 -> 25.1275 | E11: =E10*輸入與假設!E$26*輸入與假設!$C$20*輸入與假設!E$25*E5 -> 35.883795 | F11: =F10*輸入與假設!F$26*輸入與假設!$C$20*輸入與假設!F$25*F5 -> 42.11691 | G11: =G10*輸入與假設!G$26*輸入與假設!$C$20*輸入與假設!G$25*G5 -> 47.06835
A12: （B）合約：排程 RPO
A13: 排程 RPO（模型期，依 10-Q 桶分攤） | B13: US$bn | C13: =(輸入與假設!$C$13+輸入與假設!$C$14)*(輸入與假設!C$22/輸入與假設!$C$16)*輸入與假設!$C$15 -> 13.19175 | D13: =(輸入與假設!$C$13+輸入與假設!$C$14)*(輸入與假設!D$22/輸入與假設!$C$16)*輸入與假設!$C$15 -> 26.3835 | E13: =(輸入與假設!$C$13+輸入與假設!$C$14)*(輸入與假設!E$22/輸入與假設!$C$16)*輸入與假設!$C$15 -> 25.74 | F13: =(輸入與假設!$C$13+輸入與假設!$C$14)*(輸入與假設!F$22/輸入與假設!$C$16)*輸入與假設!$C$15 -> 25.0965 | G13: =(輸入與假設!$C$13+輸入與假設!$C$14)*(輸入與假設!G$22/輸入與假設!$C$16)*輸入與假設!$C$15 -> 17.69625
A14: （C）兩條線相減
A15: 產能瓶頸（模型期：排程 − 容量） | B15: US$bn | C15: =MAX(0,C13-C11) -> 5.07875 | D15: =MAX(0,D13-D11) -> 1.256 | E15: =MAX(0,E13-E11) -> 0 | F15: =MAX(0,F13-F11) -> 0 | G15: =MAX(0,G13-G11) -> 0
A16: 期初 RPO 轉換收入（模型期） | B16: US$bn | C16: =C13-C15 -> 8.113 | D16: =D13-D15 -> 25.1275 | E16: =E13-E15 -> 25.74 | F16: =F13-F15 -> 25.0965 | G16: =G13-G15 -> 17.69625
A17: 未被期初 RPO 占用的產能 | B17: US$bn | C17: =MAX(0,C11-C13) -> 0 | D17: =MAX(0,D11-D13) -> 0 | E17: =MAX(0,E11-E13) -> 10.143795 | F17: =MAX(0,F11-F13) -> 17.02041 | G17: =MAX(0,G11-G13) -> 29.3721
A18: 新簽約收入 | B18: US$bn | C18: =C17*輸入與假設!C$27 -> 0 | D18: =D17*輸入與假設!D$27 -> 0 | E18: =E17*輸入與假設!E$27 -> 9.1294155 | F18: =F17*輸入與假設!F$27 -> 14.467348 | G18: =G17*輸入與假設!G$27 -> 23.49768
A19: 損益用算力收入（模型期＝RPO 轉換＋新簽約） | B19: US$bn | C19: =C16+C18 -> 8.113 | D19: =D16+D18 -> 25.1275 | E19: =E16+E18 -> 34.869416 | F19: =F16+F18 -> 39.563848 | G19: =G16+G18 -> 41.19393
A20: （D）收入 → 現金：三道折扣
A21: 信用損失（期初 RPO 部分） | B21: US$bn | C21: =C16*輸入與假設!C$28*(1-輸入與假設!C$29) -> 0.0202825 | D21: =D16*輸入與假設!D$28*(1-輸入與假設!D$29) -> 0.1256375 | E21: =E16*輸入與假設!E$28*(1-輸入與假設!E$29) -> 0.19305 | F21: =F16*輸入與假設!F$28*(1-輸入與假設!F$29) -> 0.250965 | G21: =G16*輸入與假設!G$28*(1-輸入與假設!G$29) -> 0.22120313
A22: 收現（期初 RPO 部分） | B22: US$bn | C22: =C16-C21 -> 8.0927175 | D22: =D16-D21 -> 25.001863 | E22: =E16-E21 -> 25.54695 | F22: =F16-F21 -> 24.845535 | G22: =G16-G21 -> 17.475047
A23: 模型期總營收（算力＋服務） | B23: US$bn | C23: =C19+輸入與假設!C$30 -> 8.413 | D23: =D19+輸入與假設!D$30 -> 26.1275 | E23: =E19+輸入與假設!E$30 -> 36.669415 | F23: =F19+輸入與假設!F$30 -> 42.363849 | G23: =G19+輸入與假設!G$30 -> 44.99393
A24: EBITDAR 率（EBITDA 率＋租金÷營收） | B24: % | C24: =輸入與假設!C$34+收支與融資!C11/MAX(0.01,C23) -> 0.74927731 | D24: =輸入與假設!D$34+收支與融資!D11/MAX(0.01,D23) -> 0.75576069 | E24: =輸入與假設!E$34+收支與融資!E11/MAX(0.01,E23) -> 0.74886365 | F24: =輸入與假設!F$34+收支與融資!F11/MAX(0.01,F23) -> 0.75592858 | G24: =輸入與假設!G$34+收支與融資!G11/MAX(0.01,G23) -> 0.76536086
A25: RPO 現金（可支應資本用途） | B25: US$bn | C25: =C22*C24 -> 6.0636896 | D25: =D22*D24 -> 18.895425 | E25: =E22*E24 -> 19.131182 | F25: =F22*F24 -> 18.78145 | G25: =G22*G24 -> 13.374717
A26: 新簽約現金 | B26: US$bn | C26: =C18*(1-輸入與假設!C$28*(1-輸入與假設!C$29))*C24 -> 0 | D26: =D18*(1-輸入與假設!D$28*(1-輸入與假設!D$29))*D24 -> 0 | E26: =E18*(1-輸入與假設!E$28*(1-輸入與假設!E$29))*E24 -> 6.7854123 | F26: =F18*(1-輸入與假設!F$28*(1-輸入與假設!F$29))*F24 -> 10.826919 | G26: =G18*(1-輸入與假設!G$28*(1-輸入與假設!G$29))*G24 -> 17.759402

Sheet 損益與評價
A1: 損益（類損益表）— 與資金模型同一組收入
A2: 算力收入、Cash CapEx、利息皆由前面分頁連結而來；改資金假設，此頁會跟著動
A4: 項目 | B4: 單位 | C4: FY26 | D4: FY27 | E4: FY28 | F4: FY29 | G4: FY30
A5: 損益表
A6: 算力收入 | B6: US$bn | C6: =產能與收入!C19 -> 8.113 | D6: =產能與收入!D19 -> 25.1275 | E6: =產能與收入!E19 -> 34.869416 | F6: =產能與收入!F19 -> 39.563848 | G6: =產能與收入!G19 -> 41.19393
A7: 非算力服務 | B7: US$bn | C7: =輸入與假設!C$30 -> 0.3 | D7: =輸入與假設!D$30 -> 1 | E7: =輸入與假設!E$30 -> 1.8 | F7: =輸入與假設!F$30 -> 2.8 | G7: =輸入與假設!G$30 -> 3.8
A8: 總營收 | B8: US$bn | C8: =C6+C7 -> 8.413 | D8: =D6+D7 -> 26.1275 | E8: =E6+E7 -> 36.669415 | F8: =F6+F7 -> 42.363849 | G8: =G6+G7 -> 44.99393
A9: 營業利益（EBIT） | B9: US$bn | C9: =C8*輸入與假設!C$34-輸入與假設!C$64 -> 0.20083667 | D9: =D8*輸入與假設!D$34-輸入與假設!D$64 -> 1.3505542 | E9: =E8*輸入與假設!E$34-輸入與假設!E$64 -> 2.6330376 | F9: =F8*輸入與假設!F$34-輸入與假設!F$64 -> 2.0815438 | G9: =G8*輸入與假設!G$34-輸入與假設!G$64 -> 0.19072117
A10: D&A | B10: US$bn | C10: =輸入與假設!C$64 -> 4.7628333 | D10: =輸入與假設!D$64 -> 14.456583 | E10: =輸入與假設!E$64 -> 20.102 | F10: =輸入與假設!F$64 -> 24.8195 | G10: =輸入與假設!G$64 -> 29.055333
A11: EBITDA | B11: US$bn | C11: =C9+C10 -> 4.96367 | D11: =D9+D10 -> 15.807137 | E11: =E9+E10 -> 22.735038 | F11: =F9+F10 -> 26.901044 | G11: =G9+G10 -> 29.246054
A12: 基礎股數（每年 +SBC 稀釋） | B12: bn | C12: =輸入與假設!$C$89 -> 0.587 | D12: =C12*(1+輸入與假設!$C$103) -> 0.59287 | E12: =D12*(1+輸入與假設!$C$103) -> 0.5987987 | F12: =E12*(1+輸入與假設!$C$103) -> 0.60478669 | G12: =F12*(1+輸入與假設!$C$103) -> 0.61083455
A13: 股數（含瀑布新股） | B13: bn | C13: =C12+收支與融資!C64 -> 0.587 | D13: =D12+收支與融資!D64 -> 0.59287 | E13: =E12+收支與融資!E64 -> 0.5987987 | F13: =F12+收支與融資!F64 -> 0.71121572 | G13: =G12+收支與融資!G64 -> 0.7822679
A14: 損益表（全年口徑；FY26＝1H 實際＋下半年模型；與 HTML 損益簡表一致）
A15: 1H26 實際營收（已實現） | B15: US$bn | C15: =輸入與假設!$C$128 -> 4.653 | D15: =0 -> 0 | E15: =0 -> 0 | F15: =0 -> 0 | G15: =0 -> 0
A16: 全年總營收 | B16: US$bn | C16: =C15+C8 -> 13.066 | D16: =D15+D8 -> 26.1275 | E16: =E15+E8 -> 36.669415 | F16: =F15+F8 -> 42.363849 | G16: =G15+G8 -> 44.99393
A17: 全年 GAAP 營業利益 | B17: US$bn | C17: =輸入與假設!$C$129+C9 -> 0.0078366667 | D17: =D9 -> 1.3505542 | E17: =E9 -> 2.6330376 | F17: =F9 -> 2.0815438 | G17: =G9 -> 0.19072117
A18: 全年 D&A | B18: US$bn | C18: =輸入與假設!$C$130+C10 -> 7.3028333 | D18: =D10 -> 14.456583 | E18: =E10 -> 20.102 | F18: =F10 -> 24.8195 | G18: =G10 -> 29.055333
A19: 全年 EBITDA | B19: US$bn | C19: =C17+C18 -> 7.31067 | D19: =D17+D18 -> 15.807137 | E19: =E17+E18 -> 22.735038 | F19: =F17+F18 -> 26.901044 | G19: =G17+G18 -> 29.246054
A21: 評價 — DCF、EV/EBITDA、加權目標價
A22: 營收、營業利益、D&A、EBITDA、股數引用『損益與評價』頁；Cash CapEx 與融資引用『收支與融資』頁
A24: 項目 | B24: 單位 | C24: FY26 | D24: FY27 | E24: FY28 | F24: FY29 | G24: FY30
A25: DCF（無槓桿自由現金流；起點為 2026-06-30）
A26: 現金 CapEx（2026-06-30 之後） | B26: US$bn | C26: =輸入與假設!C$63-收支與融資!C7 -> 19.16912 | D26: =輸入與假設!D$63-收支與融資!D7 -> 35.2682 | E26: =輸入與假設!E$63-收支與融資!E7 -> 27.0572 | F26: =輸入與假設!F$63-收支與融資!F7 -> 28.152 | G26: =輸入與假設!G$63-收支與融資!G7 -> 29.8724
A27: 比較基期營收 | B27: US$bn | C27: =5.131 -> 5.131 | D27: =4.653+損益與評價!C8 -> 13.066 | E27: =損益與評價!D8 -> 26.1275 | F27: =損益與評價!E8 -> 36.669415 | G27: =損益與評價!F8 -> 42.363849
A28: 營運資金變動 | B28: US$bn | C28: =輸入與假設!$C$97*MAX(0,損益與評價!C8-C27) -> 0.06564 | D28: =輸入與假設!$C$97*MAX(0,損益與評價!D8-D27) -> 0.26123 | E28: =輸入與假設!$C$97*MAX(0,損益與評價!E8-E27) -> 0.21083831 | F28: =輸入與假設!$C$97*MAX(0,損益與評價!F8-F27) -> 0.11388866 | G28: =輸入與假設!$C$97*MAX(0,損益與評價!G8-G27) -> 0.05260163
A29: 無槓桿 NOL 期初 | B29: US$bn | C29: =輸入與假設!$C$95 -> 4 | D29: =C31 -> 3.8393307 | E29: =D31 -> 2.7588873 | F29: =E31 -> 0.65245725 | G29: =F31 -> 0
A30: 本期動用（無槓桿） | B30: US$bn | C30: =MIN(C29,MAX(0,損益與評價!C9)*輸入與假設!$C$96) -> 0.16066933 | D30: =MIN(D29,MAX(0,損益與評價!D9)*輸入與假設!$C$96) -> 1.0804433 | E30: =MIN(E29,MAX(0,損益與評價!E9)*輸入與假設!$C$96) -> 2.1064301 | F30: =MIN(F29,MAX(0,損益與評價!F9)*輸入與假設!$C$96) -> 0.65245725 | G30: =MIN(G29,MAX(0,損益與評價!G9)*輸入與假設!$C$96) -> 0
A31: 無槓桿 NOL 期末 | B31: US$bn | C31: =C29-C30+MAX(0,-損益與評價!C9) -> 3.8393307 | D31: =D29-D30+MAX(0,-損益與評價!D9) -> 2.7588873 | E31: =E29-E30+MAX(0,-損益與評價!E9) -> 0.65245725 | F31: =F29-F30+MAX(0,-損益與評價!F9) -> 0 | G31: =G29-G30+MAX(0,-損益與評價!G9) -> 0
A32: 無槓桿所得稅（DCF 用） | B32: US$bn | C32: =MAX(0,損益與評價!C9-C30)*輸入與假設!$C$94 -> 0.00843514 | D32: =MAX(0,損益與評價!D9-D30)*輸入與假設!$C$94 -> 0.056723275 | E32: =MAX(0,損益與評價!E9-E30)*輸入與假設!$C$94 -> 0.11058758 | F32: =MAX(0,損益與評價!F9-F30)*輸入與假設!$C$94 -> 0.30010818 | G32: =MAX(0,損益與評價!G9-G30)*輸入與假設!$C$94 -> 0.040051445
A33: UFCF | B33: US$bn | C33: =損益與評價!C9-C32+損益與評價!C10-C26-C28 -> -14.279525 | D33: =損益與評價!D9-D32+損益與評價!D10-D26-D28 -> -19.779016 | E33: =損益與評價!E9-E32+損益與評價!E10-E26-E28 -> -4.6435883 | F33: =損益與評價!F9-F32+損益與評價!F10-F26-F28 -> -1.664953 | G33: =損益與評價!G9-G32+損益與評價!G10-G26-G28 -> -0.71899857
A34: 折現期數 | B34: 年 | C34: =輸入與假設!$C$110 -> 0.5 | D34: =輸入與假設!$D$110 -> 1.5 | E34: =輸入與假設!$E$110 -> 2.5 | F34: =輸入與假設!$F$110 -> 3.5 | G34: =輸入與假設!$G$110 -> 4.5
A35: 折現因子 | C35: =1/(1+輸入與假設!$C$91)^C34 -> 0.949158 | D35: =1/(1+輸入與假設!$C$91)^D34 -> 0.85509729 | E35: =1/(1+輸入與假設!$C$91)^E34 -> 0.77035792 | F35: =1/(1+輸入與假設!$C$91)^F34 -> 0.69401615 | G35: =1/(1+輸入與假設!$C$91)^G34 -> 0.62523977
A36: UFCF 現值 | B36: US$bn | C36: =C33*C35 -> -13.553525 | D36: =D33*D35 -> -16.912983 | E36: =E33*E35 -> -3.577225 | F36: =F33*F35 -> -1.1555043 | G36: =G33*G35 -> -0.4495465
A37: 五期 UFCF 現值合計 | C37: =SUM(C36:G36) -> -35.648784
A38: 常態化 FCF（FY30） | C38: =損益與評價!G9*(1-輸入與假設!$C$94)+損益與評價!G10-損益與評價!G10*輸入與假設!$C$93 -> 5.9617364
A39: 終值（Gordon） | C39: =IF(C47=1,0,C38*(1+輸入與假設!$C$92)/(輸入與假設!$C$91-輸入與假設!$C$92)) -> 76.757356
A40: 終值現值 | C40: =C39*G35 -> 47.991752
A41: 企業價值 EV | C41: =C37+C40 -> 12.342968
A42: 減：淨負債 | C42: =-輸入與假設!$C$90 -> -30
A43: 股權價值 | C43: =C41+C42 -> -17.657032
A44: DCF 每股 | C44: =IF(C47=1,0,IF(輸入與假設!$C$104=2,C49,C48)) -> 0
A45: 新股募得現金（現值） | C45: =收支與融資!C59/(1+輸入與假設!$C$91)^輸入與假設!$C$111+收支與融資!D59/(1+輸入與假設!$C$91)^輸入與假設!$D$111+收支與融資!E59/(1+輸入與假設!$C$91)^輸入與假設!$E$111+收支與融資!F59/(1+輸入與假設!$C$91)^輸入與假設!$F$111+收支與融資!G59/(1+輸入與假設!$C$91)^輸入與假設!$G$111 -> 10.310173
A46: 融資後股數（含瀑布新股） | C46: =輸入與假設!$C$89+收支與融資!G64 -> 0.75843335
A47: DCF 失效？（WACC ≤ g 或常態化 FCF ≤ 0） | C47: =IF(OR(輸入與假設!$C$91<=輸入與假設!$C$92,C38<=0),1,0) -> 0
A48: DCF 每股：0 截斷 | C48: =MAX(0,(C43+C45)/C46) -> 0
A49: DCF 每股：選擇權（Merton） | C49: =IF((C41+C45)<=0,0,((C41+C45)*NORMSDIST(C50)-輸入與假設!$C$90*EXP(-輸入與假設!$C$106*輸入與假設!$C$107)*NORMSDIST(C51))/C46) -> 11.177763
A50: d1 | C50: =IF((C41+C45)<=0,0,(LN((C41+C45)/輸入與假設!$C$90)+(輸入與假設!$C$106+輸入與假設!$C$105^2/2)*輸入與假設!$C$107)/(輸入與假設!$C$105*SQRT(輸入與假設!$C$107))) -> 0.43520171
A51: d2 | C51: =C50-輸入與假設!$C$105*SQRT(輸入與假設!$C$107) -> -0.62545846
A52: 倍數法（錨定年度，預設 FY29；折回 2027-06-30）
A53: 錨定年度 EBITDA | C53: =INDEX(損益與評價!$D$11:$G$11,1,輸入與假設!$C$99) -> 26.901044
A54: 錨定年度企業價值（倍數 × EBITDA） | C54: =C53*輸入與假設!$C$98 -> 161.40626
A55: 錨定年度末淨負債（總債務 − 現金） | C55: =INDEX(收支與融資!$D$68:$G$68,1,輸入與假設!$C$99)-INDEX(收支與融資!$D$40:$G$40,1,輸入與假設!$C$99) -> 85.028228
A56: 錨定年度末股數（含瀑布新股） | C56: =INDEX(損益與評價!$D$13:$G$13,1,輸入與假設!$C$99) -> 0.71121572
A57: 折回 2027-06-30 的折現因子 | C57: =1/(1+輸入與假設!$C$91)^(輸入與假設!$C$99-輸入與假設!$C$109) -> 0.77035792
A58: EV/EBITDA 每股（融資後） | C58: =MAX(0,(C54-C55)/C56)*C57 -> 82.729364
A59: 加權目標價
A60: DCF 每股（推到目標價時點） | C60: =C44*(1+輸入與假設!$C$91)^輸入與假設!$C$108 -> 0
A61: DCF 每股 × 有效權重 | C61: =C60*IF(C47=1,0,輸入與假設!$C$100) -> 0
A62: EV/EBITDA（融資後）× 有效權重 | C62: =C58*IF(C47=1,1,1-輸入與假設!$C$100) -> 45.50115
A63: 加權目標價 | C63: =SUM(C61:C62) -> 45.50115
A64: 現價 | C64: =輸入與假設!$C$88 -> 90.13
A65: 潛在空間 | C65: =C63/C64-1 -> -0.49516088
A66: DCF 權重說明 | C66: =IF(C47=1,"DCF 失效，已以 EV/EBITDA 100% 計。",IF(AND(輸入與假設!$C$104<>2,C80<0),"DCF 為 $0 仍計 "&TEXT(輸入與假設!$C$100,"0%")&" 權重的原因：DCF 沒有失效，而是算出的股權價值為負（每股約 −$"&TEXT(ABS(C80),"0.0")&"），代表自由現金流折現後的企業價值不足以償還淨負債。EV/EBITDA 沒有扣除 GPU 汰換與擴張支出，保留 DCF 權重，是為了讓目標價反映「EBITDA 付不起資本成本」。若不計 DCF，目標價為 $"&TEXT(C58,"0.0")&"（"&CHOOSE(D79+2,"賣出","中立","買進")&"）；"&TEXT(輸入與假設!$C$100,"0%")&"／"&TEXT(1-輸入與假設!$C$100,"0%")&" 為判斷值。","")) -> DCF 為 $0 仍計 45% 權重的原因：DCF 沒有失效，而是算出的股權價值為負（每股約 −$9.7），代表自由現金流折現後的企業價值不足以償還淨負債。EV/EBITDA 沒有扣除 GPU 汰換與擴張支出，保留 DCF 權重，是為了讓目標價反映「EBITDA 付不起資本成本」。若不計 DCF，目標價為 $82.7（中立）；45%／55% 為判斷值。
A67: 目標價區間（情境區間、方法區間；評等仍依點位）
A68: 目標價區間｜點位（目前輸入的加權目標價） | C68: =C63 -> 45.50115 | I68: ="評等規則不變：空間 ≥"&IF(ROUND(ABS(輸入與假設!$C$112)*100,4)=INT(ROUND(ABS(輸入與假設!$C$112)*100,4)),TEXT(ROUND(ABS(輸入與假設!$C$112)*100,4),"0"),TEXT(ROUND(ABS(輸入與假設!$C$112)*100,4),"0.0"))&"%"&" 且終值占比 <"&IF(ROUND(ABS(輸入與假設!$C$113)*100,4)=INT(ROUND(ABS(輸入與假設!$C$113)*100,4)),TEXT(ROUND(ABS(輸入與假設!$C$113)*100,4),"0"),TEXT(ROUND(ABS(輸入與假設!$C$113)*100,4),"0.0"))&"%"&"、股權募資 ≤"&IF(輸入與假設!$C$115=INT(輸入與假設!$C$115),TEXT(輸入與假設!$C$115,"0"),TEXT(輸入與假設!$C$115,"0.0"))&" 倍現市值 → 買進；空間 ≤−"&IF(ROUND(ABS(輸入與假設!$C$114)*100,4)=INT(ROUND(ABS(輸入與假設!$C$114)*100,4)),TEXT(ROUND(ABS(輸入與假設!$C$114)*100,4),"0"),TEXT(ROUND(ABS(輸入與假設!$C$114)*100,4),"0.0"))&"%"&"，或股權募資 >"&IF(輸入與假設!$C$115=INT(輸入與假設!$C$115),TEXT(輸入與假設!$C$115,"0"),TEXT(輸入與假設!$C$115,"0.0"))&" 倍且空間 ≤−"&IF(ROUND(ABS(輸入與假設!$C$116)*100,4)=INT(ROUND(ABS(輸入與假設!$C$116)*100,4)),TEXT(ROUND(ABS(輸入與假設!$C$116)*100,4),"0"),TEXT(ROUND(ABS(輸入與假設!$C$116)*100,4),"0.0"))&"%"&" → 賣出；其餘中立" -> 評等規則不變：空間 ≥25% 且終值占比 <90%、股權募資 ≤1.5 倍現市值 → 買進；空間 ≤−15%，或股權募資 >1.5 倍且空間 ≤−8% → 賣出；其餘中立
A69: 目標價區間｜終值占 EV（評等用） | C69: =C40/MAX(ABS(C41),1)*IF(C41=0,1,SIGN(C41)) -> 3.8881858
A70: 目標價區間｜股權募資 ÷ 現市值（評等用） | C70: =SUM(收支與融資!C59:G59)/(輸入與假設!$C$88*輸入與假設!$C$89) -> 0.262845
A71: 目標價區間｜點位評等代碼（1＝買進、0＝中立、−1＝賣出） | C71: =IF(AND((C63/MAX(輸入與假設!$C$88,0.01)-1)>=輸入與假設!$C$112,$C$69<輸入與假設!$C$113,$C$70<=輸入與假設!$C$115),1,IF(OR((C63/MAX(輸入與假設!$C$88,0.01)-1)<=輸入與假設!$C$114,AND($C$70>輸入與假設!$C$115,(C63/MAX(輸入與假設!$C$88,0.01)-1)<=輸入與假設!$C$116)),-1,0)) -> -1 | D71: =CHOOSE(C71+2,"賣出","中立","買進") -> 賣出
A72: 目標價區間｜賣出門檻價（現價 × (1 − 15%)） | C72: =輸入與假設!$C$88*(1+輸入與假設!$C$114) -> 76.6105
A73: 目標價區間｜保守 4.2 GW（加權目標價／評等代碼／距賣出門檻） | C73: =輸入與假設!D134 -> 69.741657 | D73: =輸入與假設!E134 -> -1 | E73: =C73-$C$72 -> -6.8688431
A74: 目標價區間｜基準 5.6 GW（加權目標價／評等代碼／距賣出門檻） | C74: =輸入與假設!D135 -> 45.50115 | D74: =輸入與假設!E135 -> -1 | E74: =C74-$C$72 -> -31.10935
A75: 目標價區間｜積極 8 GW（加權目標價／評等代碼／距賣出門檻） | C75: =輸入與假設!D136 -> 30.953266 | D75: =輸入與假設!E136 -> -1 | E75: =C75-$C$72 -> -45.657234
A76: 目標價區間｜情境區間（下緣／上緣） | C76: =MIN(C73,C75) -> 30.953266 | D76: =MAX(C73,C75) -> 69.741657
A77: 目標價區間｜方法區間倍數（下端／上端） | C77: =MIN(輸入與假設!$C$101,輸入與假設!$C$102) -> 5 | D77: =MAX(輸入與假設!$C$101,輸入與假設!$C$102) -> 6
A78: 目標價區間｜方法區間（下緣／上緣） | C78: =MIN(C60*IF(C47=1,0,輸入與假設!$C$100)+MAX(0,(C53*C77-C55)/C56)*C57*IF(C47=1,1,1-輸入與假設!$C$100),C60*IF(C47=1,0,輸入與假設!$C$100)+MAX(0,(C53*D77-C55)/C56)*C57*IF(C47=1,1,1-輸入與假設!$C$100)) -> 29.475228 | D78: =MAX(C60*IF(C47=1,0,輸入與假設!$C$100)+MAX(0,(C53*C77-C55)/C56)*C57*IF(C47=1,1,1-輸入與假設!$C$100),C60*IF(C47=1,0,輸入與假設!$C$100)+MAX(0,(C53*D77-C55)/C56)*C57*IF(C47=1,1,1-輸入與假設!$C$100)) -> 45.50115
A79: 目標價區間｜100% EV/EBITDA 目標價（價位／評等代碼） | C79: =C58 -> 82.729364 | D79: =IF(AND((C58/MAX(輸入與假設!$C$88,0.01)-1)>=輸入與假設!$C$112,$C$69<輸入與假設!$C$113,$C$70<=輸入與假設!$C$115),1,IF(OR((C58/MAX(輸入與假設!$C$88,0.01)-1)<=輸入與假設!$C$114,AND($C$70>輸入與假設!$C$115,(C58/MAX(輸入與假設!$C$88,0.01)-1)<=輸入與假設!$C$116)),-1,0)) -> 0 | E79: =CHOOSE(D79+2,"賣出","中立","買進") -> 中立
A80: 目標價區間｜未截斷 DCF 每股 | C80: =(C43+C45)/C46 -> -9.6868886
A81: 目標價區間｜點位摘要 | C81: ="目標價 $"&TEXT(C63,"0.0")&"（情境區間 $"&TEXT(C76,"0.0")&"–$"&TEXT(D76,"0.0")&"）" -> 目標價 $45.5（情境區間 $31.0–$69.7）
A82: 目標價區間｜方法區間標籤 | C82: ="方法區間（目前情境，"&IF(C77=INT(C77),TEXT(C77,"0"),TEXT(C77,"0.0"))&"–"&IF(D77=INT(D77),TEXT(D77,"0"),TEXT(D77,"0.0"))&"x）" -> 方法區間（目前情境，5–6x）
A83: 目標價區間｜點位位置 | C83: =IF(ABS(輸入與假設!$C$98-D77)<0.000000001,"目前點位位於方法區間上緣（"&IF(D77=INT(D77),TEXT(D77,"0"),TEXT(D77,"0.0"))&"x 為穩態倍數上緣）",IF(ABS(輸入與假設!$C$98-C77)<0.000000001,"目前點位位於方法區間下緣（"&IF(C77=INT(C77),TEXT(C77,"0"),TEXT(C77,"0.0"))&"x）","目前點位"&IF(AND(輸入與假設!$C$98>C77,輸入與假設!$C$98<D77),"位於方法區間內",IF(輸入與假設!$C$98>D77,"高於方法區間上緣","低於方法區間下緣"))&"（目前倍數 "&IF(輸入與假設!$C$98=INT(輸入與假設!$C$98),TEXT(輸入與假設!$C$98,"0"),TEXT(輸入與假設!$C$98,"0.0"))&"x）")) -> 目前點位位於方法區間上緣（6x 為穩態倍數上緣）
A84: 目標價區間｜判斷句 | C84: =IF(D76<輸入與假設!$C$88,"情境區間上緣 $"&TEXT(D76,"0.0")&" 低於現價 $"&TEXT(輸入與假設!$C$88,"0.00")&IF((D73<>-1)+(D74<>-1)+(D75<>-1)>0,"，但"&SUBSTITUTE(TRIM(IF(D73<>-1,"保守","")&" "&IF(D74<>-1,"基準","")&" "&IF(D75<>-1,"積極",""))," ","、")&"情境未達賣出門檻 $"&TEXT($C$72,"0.0"),"：賣出在三個擴張情境下都成立"),"情境區間上緣 $"&TEXT(D76,"0.0")&" 不低於現價 $"&TEXT(輸入與假設!$C$88,"0.00")&"：賣出並非在三個擴張情境下都成立")&"。"&IF(ABS(E73)<輸入與假設!$C$117*輸入與假設!$C$88,"保守情境 $"&TEXT(C73,"0.0")&"，"&IF(E73<0,"距賣出門檻","高於賣出門檻")&" $"&TEXT($C$72,"0.0")&" 僅 $"&TEXT(ABS(E73),"0.0")&"。","")&IF(ABS(E74)<輸入與假設!$C$117*輸入與假設!$C$88,"基準情境 $"&TEXT(C74,"0.0")&"，"&IF(E74<0,"距賣出門檻","高於賣出門檻")&" $"&TEXT($C$72,"0.0")&" 僅 $"&TEXT(ABS(E74),"0.0")&"。","")&IF(ABS(E75)<輸入與假設!$C$117*輸入與假設!$C$88,"積極情境 $"&TEXT(C75,"0.0")&"，"&IF(E75<0,"距賣出門檻","高於賣出門檻")&" $"&TEXT($C$72,"0.0")&" 僅 $"&TEXT(ABS(E75),"0.0")&"。","") -> 情境區間上緣 $69.7 低於現價 $90.13：賣出在三個擴張情境下都成立。
A85: 錨定年度 × 倍數矩陣（每股；以 WACC 折回 2027-06-30）
A86: 錨定×倍數｜倍數法｜3.4x | B86: 3.4 | C86: =MAX(0,(INDEX(損益與評價!$D$11:$G$11,1,1)*$B86-(INDEX(收支與融資!$D$68:$G$68,1,1)-INDEX(收支與融資!$D$40:$G$40,1,1)))/INDEX(損益與評價!$D$13:$G$13,1,1))/(1+輸入與假設!$C$91)^(1-輸入與假設!$C$109) -> 0 | D86: =MAX(0,(INDEX(損益與評價!$D$11:$G$11,1,2)*$B86-(INDEX(收支與融資!$D$68:$G$68,1,2)-INDEX(收支與融資!$D$40:$G$40,1,2)))/INDEX(損益與評價!$D$13:$G$13,1,2))/(1+輸入與假設!$C$91)^(2-輸入與假設!$C$109) -> 0 | E86: =MAX(0,(INDEX(損益與評價!$D$11:$G$11,1,3)*$B86-(INDEX(收支與融資!$D$68:$G$68,1,3)-INDEX(收支與融資!$D$40:$G$40,1,3)))/INDEX(損益與評價!$D$13:$G$13,1,3))/(1+輸入與假設!$C$91)^(3-輸入與假設!$C$109) -> 6.9704591 | F86: =MAX(0,(INDEX(損益與評價!$D$11:$G$11,1,4)*$B86-(INDEX(收支與融資!$D$68:$G$68,1,4)-INDEX(收支與融資!$D$40:$G$40,1,4)))/INDEX(損益與評價!$D$13:$G$13,1,4))/(1+輸入與假設!$C$91)^(4-輸入與假設!$C$109) -> 9.2716388
A87: 錨定×倍數｜倍數法｜4.5x | B87: 4.5 | C87: =MAX(0,(INDEX(損益與評價!$D$11:$G$11,1,1)*$B87-(INDEX(收支與融資!$D$68:$G$68,1,1)-INDEX(收支與融資!$D$40:$G$40,1,1)))/INDEX(損益與評價!$D$13:$G$13,1,1))/(1+輸入與假設!$C$91)^(1-輸入與假設!$C$109) -> 0 | D87: =MAX(0,(INDEX(損益與評價!$D$11:$G$11,1,2)*$B87-(INDEX(收支與融資!$D$68:$G$68,1,2)-INDEX(收支與融資!$D$40:$G$40,1,2)))/INDEX(損益與評價!$D$13:$G$13,1,2))/(1+輸入與假設!$C$91)^(2-輸入與假設!$C$109) -> 25.701184 | E87: =MAX(0,(INDEX(損益與評價!$D$11:$G$11,1,3)*$B87-(INDEX(收支與融資!$D$68:$G$68,1,3)-INDEX(收支與融資!$D$40:$G$40,1,3)))/INDEX(損益與評價!$D$13:$G$13,1,3))/(1+輸入與假設!$C$91)^(3-輸入與假設!$C$109) -> 39.022303 | F87: =MAX(0,(INDEX(損益與評價!$D$11:$G$11,1,4)*$B87-(INDEX(收支與融資!$D$68:$G$68,1,4)-INDEX(收支與融資!$D$40:$G$40,1,4)))/INDEX(損益與評價!$D$13:$G$13,1,4))/(1+輸入與假設!$C$91)^(4-輸入與假設!$C$109) -> 37.812957
A88: 錨定×倍數｜倍數法｜5.0x | B88: 5 | C88: =MAX(0,(INDEX(損益與評價!$D$11:$G$11,1,1)*$B88-(INDEX(收支與融資!$D$68:$G$68,1,1)-INDEX(收支與融資!$D$40:$G$40,1,1)))/INDEX(損益與評價!$D$13:$G$13,1,1))/(1+輸入與假設!$C$91)^(1-輸入與假設!$C$109) -> 11.447387 | D88: =MAX(0,(INDEX(損益與評價!$D$11:$G$11,1,2)*$B88-(INDEX(收支與融資!$D$68:$G$68,1,2)-INDEX(收支與融資!$D$40:$G$40,1,2)))/INDEX(損益與評價!$D$13:$G$13,1,2))/(1+輸入與假設!$C$91)^(2-輸入與假設!$C$109) -> 41.934243 | E88: =MAX(0,(INDEX(損益與評價!$D$11:$G$11,1,3)*$B88-(INDEX(收支與融資!$D$68:$G$68,1,3)-INDEX(收支與融資!$D$40:$G$40,1,3)))/INDEX(損益與評價!$D$13:$G$13,1,3))/(1+輸入與假設!$C$91)^(3-輸入與假設!$C$109) -> 53.591323 | F88: =MAX(0,(INDEX(損益與評價!$D$11:$G$11,1,4)*$B88-(INDEX(收支與融資!$D$68:$G$68,1,4)-INDEX(收支與融資!$D$40:$G$40,1,4)))/INDEX(損益與評價!$D$13:$G$13,1,4))/(1+輸入與假設!$C$91)^(4-輸入與假設!$C$109) -> 50.786284
A89: 錨定×倍數｜倍數法｜6.0x | B89: 6 | C89: =MAX(0,(INDEX(損益與評價!$D$11:$G$11,1,1)*$B89-(INDEX(收支與融資!$D$68:$G$68,1,1)-INDEX(收支與融資!$D$40:$G$40,1,1)))/INDEX(損益與評價!$D$13:$G$13,1,1))/(1+輸入與假設!$C$91)^(1-輸入與假設!$C$109) -> 36.753897 | D89: =MAX(0,(INDEX(損益與評價!$D$11:$G$11,1,2)*$B89-(INDEX(收支與融資!$D$68:$G$68,1,2)-INDEX(收支與融資!$D$40:$G$40,1,2)))/INDEX(損益與評價!$D$13:$G$13,1,2))/(1+輸入與假設!$C$91)^(2-輸入與假設!$C$109) -> 74.400361 | E89: =MAX(0,(INDEX(損益與評價!$D$11:$G$11,1,3)*$B89-(INDEX(收支與融資!$D$68:$G$68,1,3)-INDEX(收支與融資!$D$40:$G$40,1,3)))/INDEX(損益與評價!$D$13:$G$13,1,3))/(1+輸入與假設!$C$91)^(3-輸入與假設!$C$109) -> 82.729364 | F89: =MAX(0,(INDEX(損益與評價!$D$11:$G$11,1,4)*$B89-(INDEX(收支與融資!$D$68:$G$68,1,4)-INDEX(收支與融資!$D$40:$G$40,1,4)))/INDEX(損益與評價!$D$13:$G$13,1,4))/(1+輸入與假設!$C$91)^(4-輸入與假設!$C$109) -> 76.732937
A90: 錨定×倍數｜倍數法｜7.0x | B90: 7 | C90: =MAX(0,(INDEX(損益與評價!$D$11:$G$11,1,1)*$B90-(INDEX(收支與融資!$D$68:$G$68,1,1)-INDEX(收支與融資!$D$40:$G$40,1,1)))/INDEX(損益與評價!$D$13:$G$13,1,1))/(1+輸入與假設!$C$91)^(1-輸入與假設!$C$109) -> 62.060408 | D90: =MAX(0,(INDEX(損益與評價!$D$11:$G$11,1,2)*$B90-(INDEX(收支與融資!$D$68:$G$68,1,2)-INDEX(收支與融資!$D$40:$G$40,1,2)))/INDEX(損益與評價!$D$13:$G$13,1,2))/(1+輸入與假設!$C$91)^(2-輸入與假設!$C$109) -> 106.86648 | E90: =MAX(0,(INDEX(損益與評價!$D$11:$G$11,1,3)*$B90-(INDEX(收支與融資!$D$68:$G$68,1,3)-INDEX(收支與融資!$D$40:$G$40,1,3)))/INDEX(損益與評價!$D$13:$G$13,1,3))/(1+輸入與假設!$C$91)^(3-輸入與假設!$C$109) -> 111.8674 | F90: =MAX(0,(INDEX(損益與評價!$D$11:$G$11,1,4)*$B90-(INDEX(收支與融資!$D$68:$G$68,1,4)-INDEX(收支與融資!$D$40:$G$40,1,4)))/INDEX(損益與評價!$D$13:$G$13,1,4))/(1+輸入與假設!$C$91)^(4-輸入與假設!$C$109) -> 102.67959
A91: 錨定×倍數｜加權目標價｜3.4x | B91: 3.4 | C91: =C60*IF(C47=1,0,輸入與假設!$C$100)+C86*IF(C47=1,1,1-輸入與假設!$C$100) -> 0 | D91: =C60*IF(C47=1,0,輸入與假設!$C$100)+D86*IF(C47=1,1,1-輸入與假設!$C$100) -> 0 | E91: =C60*IF(C47=1,0,輸入與假設!$C$100)+E86*IF(C47=1,1,1-輸入與假設!$C$100) -> 3.8337525 | F91: =C60*IF(C47=1,0,輸入與假設!$C$100)+F86*IF(C47=1,1,1-輸入與假設!$C$100) -> 5.0994013
A92: 錨定×倍數｜加權目標價｜4.5x | B92: 4.5 | C92: =C60*IF(C47=1,0,輸入與假設!$C$100)+C87*IF(C47=1,1,1-輸入與假設!$C$100) -> 0 | D92: =C60*IF(C47=1,0,輸入與假設!$C$100)+D87*IF(C47=1,1,1-輸入與假設!$C$100) -> 14.135651 | E92: =C60*IF(C47=1,0,輸入與假設!$C$100)+E87*IF(C47=1,1,1-輸入與假設!$C$100) -> 21.462267 | F92: =C60*IF(C47=1,0,輸入與假設!$C$100)+F87*IF(C47=1,1,1-輸入與假設!$C$100) -> 20.797127
A93: 錨定×倍數｜加權目標價｜5.0x | B93: 5 | C93: =C60*IF(C47=1,0,輸入與假設!$C$100)+C88*IF(C47=1,1,1-輸入與假設!$C$100) -> 6.2960626 | D93: =C60*IF(C47=1,0,輸入與假設!$C$100)+D88*IF(C47=1,1,1-輸入與假設!$C$100) -> 23.063834 | E93: =C60*IF(C47=1,0,輸入與假設!$C$100)+E88*IF(C47=1,1,1-輸入與假設!$C$100) -> 29.475228 | F93: =C60*IF(C47=1,0,輸入與假設!$C$100)+F88*IF(C47=1,1,1-輸入與假設!$C$100) -> 27.932456
A94: 錨定×倍數｜加權目標價｜6.0x | B94: 6 | C94: =C60*IF(C47=1,0,輸入與假設!$C$100)+C89*IF(C47=1,1,1-輸入與假設!$C$100) -> 20.214643 | D94: =C60*IF(C47=1,0,輸入與假設!$C$100)+D89*IF(C47=1,1,1-輸入與假設!$C$100) -> 40.920198 | E94: =C60*IF(C47=1,0,輸入與假設!$C$100)+E89*IF(C47=1,1,1-輸入與假設!$C$100) -> 45.50115 | F94: =C60*IF(C47=1,0,輸入與假設!$C$100)+F89*IF(C47=1,1,1-輸入與假設!$C$100) -> 42.203115
A95: 錨定×倍數｜加權目標價｜7.0x | B95: 7 | C95: =C60*IF(C47=1,0,輸入與假設!$C$100)+C90*IF(C47=1,1,1-輸入與假設!$C$100) -> 34.133224 | D95: =C60*IF(C47=1,0,輸入與假設!$C$100)+D90*IF(C47=1,1,1-輸入與假設!$C$100) -> 58.776563 | E95: =C60*IF(C47=1,0,輸入與假設!$C$100)+E90*IF(C47=1,1,1-輸入與假設!$C$100) -> 61.527072 | F95: =C60*IF(C47=1,0,輸入與假設!$C$100)+F90*IF(C47=1,1,1-輸入與假設!$C$100) -> 56.473775
A96: 穩健性與關鍵假設（建置時由 Python 重跑本活頁簿求得的快照；0 截斷口徑；±10% 為彈性，非可能性（GPU 經濟壽命為 ±1 年））
A97: 穩健性｜翻轉評等（離開賣出）所需 EV/EBITDA 倍數 | B97: x | C97: 6.4 | D97: 7.95 | E97: 8.7
A98: 穩健性｜加權目標價等於現價所需 EV/EBITDA 倍數 | B98: x | C98: 7.171916 | D98: 8.784791 | E98: 9.457791
A99: 對照｜共識平均目標價隱含 EV/EBITDA（共識 FY28 數字） | B99: x | C99: =摘要!C48 -> 6.1924133
A100: 對照｜同式：共識平均目標價以模型數字換算的 EV/EBITDA（目前情境，活公式） | B100: x | C100: =(輸入與假設!$C$138*輸入與假設!$C$89+摘要!E30)/摘要!E20 -> 7.3439676
A101: 對照｜同式：共識平均目標價以模型數字換算的 EV/EBITDA | B101: x | C101: 7.020594 | D101: 7.343968 | E101: 7.838611
A102: 穩健性｜翻轉為非賣出所需 WACC | B102: % | C102: 0.1025 | D102: 0.0745 | E102: 0.056
A103: 關鍵假設｜第 1 名 | C103: 每 MW 年收入（含利用率） | D103: 每 MW 年收入（含利用率） | E103: 每 MW 年收入（含利用率）
...
