Workbook

Sheet 導覽
A1: CoreWeave 收支與評價模型 — Excel 版 v4.0（更新 2026-09-24；與 HTML v4.0 同步；市價截至 2026-09-21 收盤）
A3: 這個活頁簿在回答什麼
A4: 一句話：CoreWeave 手上 $103.7bn 的合約（RPO）在 2030 年前能變成多少現金，而同一段時間要付出多少現金——
A5: 差額就是必須向外籌措的金額。所有分頁用同一組數字，改任何一個輸入，後面全部會跟著動。
A7: 分頁結構（依模組分組，分頁標籤顏色相同者為同一模組）
A8: 輸入與假設 所有可調參數（A 情境 → B 產能與收入 → C 利潤率 → D 支出 → E 融資 → F 評價 → G 1H 實際）。
A9: 各期收支 類現金流量：來源、用途、融資前缺口、期前融資瀑布。
A10: 運營_產能與收入 合約排程 vs 機房產能 → 收入 → 現金；運營_站點：房東揭露與租金檢驗。
A11: 資產負債_既有債務／新債與新股／租賃承諾 類資產負債表：10-Q 債務明細、每期現金與總債務與股數、租賃承諾。
A12: 損益 類損益表（FY26＝1H 實際＋下半年模型）。
A13: 評價_DCF與目標價／評價_可比公司 DCF、EV/EBITDA、加權目標價；同業 EV/Sales 比較。
A14: 評價_反向DCF 現價隱含的收入與成本（目標搜尋＋HTML 快照）。
... A81: 舊版的透支利息（借款利息）與扣 NTM 缺口（借款本金）並非重複計費；v2.0 的差別是新債設上限、超出部分改以股權支應。瀑布位於「支出與資金」頁下方。

Sheet 輸入與假設
A1: 輸入（依類別排序；點左側 ＋／− 展開或收合。藍字可改；黃底為最關鍵假設）
A2: A 情境 → B 產能與收入 → C 利潤率 → D 支出（CapEx／折舊／租賃／JV）→ E 融資 → F 評價 → G 參考：1H26 實際。灰底『▸』為明細子區，預設收合
A4: A｜情境與規模（管理層擴張力道）
A5: 情境選擇（1＝保守 4.2 GW、2＝基準 5.6 GW、3＝積極 8 GW） | C5: 2 | D5: =CHOOSE(C5,"保守 4.2 GW","基準 5.6 GW","積極 8 GW") -> 基準 5.6 GW | I5: 三情境只改變管理層的擴張力道；其餘假設相同。FY26–FY27 三者相同（年底 1,850／3,100 MW），FY28 起分歧
A6: ▸ 情境路徑明細（Accepted MW、爬坡比例、表外租金基準）
A7: Accepted MW 路徑 | B7: 單位 | C7: FY26 | D7: FY27 | E7: FY28 | F7: FY29 | G7: FY30 | I7: FY31 新增 MW
A8: 保守 4.2 GW | B8: MW | C8: 1850 | D8: 3100 | E8: 3800 | F8: 4200 | G8: 4200 | I8: 0 | J8: 只交付已簽約電力 4.2 GW（8/11 法說），不再新簽
A9: 基準 5.6 GW | B9: MW | C9: 1850 | D9: 3100 | E9: 4000 | F9: 4800 | G9: 5600 | I9: 500 | J9: 2027 年後每年約 +800 MW
A10: 積極 8 GW | B10: MW | C10: 1850 | D10: 3100 | E10: 4600 | F10: 6300 | G10: 8000 | I10: 1000 | J10: 公司目標 2030 ≥8 GW
A11: Billable／Accepted 爬坡比例 | B11: % | C11: 0.91891892 | D11: 0.93548387 | E11: 0.93478261 | F11: 0.93650794 | G11: 0.9375 | I11: 三情境共用
A12: 表外現金租金（積極路徑） | B12: US$bn | C12: 0.3 | D12: 1.6 | E12: 3 | F12: 4 | G12: 4.6 | I12: 其他情境依「新增 MW（相對 6/30 的 1,500 MW）」等比例縮放
A14: B｜產能與收入（RPO、MW、利用率、單價、簽約、信用）
A15: 6/30 RPO | B15: US$bn | C15: 103.7 | I15: 10-Q 103.7（backlog 104.2 含 0.5 其他）[Verified]
A16: Q3 初新增承諾 | B16: US$bn | C16: 25 | I16: 法說「>25」，尚未入 RPO [Interested-party]
A17: 五期認列比例（至 2030 末） | B17: % | C17: 0.84 | I17: 10-Q 桶 41／39／20 線性分攤後五期合計 84% [Derived]
A18: RPO 桶權重合計 | B18: % | C18: 0.84 | I18: 下方權重列的合計，用於歸一化
A19: 2025-12-31 主動電力 | B19: MW | C19: 850 | I19: Q4 2025 法說：年底 >850 MW、43 座資料中心 [Verified]
A20: 6/30 Billable MW | B20: MW | C20: 1350 | I20: 主動電力 1.5 GW 扣爬坡中 [Assumed]
A21: 收入用平均在役 MW（1=是） | C21: 1 | I21: 0＝用期末存量全期化。CRWV 交付後載（6 月 +300MW），建議 1
A22: 每 MW 年收入倍數（整體） | B22: % | C22: 1 | I22: 反向 DCF 與壓力測試用；預設 100%。以『目標搜尋』調整此格即可反解市價隱含單價
A23: 項目 | B23: 單位 | C23: FY26 | D23: FY27 | E23: FY28 | F23: FY29 | G23: FY30 | I23: 來源／標籤
A24: 模型期長度（年） | C24: 0.5 | D24: 1 | E24: 1 | F24: 1 | G24: 1 | I24: 勿改。FY26 模型期為 2026-07-01～12-31（0.5 年）。只用於容量上限、電力、維護三處年率換算 [Derived]
A25: RPO 桶權重 | B25: % | C25: 0.1025 | D25: 0.205 | E25: 0.2 | F25: 0.195 | G25: 0.1375 | H25: =SUM(C25:G25) -> 0.84 | I25: 10-Q 41%／24m、39%／25-48m、20%／49-78m 桶內線性分攤 [Derived]
A26: Accepted MW（期末主動電力） | B26: MW | C26: =CHOOSE(輸入與假設!$C$5,C8,C9,C10) -> 1850 | D26: =CHOOSE(輸入與假設!$C$5,D8,D9,D10) -> 3100 | E26: =CHOOSE(輸入與假設!$C$5,E8,E9,E10) -> 4000 | F26: =CHOOSE(輸入與假設!$C$5,F8,F9,F10) -> 4800 | G26: =CHOOSE(輸入與假設!$C$5,G8,G9,G10) -> 5600 | I26: ＝依 A 區情境選擇器
A27: Billable MW | B27: MW | C27: =ROUND(C26*C11,0) -> 1700 | D27: =ROUND(D26*D11,0) -> 2900 | E27: =ROUND(E26*E11,0) -> 3739 | F27: =ROUND(F26*F11,0) -> 4495 | G27: =ROUND(G26*G11,0) -> 5250 | I27: ＝Accepted × 爬坡比例（A 區）
A28: 利用率 | B28: % | C28: 0.95 | D28: 0.95 | E28: 0.94 | F28: 0.93 | G28: 0.92 | I28: 法說「近期產能實質售罄」，不擬合 100% [Assumed]
A29: 每 MW 年收入 | B29: US$bn/MW | C29: 0.0112 | D29: 0.0115 | E29: 0.0115 | F29: 0.011 | G29: 0.0105 | I29: 期末 ARR 18.5–19.5÷1.85GW≈10.0–10.5M/MW；7 月漲價 25% 只影響新約 [Derived]
A30: 新產能簽約率 | B30: % | C30: 1 | D30: 1 | E30: 0.9 | F30: 0.85 | G30: 0.8 | I30: 未被期初 RPO 占用的產能能賣掉的比例 [Assumed]
A31: 客戶違約率 | B31: % | C31: 0.005 | D31: 0.01 | E31: 0.015 | F31: 0.02 | G31: 0.025 | I31: 前三大客戶 72% 營收的定價，非預測 [Assumed]
A32: 回收率 | B32: % | C32: 0.5 | D32: 0.5 | E32: 0.5 | F32: 0.5 | G32: 0.5 | I32: [Assumed]
A33: 非算力服務營收 | B33: US$bn | C33: 0.3 | D33: 1 | E33: 1.8 | F33: 2.8 | G33: 3.8 | I33: 軟體／儲存／CPU／managed inference；損益營收與資金現金共用 [Derived]
A35: C｜利潤率（EBITDA 率單一來源；損益與資金共用）
A36: 起始 EBITDA 率（FY26） | B36: % | C36: 0.59 | I36: Q2 實際 Adj. EBITDA 率 58.6% [Verified]
A37: 穩態 EBITDA 率（FY30） | B37: % | C37: 0.65 | I37: 由下而上：每 MW 現金成本約 $3.2–3.6m／年收入 $10.9m → 67–71%；Q2 59% 含爬坡成本。基準 65%，敏感度 59%／70% [Derived]
A38: 項目 | B38: 單位 | C38: FY26 | D38: FY27 | E38: FY28 | F38: FY29 | G38: FY30 | I38: 來源／標籤
A39: EBITDA 率 | B39: % | C39: =輸入與假設!$C$36+(輸入與假設!$C$37-輸入與假設!$C$36)*0/4 -> 0.59 | D39: =輸入與假設!$C$36+(輸入與假設!$C$37-輸入與假設!$C$36)*1/4 -> 0.605 | E39: =輸入與假設!$C$36+(輸入與假設!$C$37-輸入與假設!$C$36)*2/4 -> 0.62 | F39: =輸入與假設!$C$36+(輸入與假設!$C$37-輸入與假設!$C$36)*3/4 -> 0.635 | G39: =輸入與假設!$C$36+(輸入與假設!$C$37-輸入與假設!$C$36)*4/4 -> 0.65 | I39: ＝起始＋(穩態−起始)×期數÷4（公式）
A40: 非算力服務現金 | B40: US$bn | C40: =輸入與假設!C$33*運營_產能與收入!C35 -> 0.22478319 | D40: =輸入與假設!D$33*運營_產能與收入!D35 -> 0.75576069 | E40: =輸入與假設!E$33*運營_產能與收入!E35 -> 1.3479546 | F40: =輸入與假設!F$33*運營_產能與收入!F35 -> 2.1166 | G40: =輸入與假設!G$33*運營_產能與收入!G35 -> 2.9083713 | I40: ＝服務營收 × EBITDAR 率（公式）
A41: ▸ 電力／維護 overlay（預設關閉；EBITDA 已含電費）
A42: 電力／維護 overlay（1=開） | C42: 0 | I42: EBITDA 率已含電費，開啟會重複扣除，僅供壓力測試
A43: 電價 | B43: $/MWh | C43: 60 | D43: 62 | E43: 64 | F43: 66 | G43: 68 | I43: overlay 用 [Assumed]
A44: PUE | C44: 1.25 | D44: 1.24 | E44: 1.22 | F44: 1.2 | G44: 1.2 | I44: overlay 用 [Assumed]
A45: 維護成本 | B45: US$m/MW | C45: 0.15 | D45: 0.15 | E45: 0.16 | F45: 0.16 | G45: 0.17 | I45: overlay 用 [Assumed]
A47: D｜支出（CapEx、車隊折舊、租賃、JV）
A48: 提前支出比例 λ | B48: % | C48: 0.35 | I48: 次年才上線的 MW，其建置支出落在前一年的比例 [Assumed]
A49: FY31 新增 MW（FY30 預建用） | B49: MW | C49: =CHOOSE(輸入與假設!$C$5,I8,I9,I10) -> 500 | I49: 隨情境：保守 0／基準 500／積極 1,000 [Assumed]
A50: FY26 CapEx 下限（已承諾） | B50: US$bn | C50: 35 | I50: 全年指引下緣：2026 年支出多已下單 [Interested-party]
A51: GPU 經濟壽命（年） | B51: 年 | C51: 6 | I51: 公司對伺服器與網路設備的折舊年限；決定汰換時點與車隊折舊 [Verified]
A52: 2023 年底主動電力 | B52: MW | C52: 100 | I52: 由 2023 CapEx 約 3.1bn ÷ 約 $30m/MW 推估 [Assumed]
A53: 2024 年底主動電力 | B53: MW | C53: 360 | I53: S-1：2024 年底 >360 MW [Verified]
A54: 6/30 毛 PP&E | B54: US$bn | C54: 46.736 | I54: 10-Q（含 CIP 11.9）[Verified]
A55: 每 MW 建置成本倍數（整體） | B55: % | C55: 1 | I55: 同時影響 CapEx、汰換與車隊折舊；反向 DCF 用；預設 100%
A56: 項目 | B56: 單位 | C56: FY26 | D56: FY27 | E56: FY28 | F56: FY29 | G56: FY30 | I56: 來源／標籤
A57: 每 MW 建置成本 | B57: US$m/MW | C57: 34 | D57: 34 | E57: 34 | F57: 34 | G57: 34 | I57: GPU＋網路＋機房內裝；以 FY26 校準重現全年指引 35–39 [Derived]
A58: 客戶預付占毛 CapEx | B58: % | C58: 0.08 | D58: 0.08 | E58: 0.08 | F58: 0.08 | G58: 0.08 | I58: H1 遞延收入淨流入 1.365÷CapEx 16.139＝8.5% [Derived]
A59: 在帳現金租金（10-Q 到期表） | B59: US$bn | C59: 1.04 | D59: 2.339 | E59: 2.306 | F59: 2.373 | G59: 2.289 | I59: 營業＋融資租賃未折現付款；2030 後尚有 19.023 [Verified]
A60: 表外現金租金（未起租） | B60: US$bn | C60: =C12*MAX(0,C26-1500)/(C10-1500) -> 0.3 | D60: =D12*MAX(0,D26-1500)/(D10-1500) -> 1.6 | E60: =E12*MAX(0,E26-1500)/(E10-1500) -> 2.4193548 | F60: =F12*MAX(0,F26-1500)/(F10-1500) -> 2.75 | G60: =G12*MAX(0,G26-1500)/(G10-1500) -> 2.9015385 | I60: ＝積極路徑 × 新增 MW 比例（A 區）[Assumed]
A61: JV 已承諾餘額出資 | B61: US$bn | C61: 1.15 | D61: 0 | E61: 0 | F61: 0 | G61: 0 | I61: 10-Q：兩個 JV 承諾最高 1.7，2026 年內履行；H1 已付 0.55 [Verified／Derived]
A62: JV 後續增資＋策略投資 | B62: US$bn | C62: 0.1 | D62: 0.4 | E62: 0.3 | F62: 0.2 | G62: 0.2 | I62: 入夥後須追加出資，金額未揭露 [Assumed]
A63: JV／策略投資出資 | B63: US$bn | C63: =C61+C62 -> 1.25 | D63: =D61+D62 -> 0.4 | E63: =E61+E62 -> 0.3 | F63: =F61+F62 -> 0.2 | G63: =G61+G62 -> 0.2 | I63: ＝已承諾餘額＋後續增資
A64: ▸ CapEx 推導明細（由 Accepted MW 連動）
A65: 期初主動電力 | B65: MW | C65: =輸入與假設!$C$19 -> 850 | D65: =C26 -> 1850 | E65: =D26 -> 3100 | F65: =E26 -> 4000 | G65: =F26 -> 4800 | I65: FY26 期初＝2025 年底 850 MW
A66: 本期新增 MW | B66: MW | C66: =C26-C65 -> 1000 | D66: =D26-D65 -> 1250 | E66: =E26-E65 -> 900 | F66: =F26-F65 -> 800 | G66: =G26-G65 -> 800
A67: 次期新增 MW | B67: MW | C67: =D26-C26 -> 1250 | D67: =E26-D26 -> 900 | E67: =F26-E26 -> 800 | F67: =G26-F26 -> 800 | G67: =輸入與假設!$C$49 -> 500
A68: 全年毛 CapEx（公式） | B68: US$bn | C68: =(C66*(1-輸入與假設!$C$48)+C67*輸入與假設!$C$48)*C57*輸入與假設!$C$55/1000 -> 36.975 | D68: =(D66*(1-輸入與假設!$C$48)+D67*輸入與假設!$C$48)*D57*輸入與假設!$C$55/1000 -> 38.335 | E68: =(E66*(1-輸入與假設!$C$48)+E67*輸入與假設!$C$48)*E57*輸入與假設!$C$55/1000 -> 29.41 | F68: =(F66*(1-輸入與假設!$C$48)+F67*輸入與假設!$C$48)*F57*輸入與假設!$C$55/1000 -> 27.2 | G68: =(G66*(1-輸入與假設!$C$48)+G67*輸入與假設!$C$48)*G57*輸入與假設!$C$55/1000 -> 23.63 | I68: ＝(本期新增×(1−λ)＋次期新增×λ)×每 MW 成本
A69: 成長型 CapEx（模型期） | B69: US$bn | C69: =MAX(C68,輸入與假設!$C$50)-輸入與假設!$C$124 -> 20.836 | D69: =D68 -> 38.335 | E69: =E68 -> 29.41 | F69: =F68 -> 27.2 | G69: =G68 -> 23.63 | I69: FY26＝MAX(全年公式, 下限) − 1H 已認列 16.139
A70: GPU 汰換 CapEx | B70: US$bn | C70: =IF(2026-輸入與假設!$C$51=2023,輸入與假設!$C$52,IF(2026-輸入與假設!$C$51=2024,輸入與假設!$C$53-輸入與假設!$C$52,IF(2026-輸入與假設!$C$51=2025,輸入與假設!$C$19-輸入與假設!$C$53,0)))*C57*輸入與假設!$C$55/1000 -> 0 | D70: =IF(2027-輸入與假設!$C$51=2023,輸入與假設!$C$52,IF(2027-輸入與假設!$C$51=2024,輸入與假設!$C$53-輸入與假設!$C$52,IF(2027-輸入與假設!$C$51=2025,輸入與假設!$C$19-輸入與假設!$C$53,0)))*D57*輸入與假設!$C$55/1000 -> 0 | E70: =IF(2028-輸入與假設!$C$51=2023,輸入與假設!$C$52,IF(2028-輸入與假設!$C$51=2024,輸入與假設!$C$53-輸入與假設!$C$52,IF(2028-輸入與假設!$C$51=2025,輸入與假設!$C$19-輸入與假設!$C$53,0)))*E57*輸入與假設!$C$55/1000 -> 0 | F70: =IF(2029-輸入與假設!$C$51=2023,輸入與假設!$C$52,IF(2029-輸入與假設!$C$51=2024,輸入與假設!$C$53-輸入與假設!$C$52,IF(2029-輸入與假設!$C$51=2025,輸入與假設!$C$19-輸入與假設!$C$53,0)))*F57*輸入與假設!$C$55/1000 -> 3.4 | G70: =IF(2030-輸入與假設!$C$51=2023,輸入與假設!$C$52,IF(2030-輸入與假設!$C$51=2024,輸入與假設!$C$53-輸入與假設!$C$52,IF(2030-輸入與假設!$C$51=2025,輸入與假設!$C$19-輸入與假設!$C$53,0)))*G57*輸入與假設!$C$55/1000 -> 8.84 | I70: ＝(本年 − 壽命) 那年新增的 MW × 每 MW 成本；取代已折舊完的設備
A71: 期初毛 PP&E | B71: US$bn | C71: =輸入與假設!$C$54 -> 46.736 | D71: =C71+C69 -> 67.572 | E71: =D71+D69 -> 105.907 | F71: =E71+E69 -> 135.317 | G71: =F71+F69 -> 162.517 | I71: 之後＝前期期初＋前期成長型 CapEx（汰換不增加基礎）
A72: ▸ CapEx 與折舊（結果；下游引用）
A73: 毛 CapEx（模型期，下游引用此列） | B73: US$bn | C73: =C69+C70 -> 20.836 | D73: =D69+D70 -> 38.335 | E73: =E69+E70 -> 29.41 | F73: =F69+F70 -> 30.6 | G73: =G69+G70 -> 32.47 | I73: ＝成長型＋汰換
A74: D&A（車隊折舊） | B74: US$bn | C74: =(C71+0.5*C69)/輸入與假設!$C$51*C24 -> 4.7628333 | D74: =(D71+0.5*D69)/輸入與假設!$C$51*D24 -> 14.456583 | E74: =(E71+0.5*E69)/輸入與假設!$C$51*E24 -> 20.102 | F74: =(F71+0.5*F69)/輸入與假設!$C$51*F24 -> 24.8195 | G74: =(G71+0.5*G69)/輸入與假設!$C$51*G24 -> 29.055333 | I74: ＝(期初毛 PP&E＋本期成長型×½)÷壽命×期間長度
A76: E｜融資（期初現金、既有債務、瀑布參數）
A77: 期初現金（2026-06-30） | B77: US$bn | C77: 5.5 | I77: 10-Q：現金 5.524＋有價證券 0.015；受限現金 1.38 不計 [Verified]
A78: 股權／可轉債金額 | B78: US$bn | C78: 6.2 | I78: 9/17 可轉債淨現金約 3.2＋ATM 上限 35m 股 × $85.43 ≈ 3.0 [Verified]
A79: 計入股權／可轉債（1=是） | C79: 1 | I79: 關閉則 FY26 少 6.2bn 來源
A80: 未動用信用額度 | B80: US$bn | C80: 10 | I80: 10-Q 可用額度 10.014（RCF＋DDTL 未動用）[Verified]
A81: 瀑布可動用未動用額度（1=是） | C81: 1 | I81: 瀑布第一順位；已承諾額度，不受 債務／backlog 上限限制
A82: 債務排程攤還（1=開） | C82: 1 | I82: 10-Q 本金到期表；關閉＝假設全額再融資
A83: 債務／backlog 上限 | B83: x | C83: 1 | I83: 預設 1.0x：依 2026 年實際融資組合（債務約 77%、股權約 23%）校準；公司簡報當前約 0.4x（敏感度）[Derived]
A84: 新簽合約年期 | B84: 年 | C84: 5 | I84: Q4 法說：加權平均合約約 5 年；決定 backlog 補入量 [Interested-party]
A85: 最低現金 | B85: US$bn | C85: 2 | I85: 期前融資的現金底線 [Assumed]
A86: 股權發行價 | B86: US$ | C86: 85.43 | I86: 預設 2026-09-21 收盤 [Verified]
A87: 股權發行折價 | B87: % | C87: 0.1 | I87: 大額增資的折讓 [Assumed]
A88: 每年股權吸收上限（占現市值） | B88: % | C88: 0.2 | I88: 2026 年實際約 13%；輸入 ≥900% 視為無上限 [Assumed]
A89: 高息債利率（股權上限溢出） | B89: % | C89: 0.12 | I89: 高於 2031 票據 9.75%；CDS 中價 720bps [Assumed]
A90: CDS 中價 | B90: bps | C90: 720 | I90: 2026-09 中價 720、Bid/Ask 690／750、區間 680–855 [User-provided]
A91: CDS 傳入新債利率（1=開） | C91: 0 | I91: 開啟：新債利率＋MAX(0,CDS−450)×0.4/100。預設關以免與 9% 重複
A92: 項目 | B92: 單位 | C92: FY26 | D92: FY27 | E92: FY28 | F92: FY29 | G92: FY30 | I92: 來源／標籤
A93: 排程還本（10-Q 本金表） | B93: US$bn | C93: 4.413 | D93: 6.184 | E93: 4.416 | F93: 2.421 | G93: 3.221 | I93: 本金合計 35.551；其後 14.896 [Verified]
A94: 新債利率 | B94: % | C94: 0.09 | D94: 0.09 | E94: 0.09 | F94: 0.09 | G94: 0.09 | I94: 瀑布新債成本：2031 票據 9.75%、2032 9.625%、DDTL5.0 SOFR+450 [Derived]
A95: 存量債務利息（下游引用此列） | B95: US$bn | C95: =資產負債_既有債務!C35 -> 1.8058963 | D95: =資產負債_既有債務!D35 -> 2.4660068 | E95: =資產負債_既有債務!E35 -> 2.0200947 | F95: =資產負債_既有債務!F35 -> 1.7324815 | G95: =資產負債_既有債務!G35 -> 1.4951385 | I95: ＝債務明細頁：平均本金×加權有效利率×期間長度＋可轉債利息＋FY26 校準
A97: F｜評價（價格、股數、折現、倍數、權重）
A98: 現價（2026-09-21 收盤） | B98: US$ | C98: 85.43 | I98: S&P Global via stockanalysis.com；9/17 收盤 79.88 [Verified]
A99: 股數（含 ATM 上限） | B99: bn | C99: 0.587 | I99: 7/31 流通 0.5515＋ATM 35m [Verified]
A100: 淨負債（6/30） | B100: US$bn | C100: 30 | I100: 本金 35.551 − 現金 5.524 [Verified]
A101: WACC | B101: % | C101: 0.11 | I101: [Assumed]
A102: 永續成長 g | B102: % | C102: 0.03 | I102: [Assumed]
A103: 終值維持性 CapEx 占 D&A | B103: % | C103: 0.8 | I103: 終值不讓成長性 CapEx 偽裝成永續 FCF [Assumed]
A104: 稅率 | B104: % | C104: 0.21 | I104: 美國聯邦名目稅率 [Verified]
A105: 期初 NOL（虧損扣抵） | B105: US$bn | C105: 4 | I105: 6/30 累積虧損約 4.0；抵扣上限為應稅所得 80% [Derived]
A106: EV/EBITDA 倍數 | B106: x | C106: 6 | I106: 穩態合理倍數約 3.4–6.0x（轉換率 ÷ (WACC − g)），6x 為上緣 [Assumed]
...

Sheet 各期收支
A1: 支出與資金 — 五層支出、四層來源、現金橋
A2: FY26 欄＝1H 實際（10-Q 現金流量表口徑）＋下半年模型；FY27 以後為純模型。瀑布以「融資前現金」決定需求並直接由各支出列加總，因此沒有循環參照
A4: 項目 | B4: 單位 | C4: FY26 | D4: FY27 | E4: FY28 | F4: FY29 | G4: FY30 | I4: 公式／來源說明
A5: 支出（五層）
A6: ① 毛 CapEx（認列，備忘） | B6: US$bn | C6: =輸入與假設!$C$124+輸入與假設!C$73 -> 36.975 | D6: =輸入與假設!D$73 -> 38.335 | E6: =輸入與假設!E$73 -> 29.41 | F6: =輸入與假設!F$73 -> 30.6 | G6: =輸入與假設!G$73 -> 32.47 | I6: FY26＝1H 實際認列 16.139＋2H 模型；對照公司全年指引 35–39。備忘列：用途合計採現金口徑，不用這一列
A7: 客戶預付率 | B7: % | C7: =輸入與假設!C$58 -> 0.08 | D7: =輸入與假設!D$58 -> 0.08 | E7: =輸入與假設!E$58 -> 0.08 | F7: =輸入與假設!F$58 -> 0.08 | G7: =輸入與假設!G$58 -> 0.08
A8: 客戶預付金額（抵減，2H 起） | B8: US$bn | C8: =輸入與假設!C$73*C7 -> 1.66688 | D8: =輸入與假設!D$73*D7 -> 3.0668 | E8: =輸入與假設!E$73*E7 -> 2.3528 | F8: =輸入與假設!F$73*F7 -> 2.448 | G8: =輸入與假設!G$73*G7 -> 2.5976 | I8: 1H 的預付已含在實際 CFO 內，不重複計入
A9: ① CapEx（用途用：1H 現金／2H 毛額） | B9: US$bn | C9: =輸入與假設!$C$123+輸入與假設!C$73 -> 34.953 | D9: =輸入與假設!D$73 -> 38.335 | E9: =輸入與假設!E$73 -> 29.41 | F9: =輸入與假設!F$73 -> 30.6 | G9: =輸入與假設!G$73 -> 32.47 | I9: 1H 採現金流量表的現金購置 14.117；2H 起採毛額，客戶預付在來源端抵回（避免重複計入）
A10: ② 在帳現金租金（備忘，1H 已含在 CFO） | B10: US$bn | C10: =輸入與假設!C$59 -> 1.04 | D10: =輸入與假設!D$59 -> 2.339 | E10: =輸入與假設!E$59 -> 2.306 | F10: =輸入與假設!F$59 -> 2.373 | G10: =輸入與假設!G$59 -> 2.289 | I10: 見『租賃與承諾』頁；2030 後尚有 19.023。FY26 欄僅 2H：1H 租金 0.748 已含在實際 CFO 內
A11: ② 表外現金租金（未起租） | B11: US$bn | C11: =輸入與假設!C$60 -> 0.3 | D11: =輸入與假設!D$60 -> 1.6 | E11: =輸入與假設!E$60 -> 2.4193548 | F11: =輸入與假設!F$60 -> 2.75 | G11: =輸入與假設!G$60 -> 2.9015385 | I11: 未起租 35.5＋單站上限 14.7＋355MW 造價計租的現金路徑
A12: 租金合計 | B12: US$bn | C12: =C10+C11 -> 1.34 | D12: =D10+D11 -> 3.939 | E12: =E10+E11 -> 4.7253548 | F12: =F10+F11 -> 5.123 | G12: =G10+G11 -> 5.1905385
A13: ③ 存量債務利息（備忘，1H 已含在 CFO） | B13: US$bn | C13: =輸入與假設!C$95 -> 1.8058963 | D13: =輸入與假設!D$95 -> 2.4660068 | E13: =輸入與假設!E$95 -> 2.0200947 | F13: =輸入與假設!F$95 -> 1.7324815 | G13: =輸入與假設!G$95 -> 1.4951385 | I13: 6/30 債務餘額的利息。FY26 全年利息＝1H 實際 1.176＋2H 1.8＝2.98（見下方備忘）
A14: 期初累積現金 | B14: US$bn | C14: =輸入與假設!$C$121 -> 3.127 | D14: =C41 -> 2 | E14: =D41 -> 2 | F14: =E41 -> 2 | G14: =F41 -> 2 | I14: FY26 自 2025-12-31 的 3.127 起算；之後＝前期期末累積現金
A15: 新債利率 | B15: % | C15: =IF(輸入與假設!$C$91=1,輸入與假設!C$94+MAX(0,輸入與假設!$C$90-450)/100*0.004,輸入與假設!C$94) -> 0.09 | D15: =IF(輸入與假設!$C$91=1,輸入與假設!D$94+MAX(0,輸入與假設!$C$90-450)/100*0.004,輸入與假設!D$94) -> 0.09 | E15: =IF(輸入與假設!$C$91=1,輸入與假設!E$94+MAX(0,輸入與假設!$C$90-450)/100*0.004,輸入與假設!E$94) -> 0.09 | F15: =IF(輸入與假設!$C$91=1,輸入與假設!F$94+MAX(0,輸入與假設!$C$90-450)/100*0.004,輸入與假設!F$94) -> 0.09 | G15: =IF(輸入與假設!$C$91=1,輸入與假設!G$94+MAX(0,輸入與假設!$C$90-450)/100*0.004,輸入與假設!G$94) -> 0.09 | I15: CDS 開關：＋MAX(0,CDS−450)×0.4bp/bp
A16: ③ 新債利息（瀑布） | B16: US$bn | C16: =C63 -> 0.56495231 | D16: =D63 -> 4.0708204 | E16: =E63 -> 5.5864719 | F16: =F63 -> 5.8690106 | G16: =G63 -> 6.515096 | I16: ＝新債利率×期間長度×(期初新債＋本期舉借)；見下方「期前融資瀑布」
A17: 利息合計 | B17: US$bn | C17: =C13+C16 -> 2.3708486 | D17: =D13+D16 -> 6.5368271 | E17: =E13+E16 -> 7.6065666 | F17: =F13+F16 -> 7.6014921 | G17: =G13+G16 -> 8.0102346
A18: ④ JV／策略投資出資 | B18: US$bn | C18: =輸入與假設!$C$125+輸入與假設!C$63 -> 1.938 | D18: =輸入與假設!D$63 -> 0.4 | E18: =輸入與假設!E$63 -> 0.3 | F18: =輸入與假設!F$63 -> 0.2 | G18: =輸入與假設!G$63 -> 0.2 | I18: FY26＝1H 實際 0.688（JV 0.550＋策略投資 0.138）＋2H 模型。10-Q 已承諾 1.7bn。CRWV 不發股息
A19: 電力（overlay） | B19: US$bn | C19: =IF(輸入與假設!$C$42=1,運營_產能與收入!C9*8760*輸入與假設!C$44*輸入與假設!C$43/1000000000*運營_產能與收入!C7,0) -> 0 | D19: =IF(輸入與假設!$C$42=1,運營_產能與收入!D9*8760*輸入與假設!D$44*輸入與假設!D$43/1000000000*運營_產能與收入!D7,0) -> 0 | E19: =IF(輸入與假設!$C$42=1,運營_產能與收入!E9*8760*輸入與假設!E$44*輸入與假設!E$43/1000000000*運營_產能與收入!E7,0) -> 0 | F19: =IF(輸入與假設!$C$42=1,運營_產能與收入!F9*8760*輸入與假設!F$44*輸入與假設!F$43/1000000000*運營_產能與收入!F7,0) -> 0 | G19: =IF(輸入與假設!$C$42=1,運營_產能與收入!G9*8760*輸入與假設!G$44*輸入與假設!G$43/1000000000*運營_產能與收入!G7,0) -> 0 | I19: ＝Accepted MW×8760×PUE×電價÷1e9×期間係數。CRWV 電費多經房東轉嫁，預設關閉
A20: 維護（overlay） | B20: US$bn | C20: =IF(輸入與假設!$C$42=1,運營_產能與收入!C9*輸入與假設!C$45/1000*運營_產能與收入!C7,0) -> 0 | D20: =IF(輸入與假設!$C$42=1,運營_產能與收入!D9*輸入與假設!D$45/1000*運營_產能與收入!D7,0) -> 0 | E20: =IF(輸入與假設!$C$42=1,運營_產能與收入!E9*輸入與假設!E$45/1000*運營_產能與收入!E7,0) -> 0 | F20: =IF(輸入與假設!$C$42=1,運營_產能與收入!F9*輸入與假設!F$45/1000*運營_產能與收入!F7,0) -> 0 | G20: =IF(輸入與假設!$C$42=1,運營_產能與收入!G9*輸入與假設!G$45/1000*運營_產能與收入!G7,0) -> 0
A21: ⑤ 排程還本（10-Q 本金表） | B21: US$bn | C21: =輸入與假設!$C$127+IF(輸入與假設!$C$82=1,輸入與假設!C$93,0) -> 9.632 | D21: =IF(輸入與假設!$C$82=1,輸入與假設!D$93,0) -> 6.184 | E21: =IF(輸入與假設!$C$82=1,輸入與假設!E$93,0) -> 4.416 | F21: =IF(輸入與假設!$C$82=1,輸入與假設!F$93,0) -> 2.421 | G21: =IF(輸入與假設!$C$82=1,輸入與假設!G$93,0) -> 3.221 | I21: FY26＝1H 實際還款 5.219＋2H 到期表 4.413
A22: ⑥ capped call 支出（1H 實際） | B22: US$bn | C22: =輸入與假設!$C$128 -> 0.492 | D22: =0 -> 0 | E22: =0 -> 0 | F22: =0 -> 0 | G22: =0 -> 0 | I22: Q2 4.0bn 可轉債的 capped call 現金支出
A23: 用途合計（現金口徑） | B23: US$bn | C23: =C9+C12+C17+C18+C19+C20+C21+C22 -> 50.725849 | D23: =D9+D12+D17+D18+D19+D20+D21+D22 -> 55.394827 | E23: =E9+E12+E17+E18+E19+E20+E21+E22 -> 46.457921 | F23: =F9+F12+F17+F18+F19+F20+F21+F22 -> 45.945492 | G23: =G9+G12+G17+G18+G19+G20+G21+G22 -> 49.091773 | I23: FY26 的 1H 部分採 10-Q 現金流量表口徑（現金購置、還款、JV、capped call）；1H 的利息與租金已含在 CFO 內，不重複列
A24: 來源（四層）
A25: Ⓐ0 1H26 實際營運現金流（CFO） | B25: US$bn | C25: =輸入與假設!$C$122 -> 3.663 | D25: =0 -> 0 | E25: =0 -> 0 | F25: =0 -> 0 | G25: =0 -> 0 | I25: 10-Q 實際值，取代模型推算；已含 1H 的利息、租金與客戶預付
A26: Ⓐ RPO 現金（2H 起） | B26: US$bn | C26: =運營_產能與收入!C36 -> 6.0636896 | D26: =運營_產能與收入!D36 -> 18.895425 | E26: =運營_產能與收入!E36 -> 19.131182 | F26: =運營_產能與收入!F36 -> 18.78145 | G26: =運營_產能與收入!G36 -> 13.374717
A27: Ⓑ 新簽約現金 | B27: US$bn | C27: =運營_產能與收入!C37 -> 0 | D27: =運營_產能與收入!D37 -> 0 | E27: =運營_產能與收入!E37 -> 6.7854123 | F27: =運營_產能與收入!F37 -> 10.826919 | G27: =運營_產能與收入!G37 -> 17.759402
A28: Ⓒ 非算力服務現金 | B28: US$bn | C28: =輸入與假設!C$40 -> 0.22478319 | D28: =輸入與假設!D$40 -> 0.75576069 | E28: =輸入與假設!E$40 -> 1.3479546 | F28: =輸入與假設!F$40 -> 2.1166 | G28: =輸入與假設!G$40 -> 2.9083713
A29: Ⓓ 客戶預付（2H 起） | B29: US$bn | C29: =C8 -> 1.66688 | D29: =D8 -> 3.0668 | E29: =E8 -> 2.3528 | F29: =F8 -> 2.448 | G29: =G8 -> 2.5976
A30: 營運來源合計 | B30: US$bn | C30: =C25+C26+C27+C28+C29 -> 11.618353 | D30: =D25+D26+D27+D28+D29 -> 22.717986 | E30: =E25+E26+E27+E28+E29 -> 29.617349 | F30: =F25+F26+F27+F28+F29 -> 34.172969 | G30: =G25+G26+G27+G28+G29 -> 36.64009
A31: Ⓔ 股權／可轉債（融資） | B31: US$bn | C31: =輸入與假設!$C$129+IF(輸入與假設!$C$79=1,輸入與假設!$C$78,0) -> 9.182 | D31: =0 -> 0 | E31: =0 -> 0 | F31: =0 -> 0 | G31: =0 -> 0 | I31: FY26＝1H 私募股權 2.982＋2H 可轉債淨現金 3.2＋ATM 上限 2.8
A32: Ⓕ 1H26 實際借款（融資） | B32: US$bn | C32: =輸入與假設!$C$126 -> 16.747 | D32: =0 -> 0 | E32: =0 -> 0 | F32: =0 -> 0 | G32: =0 -> 0 | I32: 10-Q：H1 借款 16.747。1H 的缺口實際上就是靠舉債填補的
A33: Ⓖ 瀑布：新債（額度＋資產層） | B33: US$bn | C33: =C58 -> 12.554496 | D33: =D58 -> 32.676842 | E33: =E58 -> 16.840572 | F33: =F58 -> 3.1393189 | G33: =G58 -> 7.1787275 | I33: 見下方「期前融資瀑布」
A34: Ⓗ 瀑布：股權募資 | B34: US$bn | C34: =C61 -> 0 | D34: =D61 -> 0 | E34: =E61 -> 0 | F34: =F61 -> 8.6332038 | G34: =G61 -> 5.2729553 | I34: 債務用罄後的殘差；每年不超過股權吸收上限
A35: Ⓘ 瀑布：高息債（股權上限溢出） | B35: US$bn | C35: =C62 -> 0 | D35: =D62 -> 0 | E35: =E62 -> 0 | F35: =F62 -> 0 | G35: =G62 -> 0 | I35: 股權超過每年上限的部分；不受 backlog 上限約束
A36: 總來源（含融資） | B36: US$bn | C36: =C30+C31+C32+C33+C34+C35 -> 50.101849 | D36: =D30+D31+D32+D33+D34+D35 -> 55.394827 | E36: =E30+E31+E32+E33+E34+E35 -> 46.457921 | F36: =F30+F31+F32+F33+F34+F35 -> 45.945492 | G36: =G30+G31+G32+G33+G34+G35 -> 49.091773
A37: 缺口與現金橋
A38: 1H 其他／受限現金調節 | B38: US$bn | C38: =輸入與假設!$C$77-(輸入與假設!$C$121+輸入與假設!$C$122+輸入與假設!$C$126+輸入與假設!$C$129-輸入與假設!$C$123-輸入與假設!$C$125-輸入與假設!$C$127-輸入與假設!$C$128) -> -0.503 | D38: =0 -> 0 | E38: =0 -> 0 | F38: =0 -> 0 | G38: =0 -> 0 | I38: 使 1H 實際流量接回 6/30 現金餘額；差額來自受限現金重分類與未逐項列出的項目
A39: 營運缺口（不含融資、不含還本） | B39: US$bn | C39: =C30-(C23-C21-C22) -> -28.983496 | D39: =D30-(D23-D21-D22) -> -26.492842 | E39: =E30-(E23-E21-E22) -> -12.424572 | F39: =F30-(F23-F21-F22) -> -9.3515227 | G39: =G30-(G23-G21-G22) -> -9.2306828 | I39: 本業能不能自給：營運來源 −（用途 − 排程還本 − capped call）
A40: 期間缺口（含融資） | B40: US$bn | C40: =C36-C23+C38 -> -1.127 | D40: =D36-D23+D38 -> 0 | E40: =E36-E23+E38 -> 0 | F40: =F36-F23+F38 -> 0 | G40: =G36-G23+G38 -> 0
A41: 期末累積現金 | B41: US$bn | C41: =C14+C40 -> 2 | D41: =D14+D40 -> 2 | E41: =E14+E40 -> 2 | F41: =F14+F40 -> 2 | G41: =G14+G40 -> 2 | I41: 期前融資：每期末不低於最低現金
A43: 期前融資瀑布（缺口在需要前一期先融好：額度 → 資產層新債 → 股權）
A44: 用途（不含新債利息） | B44: US$bn | C44: =C9+C12+C13+C18+C19+C20+C21+C22 -> 50.160896 | D44: =D9+D12+D13+D18+D19+D20+D21+D22 -> 51.324007 | E44: =E9+E12+E13+E18+E19+E20+E21+E22 -> 40.87145 | F44: =F9+F12+F13+F18+F19+F20+F21+F22 -> 40.076481 | G44: =G9+G12+G13+G18+G19+G20+G21+G22 -> 42.576677 | I44: 避免循環參照：直接由各支出列加總
A45: 新債期初餘額 | B45: US$bn | C45: =0 -> 0 | D45: =C67 -> 12.554496 | E45: =D67 -> 45.231337 | F45: =E67 -> 62.07191 | G45: =F67 -> 65.211229
A46: 新債利率 × 期間長度 | B46: % | C46: =C15*運營_產能與收入!C7 -> 0.045 | D46: =D15*運營_產能與收入!D7 -> 0.09 | E46: =E15*運營_產能與收入!E7 -> 0.09 | F46: =F15*運營_產能與收入!F7 -> 0.09 | G46: =G15*運營_產能與收入!G7 -> 0.09
A47: 高息債期初餘額 | B47: US$bn | C47: =0 -> 0 | D47: =C69 -> 0 | E47: =D69 -> 0 | F47: =E69 -> 0 | G47: =F69 -> 0
A48: 高息債利率 × 期間長度 | B48: % | C48: =(輸入與假設!$C$89+IF(輸入與假設!$C$91=1,MAX(0,輸入與假設!$C$90-450)/10000*0.4,0))*運營_產能與收入!C7 -> 0.06 | D48: =(輸入與假設!$C$89+IF(輸入與假設!$C$91=1,MAX(0,輸入與假設!$C$90-450)/10000*0.4,0))*運營_產能與收入!D7 -> 0.12 | E48: =(輸入與假設!$C$89+IF(輸入與假設!$C$91=1,MAX(0,輸入與假設!$C$90-450)/10000*0.4,0))*運營_產能與收入!E7 -> 0.12 | F48: =(輸入與假設!$C$89+IF(輸入與假設!$C$91=1,MAX(0,輸入與假設!$C$90-450)/10000*0.4,0))*運營_產能與收入!F7 -> 0.12 | G48: =(輸入與假設!$C$89+IF(輸入與假設!$C$91=1,MAX(0,輸入與假設!$C$90-450)/10000*0.4,0))*運營_產能與收入!G7 -> 0.12
A49: 融資前現金（扣既有新債利息） | B49: US$bn | C49: =C14+C30+C31+C32+C38-C44-C46*C45-C48*C47 -> -9.9895435 | D49: =D14+D30+D31+D32+D38-D44-D46*D45-D48*D47 -> -27.735926 | E49: =E14+E30+E31+E32+E38-E44-E46*E45-E48*E47 -> -13.324921 | F49: =F14+F30+F31+F32+F38-F44-F46*F45-F48*F47 -> -9.489984 | G49: =G14+G30+G31+G32+G38-G44-G46*G45-G48*G47 -> -9.8055974
A50: 融資需求（補足至最低現金） | B50: US$bn | C50: =MAX(0,輸入與假設!$C$85-C49) -> 11.989544 | D50: =MAX(0,輸入與假設!$C$85-D49) -> 29.735926 | E50: =MAX(0,輸入與假設!$C$85-E49) -> 15.324921 | F50: =MAX(0,輸入與假設!$C$85-F49) -> 11.489984 | G50: =MAX(0,輸入與假設!$C$85-G49) -> 11.805597
A51: 期初 backlog | B51: US$bn | C51: =輸入與假設!$C$15+輸入與假設!$C$16 -> 128.7 | D51: =C53 -> 115.50825 | E51: =D53 -> 89.12475 | F51: =E53 -> 99.902412 | G51: =F53 -> 87.028228 | I51: FY26 期初＝6/30 RPO 103.7＋Q3 新增 25
A52: 新簽合約增量（年化增量×年期） | B52: US$bn | C52: =MAX(0,運營_產能與收入!C23/運營_產能與收入!C7-0)*輸入與假設!$C$84 -> 0 | D52: =MAX(0,運營_產能與收入!D23/運營_產能與收入!D7-運營_產能與收入!C23/運營_產能與收入!C7)*輸入與假設!$C$84 -> 0 | E52: =MAX(0,運營_產能與收入!E23/運營_產能與收入!E7-運營_產能與收入!D23/運營_產能與收入!D7)*輸入與假設!$C$84 -> 45.647078 | F52: =MAX(0,運營_產能與收入!F23/運營_產能與收入!F7-運營_產能與收入!E23/運營_產能與收入!E7)*輸入與假設!$C$84 -> 26.689665 | G52: =MAX(0,運營_產能與收入!G23/運營_產能與收入!G7-運營_產能與收入!F23/運營_產能與收入!F7)*輸入與假設!$C$84 -> 45.151657
A53: 期末 backlog | B53: US$bn | C53: =C51-運營_產能與收入!C17-運營_產能與收入!C23+C52 -> 115.50825 | D53: =D51-運營_產能與收入!D17-運營_產能與收入!D23+D52 -> 89.12475 | E53: =E51-運營_產能與收入!E17-運營_產能與收入!E23+E52 -> 99.902412 | F53: =F51-運營_產能與收入!F17-運營_產能與收入!F23+F52 -> 87.028228 | G53: =G51-運營_產能與收入!G17-運營_產能與收入!G23+G52 -> 90.985956 | I53: ＝期初 − 排程認列 − 新簽約認列 ＋ 新簽合約增量
A54: 既有債務＋9/17 可轉債（期末） | B54: US$bn | C54: =IF(輸入與假設!$C$82=1,資產負債_既有債務!C30,35.551)+3.7 -> 34.838 | D54: =IF(輸入與假設!$C$82=1,資產負債_既有債務!D30,35.551)+3.7 -> 28.654 | E54: =IF(輸入與假設!$C$82=1,資產負債_既有債務!E30,35.551)+3.7 -> 24.238 | F54: =IF(輸入與假設!$C$82=1,資產負債_既有債務!F30,35.551)+3.7 -> 21.817 | G54: =IF(輸入與假設!$C$82=1,資產負債_既有債務!G30,35.551)+3.7 -> 18.596 | I54: ＝(依到期表遞減的既有本金，若關閉攤還則維持 35.551)＋9/17 可轉債 3.7
A55: 債務上限（債務／backlog × 期末 backlog） | B55: US$bn | C55: =輸入與假設!$C$83*C53 -> 115.50825 | D55: =輸入與假設!$C$83*D53 -> 89.12475 | E55: =輸入與假設!$C$83*E53 -> 99.902412 | F55: =輸入與假設!$C$83*F53 -> 87.028228 | G55: =輸入與假設!$C$83*G53 -> 90.985956
A56: 未動用額度（期初） | B56: US$bn | C56: =IF(輸入與假設!$C$81=1,輸入與假設!$C$80,0) -> 10 | D56: =C68 -> 0 | E56: =D68 -> 0 | F56: =E68 -> 0 | G56: =F68 -> 0
A57: 新債可借上限 | B57: US$bn | C57: =MAX(0,C55-(C54+C45),C56) -> 80.67025 | D57: =MAX(0,D55-(D54+D45),D56) -> 47.916254 | E57: =MAX(0,E55-(E54+E45),E56) -> 30.433075 | F57: =MAX(0,F55-(F54+F45),F56) -> 3.1393189 | G57: =MAX(0,G55-(G54+G45),G56) -> 7.1787275 | I57: ＝MAX(上限 − 既有債務 − 期初新債, 未動用額度)
A58: 新債舉借 | B58: US$bn | C58: =MIN(C57,C50/(1-C46)) -> 12.554496 | D58: =MIN(D57,D50/(1-D46)) -> 32.676842 | E58: =MIN(E57,E50/(1-E46)) -> 16.840572 | F58: =MIN(F57,F50/(1-F46)) -> 3.1393189 | G58: =MIN(G57,G50/(1-G46)) -> 7.1787275 | I58: 期前融資：期初到位，當期全額計息，所以需求要除以 (1−利率×期間)
A59: 債務後剩餘需求 | B59: US$bn | C59: =MAX(0,C50+C46*C58-C58) -> 0 | D59: =MAX(0,D50+D46*D58-D58) -> 0 | E59: =MAX(0,E50+E46*E58-E58) -> 0 | F59: =MAX(0,F50+F46*F58-F58) -> 8.6332038 | G59: =MAX(0,G50+G46*G58-G58) -> 5.2729553
A60: 每年股權吸收上限 | B60: US$bn | C60: =IF(輸入與假設!$C$88>=9,1E+099,輸入與假設!$C$88*輸入與假設!$C$86*0.5865*運營_產能與收入!C7) -> 5.0104695 | D60: =IF(輸入與假設!$C$88>=9,1E+099,輸入與假設!$C$88*輸入與假設!$C$86*0.5865*運營_產能與收入!D7) -> 10.020939 | E60: =IF(輸入與假設!$C$88>=9,1E+099,輸入與假設!$C$88*輸入與假設!$C$86*0.5865*運營_產能與收入!E7) -> 10.020939 | F60: =IF(輸入與假設!$C$88>=9,1E+099,輸入與假設!$C$88*輸入與假設!$C$86*0.5865*運營_產能與收入!F7) -> 10.020939 | G60: =IF(輸入與假設!$C$88>=9,1E+099,輸入與假設!$C$88*輸入與假設!$C$86*0.5865*運營_產能與收入!G7) -> 10.020939 | I60: ＝現市值（發行參考價 × 0.5865bn 股）× 上限 % × 期間長度
A61: 股權募資 | B61: US$bn | C61: =MIN(C59,C60) -> 0 | D61: =MIN(D59,D60) -> 0 | E61: =MIN(E59,E60) -> 0 | F61: =MIN(F59,F60) -> 8.6332038 | G61: =MIN(G59,G60) -> 5.2729553
A62: 高息債舉借（溢出） | B62: US$bn | C62: =(C59-C61)/(1-C48) -> 0 | D62: =(D59-D61)/(1-D48) -> 0 | E62: =(E59-E61)/(1-E48) -> 0 | F62: =(F59-F61)/(1-F48) -> 0 | G62: =(G59-G61)/(1-G48) -> 0
A63: 新債＋高息債利息（期初餘額＋本期舉借） | B63: US$bn | C63: =C46*(C45+C58)+C48*(C47+C62) -> 0.56495231 | D63: =D46*(D45+D58)+D48*(D47+D62) -> 4.0708204 | E63: =E46*(E45+E58)+E48*(E47+E62) -> 5.5864719 | F63: =F46*(F45+F58)+F48*(F47+F62) -> 5.8690106 | G63: =G46*(G45+G58)+G48*(G47+G62) -> 6.515096
A64: 發行價（現價×(1−折價)） | B64: US$ | C64: =輸入與假設!$C$86*(1-輸入與假設!$C$87) -> 76.887 | D64: =輸入與假設!$C$86*(1-輸入與假設!$C$87) -> 76.887 | E64: =輸入與假設!$C$86*(1-輸入與假設!$C$87) -> 76.887 | F64: =輸入與假設!$C$86*(1-輸入與假設!$C$87) -> 76.887 | G64: =輸入與假設!$C$86*(1-輸入與假設!$C$87) -> 76.887
A65: 新發行股數 | B65: bn | C65: =C61/C64 -> 0 | D65: =D61/D64 -> 0 | E65: =E61/E64 -> 0 | F65: =F61/F64 -> 0.11228431 | G65: =G61/G64 -> 0.068580584
A66: 累計新股 | B66: bn | C66: =C65 -> 0 | D66: =C66+D65 -> 0 | E66: =D66+E65 -> 0 | F66: =E66+F65 -> 0.11228431 | G66: =F66+G65 -> 0.18086489
A67: 新債期末餘額 | B67: US$bn | C67: =C45+C58 -> 12.554496 | D67: =D45+D58 -> 45.231337 | E67: =E45+E58 -> 62.07191 | F67: =F45+F58 -> 65.211229 | G67: =G45+G58 -> 72.389956
A68: 未動用額度（期末） | B68: US$bn | C68: =C56-MIN(C56,C58) -> 0 | D68: =D56-MIN(D56,D58) -> 0 | E68: =E56-MIN(E56,E58) -> 0 | F68: =F56-MIN(F56,F58) -> 0 | G68: =G56-MIN(G56,G58) -> 0
A69: 高息債期末餘額 | B69: US$bn | C69: =C47+C62 -> 0 | D69: =D47+D62 -> 0 | E69: =E47+E62 -> 0 | F69: =F47+F62 -> 0 | G69: =G47+G62 -> 0
A70: 期末總債務（既有＋可轉債＋新債＋高息債） | B70: US$bn | C70: =C54+C67+C69 -> 47.392496 | D70: =D54+D67+D69 -> 73.885337 | E70: =E54+E67+E69 -> 86.30991 | F70: =F54+F67+F69 -> 87.028228 | G70: =G54+G67+G69 -> 90.985956
A71: 融資前累積現金 | B71: US$bn | C71: =C14+C30+C31+C32+C38-C44 -> -9.9895435 | D71: =C71+D30+D31-D44 -> -38.595565 | E71: =D71+E30+E31-E44 -> -49.849665 | F71: =E71+F30+F31-F44 -> -55.753177 | G71: =F71+G30+G31-G44 -> -61.689764 | I71: 若不做任何新融資的累積現金；負值＝外部資金需求
A73: 四層橋（驗算）
A74: 期初現金（2025-12-31） | C74: =輸入與假設!$C$121 -> 3.127
A75: ＋ 營運缺口合計 | C75: =SUM(C39:G39) -> -86.483115
A76: ＋ 股權／可轉債合計 | C76: =SUM(C31:G31) -> 9.182
A77: ＋ 1H 實際借款 | C77: =SUM(C32:G32) -> 16.747
A78: − capped call（1H） | C78: =-SUM(C22:G22) -> -0.492
A79: ＋ 1H 其他／受限現金調節 | C79: =SUM(C38:G38) -> -0.503
A80: ＋ 瀑布新債＋股權＋高息債合計 | C80: =SUM(C33:G33)+SUM(C34:G34)+SUM(C35:G35) -> 86.296115
A81: − 排程還本合計 | C81: =-SUM(C21:G21) -> -25.874
A82: ＝ 期末現金（橋算） | C82: =SUM(C74:C81) -> 2
A83: 對照：期末累積現金（表算） | C83: =G41 -> 2
A84: 差異（應為 0） | C84: =C82-C83 -> -2.5757174e-14 | I84: 若不為 0，表示公式鏈被改壞
A86: FY26 全年備忘（對照公司指引）
A87: FY26 總營收（1H 實際＋2H 模型） | C87: =運營_產能與收入!C27 -> 13.066 | I87: 公司指引 12.4–13.2
A88: FY26 CapEx 認列（1H＋2H） | C88: =C6 -> 36.975 | I88: 公司指引 35–39
A89: FY26 利息（1H 實際＋2H 模型） | C89: =輸入與假設!$C$130+輸入與假設!C$95+C16 -> 3.5468486 | I89: Q3 指引 0.86–0.94／季
A90: FY26 租賃現金（1H 實際＋2H 模型） | C90: =輸入與假設!$C$131+C12 -> 2.088 | I90: 1H 實際支付 0.748
A91: FY26 排程還本（1H 實際＋2H） | C91: =C21 -> 9.632 | I91: 1H 實際還款 5.219＋2H 到期表 4.413

Sheet 運營_產能與收入
A1: 產能與收入 — 合約排程 vs 機房產能
A2: 兩條線獨立產生後相減：排程>容量→瓶頸（收不到）；容量>排程→剩餘產能（要靠新簽約賣掉）
A3: FY26 欄口徑：MW 為年底存量；標示「（模型期）」的收入列只含 2026 下半年——RPO 桶自 2026-06-30 起算，1H 收入已實現、不再受產能約束。1H 實際單列，兩者相加即 FY26 全年（見本頁「FY26 全年」列）。
A5: 項目 | B5: 單位 | C5: FY26 | D5: FY27 | E5: FY28 | F5: FY29 | G5: FY30 | I5: 公式／來源說明
A6: 模型期間 | C6: ="2026-07-01~12-31" -> 2026-07-01~12-31 | D6: ="2027 全年" -> 2027 全年 | E6: ="2028 全年" -> 2028 全年 | F6: ="2029 全年" -> 2029 全年 | G6: ="2030 全年" -> 2030 全年 | I6: FY26 的模型期只有下半年；1H 已實現的營收單列於下方
A7: 模型期長度（年） | C7: =輸入與假設!C$24 -> 0.5 | D7: =輸入與假設!D$24 -> 1 | E7: =輸入與假設!E$24 -> 1 | F7: =輸入與假設!F$24 -> 1 | G7: =輸入與假設!G$24 -> 1 | I7: 只用於下方三處：容量上限、電力、維護——把年率換算成該期金額
A8: （A）機房：容量上限
A9: Accepted MW（已驗收，單調不減） | B9: MW | C9: =MAX(0,輸入與假設!C$26) -> 1850 | D9: =MAX(輸入與假設!D$26,C9) -> 3100 | E9: =MAX(輸入與假設!E$26,D9) -> 4000 | F9: =MAX(輸入與假設!F$26,E9) -> 4800 | G9: =MAX(輸入與假設!G$26,F9) -> 5600 | I9: 引擎規則：不得低於前期（產能不會消失）
A10: Billable MW（上限為 Accepted） | B10: MW | C10: =MIN(MAX(0,輸入與假設!C$27),C9) -> 1700 | D10: =MIN(MAX(0,輸入與假設!D$27),D9) -> 2900 | E10: =MIN(MAX(0,輸入與假設!E$27),E9) -> 3739 | F10: =MIN(MAX(0,輸入與假設!F$27),F9) -> 4495 | G10: =MIN(MAX(0,輸入與假設!G$27),G9) -> 5250 | I10: 引擎規則：可計費不得超過已驗收
A11: 期初在役 MW | B11: MW | C11: =輸入與假設!$C$20 -> 1350 | D11: =C10 -> 1700 | E11: =D10 -> 2900 | F11: =E10 -> 3739 | G11: =F10 -> 4495 | I11: 前期期末＝本期期初
A12: 平均在役 MW（FY26 欄為下半年平均） | B12: MW | C12: =IF(輸入與假設!$C$21=1,(C11+C10)/2,C10) -> 1525 | D12: =IF(輸入與假設!$C$21=1,(D11+D10)/2,D10) -> 2300 | E12: =IF(輸入與假設!$C$21=1,(E11+E10)/2,E10) -> 3319.5 | F12: =IF(輸入與假設!$C$21=1,(F11+F10)/2,F10) -> 4117 | G12: =IF(輸入與假設!$C$21=1,(G11+G10)/2,G10) -> 4872.5 | I12: 開關在輸入頁：1＝(期初+期末)/2，0＝期末全期化
A13: 利用率 | B13: % | C13: =輸入與假設!C$28 -> 0.95 | D13: =輸入與假設!D$28 -> 0.95 | E13: =輸入與假設!E$28 -> 0.94 | F13: =輸入與假設!F$28 -> 0.93 | G13: =輸入與假設!G$28 -> 0.92
A14: 每 MW 年收入 | B14: US$bn/MW | C14: =輸入與假設!C$29 -> 0.0112 | D14: =輸入與假設!D$29 -> 0.0115 | E14: =輸入與假設!E$29 -> 0.0115 | F14: =輸入與假設!F$29 -> 0.011 | G14: =輸入與假設!G$29 -> 0.0105
A15: 容量上限（模型期最多能交付的收入） | B15: US$bn | C15: =C12*輸入與假設!C$29*輸入與假設!$C$22*輸入與假設!C$28*C7 -> 8.113 | D15: =D12*輸入與假設!D$29*輸入與假設!$C$22*輸入與假設!D$28*D7 -> 25.1275 | E15: =E12*輸入與假設!E$29*輸入與假設!$C$22*輸入與假設!E$28*E7 -> 35.883795 | F15: =F12*輸入與假設!F$29*輸入與假設!$C$22*輸入與假設!F$28*F7 -> 42.11691 | G15: =G12*輸入與假設!G$29*輸入與假設!$C$22*輸入與假設!G$28*G7 -> 47.06835 | I15: ＝平均在役 MW × 每 MW 年收入 × 利用率 × 期間係數。只看機房，不看合約
A16: （B）合約：排程 RPO
A17: 排程 RPO（模型期，依 10-Q 桶分攤） | B17: US$bn | C17: =(輸入與假設!$C$15+輸入與假設!$C$16)*(輸入與假設!C$25/輸入與假設!$C$18)*輸入與假設!$C$17 -> 13.19175 | D17: =(輸入與假設!$C$15+輸入與假設!$C$16)*(輸入與假設!D$25/輸入與假設!$C$18)*輸入與假設!$C$17 -> 26.3835 | E17: =(輸入與假設!$C$15+輸入與假設!$C$16)*(輸入與假設!E$25/輸入與假設!$C$18)*輸入與假設!$C$17 -> 25.74 | F17: =(輸入與假設!$C$15+輸入與假設!$C$16)*(輸入與假設!F$25/輸入與假設!$C$18)*輸入與假設!$C$17 -> 25.0965 | G17: =(輸入與假設!$C$15+輸入與假設!$C$16)*(輸入與假設!G$25/輸入與假設!$C$18)*輸入與假設!$C$17 -> 17.69625 | I17: ＝(6/30 RPO＋Q3 新增)×本期權重÷權重合計×五期認列比例。只看合約，不看機房
A18: （C）兩條線相減
A19: 產能瓶頸（模型期：排程 − 容量） | B19: US$bn | C19: =MAX(0,C17-C15) -> 5.07875 | D19: =MAX(0,D17-D15) -> 1.256 | E19: =MAX(0,E17-E15) -> 0 | F19: =MAX(0,F17-F15) -> 0 | G19: =MAX(0,G17-G15) -> 0 | I19: 合約有、機房沒有 → 本期收不到，且不遞延到下期（保守處理）
A20: 期初 RPO 轉換收入（模型期） | B20: US$bn | C20: =C17-C19 -> 8.113 | D20: =D17-D19 -> 25.1275 | E20: =E17-E19 -> 25.74 | F20: =F17-F19 -> 25.0965 | G20: =G17-G19 -> 17.69625 | I20: ＝排程 − 瓶頸。當瓶頸>0 時，此值恆等於容量上限
A21: 未被期初 RPO 占用的產能 | B21: US$bn | C21: =MAX(0,C15-C17) -> 0 | D21: =MAX(0,D15-D17) -> 0 | E21: =MAX(0,E15-E17) -> 10.143795 | F21: =MAX(0,F15-F17) -> 17.02041 | G21: =MAX(0,G15-G17) -> 29.3721 | I21: 容量 − 排程。機房有、期初合約沒占滿 → 要靠新簽約
A22: 新產能簽約率 | B22: % | C22: =輸入與假設!C$30 -> 1 | D22: =輸入與假設!D$30 -> 1 | E22: =輸入與假設!E$30 -> 0.9 | F22: =輸入與假設!F$30 -> 0.85 | G22: =輸入與假設!G$30 -> 0.8
A23: 新簽約收入 | B23: US$bn | C23: =C21*輸入與假設!C$30 -> 0 | D23: =D21*輸入與假設!D$30 -> 0 | E23: =E21*輸入與假設!E$30 -> 9.1294155 | F23: =F21*輸入與假設!F$30 -> 14.467348 | G23: =G21*輸入與假設!G$30 -> 23.49768 | I23: 尚未簽署的合約。FY28 起模型收入主要來自此列——8 GW 敘事的風險集中點
A24: 未售產能（浪費） | B24: US$bn | C24: =MAX(0,C15-C20-C23) -> 0 | D24: =MAX(0,D15-D20-D23) -> 0 | E24: =MAX(0,E15-E20-E23) -> 1.0143795 | F24: =MAX(0,F15-F20-F23) -> 2.5530615 | G24: =MAX(0,G15-G20-G23) -> 5.87442 | I24: 蓋好但賣不掉。Bernstein：簽約電力 74% 位於 Tier 3/4 市場
A25: 損益用算力收入（模型期＝RPO 轉換＋新簽約） | B25: US$bn | C25: =C20+C23 -> 8.113 | D25: =D20+D23 -> 25.1275 | E25: =E20+E23 -> 34.869416 | F25: =F20+F23 -> 39.563848 | G25: =G20+G23 -> 41.19393 | I25: 損益與評價頁的算力收入由此連結，確保現金與損益同一組數字
A26: 1H26 實際營收（10-Q，已實現） | B26: US$bn | C26: =輸入與假設!$C$132 -> 4.653 | D26: =0 -> 0 | E26: =0 -> 0 | F26: =0 -> 0 | G26: =0 -> 0 | I26: 2026-01-01 至 06-30 已認列營收。已實現，不受下半年產能約束，故不進入上方的瓶頸計算
A27: FY26 全年總營收（1H 實際＋模型期算力＋服務） | B27: US$bn | C27: =C26+C25+輸入與假設!C$33 -> 13.066 | D27: =D26+D25+輸入與假設!D$33 -> 26.1275 | E27: =E26+E25+輸入與假設!E$33 -> 36.669415 | F27: =F26+F25+輸入與假設!F$33 -> 42.363849 | G27: =G26+G25+輸入與假設!G$33 -> 44.99393 | I27: FY26 欄可直接對照公司全年指引 12.4–13.2；FY27 以後即為該年度總營收
A28: （D）收入 → 現金：三道折扣
A29: 客戶違約率 | B29: % | C29: =輸入與假設!C$31 -> 0.005 | D29: =輸入與假設!D$31 -> 0.01 | E29: =輸入與假設!E$31 -> 0.015 | F29: =輸入與假設!F$31 -> 0.02 | G29: =輸入與假設!G$31 -> 0.025
A30: 回收率 | B30: % | C30: =輸入與假設!C$32 -> 0.5 | D30: =輸入與假設!D$32 -> 0.5 | E30: =輸入與假設!E$32 -> 0.5 | F30: =輸入與假設!F$32 -> 0.5 | G30: =輸入與假設!G$32 -> 0.5
A31: 信用損失（期初 RPO 部分） | B31: US$bn | C31: =C20*輸入與假設!C$31*(1-輸入與假設!C$32) -> 0.0202825 | D31: =D20*輸入與假設!D$31*(1-輸入與假設!D$32) -> 0.1256375 | E31: =E20*輸入與假設!E$31*(1-輸入與假設!E$32) -> 0.19305 | F31: =F20*輸入與假設!F$31*(1-輸入與假設!F$32) -> 0.250965 | G31: =G20*輸入與假設!G$31*(1-輸入與假設!G$32) -> 0.22120313 | I31: ＝收入 × 違約率 × (1−回收率)
A32: 收現（期初 RPO 部分） | B32: US$bn | C32: =C20-C31 -> 8.0927175 | D32: =D20-D31 -> 25.001863 | E32: =E20-E31 -> 25.54695 | F32: =F20-F31 -> 24.845535 | G32: =G20-G31 -> 17.475047
A33: EBITDA 率（損益與資金共用） | B33: % | C33: =輸入與假設!C$39 -> 0.59 | D33: =輸入與假設!D$39 -> 0.605 | E33: =輸入與假設!E$39 -> 0.62 | F33: =輸入與假設!F$39 -> 0.635 | G33: =輸入與假設!G$39 -> 0.65 | I33: 起始→穩態線性爬升
A34: 模型期總營收（算力＋服務） | B34: US$bn | C34: =C25+輸入與假設!C$33 -> 8.413 | D34: =D25+輸入與假設!D$33 -> 26.1275 | E34: =E25+輸入與假設!E$33 -> 36.669415 | F34: =F25+輸入與假設!F$33 -> 42.363849 | G34: =G25+輸入與假設!G$33 -> 44.99393
A35: EBITDAR 率（EBITDA 率＋租金÷營收） | B35: % | C35: =輸入與假設!C$39+各期收支!C12/MAX(0.01,C34) -> 0.74927731 | D35: =輸入與假設!D$39+各期收支!D12/MAX(0.01,D34) -> 0.75576069 | E35: =輸入與假設!E$39+各期收支!E12/MAX(0.01,E34) -> 0.74886365 | F35: =輸入與假設!F$39+各期收支!F12/MAX(0.01,F34) -> 0.75592858 | G35: =輸入與假設!G$39+各期收支!G12/MAX(0.01,G34) -> 0.76536086 | I35: 租金前的 EBITDA 率。EBITDA 已扣租金，而資金模型把租金列在支出端，所以要加回，避免重複扣除
A36: RPO 現金（可支應資本用途） | B36: US$bn | C36: =C32*C35 -> 6.0636896 | D36: =D32*D35 -> 18.895425 | E36: =E32*E35 -> 19.131182 | F36: =F32*F35 -> 18.78145 | G36: =G32*G35 -> 13.374717 | I36: ×EBITDAR 率。租金與利息在支出頁單獨列示
A37: 新簽約現金 | B37: US$bn | C37: =C23*(1-輸入與假設!C$31*(1-輸入與假設!C$32))*C35 -> 0 | D37: =D23*(1-輸入與假設!D$31*(1-輸入與假設!D$32))*D35 -> 0 | E37: =E23*(1-輸入與假設!E$31*(1-輸入與假設!E$32))*E35 -> 6.7854123 | F37: =F23*(1-輸入與假設!F$31*(1-輸入與假設!F$32))*F35 -> 10.826919 | G37: =G23*(1-輸入與假設!G$31*(1-輸入與假設!G$32))*G35 -> 17.759402 | I37: 同樣扣信用損失、乘 EBITDAR 率
A39: 讀法：FY26（2H）與 FY27 瓶頸>0，合約多於機房；FY28 起反轉，收入愈來愈靠『新簽約收入』這一列。
A40: 把『新產能簽約率』調到 0，就能看到只靠期初 RPO 的資金缺口有多大——這是最重要的一個壓力測試。

Sheet 運營_站點
A1: 站點租賃 — 房東揭露 vs 10-Q 總額（檢驗租金路徑用）
A2: 10-Q 不揭露逐站租金；下表為房東公告的合約值（Interested-party），用來檢驗『每 MW 年租金』與模型租金路徑是否一致
A4: 站點 | B4: 房東 | C4: 契約 MW | D4: 已起租 MW | E4: 合約總值 $bn | F4: 年期 | G4: 年租金 $bn | H4: 每 MW 年租金 $m | I4: 起租時程 | J4: 10-Q 對應 | K4: 來源
A5: Helios（德州 Dickens） | B5: Galaxy (GLXY) | C5: 526 | D5: 133 | E5: 15 | F5: 15 | G5: =E5/F5 -> 1 | H5: =G5/C5*1000 -> 1.9011407 | I5: Ph I 133 MW 2026Q2 起租；Ph II 260 MW 2027H1 起；Ph III 133 MW | J5: 未交付 393 MW＝10-Q「單站上限 14.7／16 年」 | K5: Galaxy 2026-07-06：526 MW、年均租金 >$1bn、15 年＋2×5 年延長 [Interested-party]
A6: Polaris Forge 1（北達科他 Ellendale） | B6: Applied Digital (APLD) | C6: 400 | D6: 250 | E6: 11 | F6: 15 | G6: =E6/F6 -> 0.73333333 | H6: =G6/C6*1000 -> 1.8333333 | I6: 100 MW 2025Q4；150 MW 2026 年中；150 MW 2027 | J6: 大致落在未起租 35.5 內 | K6: APLD 2025-08-29／FQ2 法說：400 MW、約 $11bn、約 15 年 [Interested-party]
A7: Core Scientific 六站（Denton 等） | B7: Core Scientific (CORZ) | C7: 590 | D7: 250 | E7: 10.2 | F7: 12 | G7: =E7/F7 -> 0.85 | H7: =G7/C7*1000 -> 1.440678 | I7: 2026 年約 250 MW；2027 年初全數 590 MW | J7: 部分在帳、部分未起租；「按造價計租」355 MW 可能含部分 | K7: CORZ 2025-02-26：約 590 MW、$10.2bn、12 年；年均約 $850m [Interested-party]
A8: Kenilworth（新澤西 JV） | B8: JV（CRWV 持股 35%） | C8: 未揭露 | D8: 0 | E8: 未揭露 | F8: 15 | I8: 施工中；完工後起租 | J8: 10-Q：租金＝建造成本的一定比例，推定屬「按造價計租」355 MW | K8: 10-Q Note 3：15 年租約、租金依建造成本計；MW 與金額未揭露 [Verified]
A9: 具名站點合計 | C9: =SUM(C5:C8) -> 1516 | D9: =SUM(D5:D8) -> 633 | E9: =SUM(E5:E8) -> 36.2 | G9: =SUM(G5:G8) -> 2.5833333 | H9: =G9/C9*1000 -> 1.7040457 | K9: 加權每 MW 年租金＝具名站點的市場基準
A11: 對帳：具名站點 vs 10-Q 租賃承諾總額
A12: 10-Q 在帳租賃（未折現，已起租） | E12: 29.37 | K12: 營業 29.135＋融資 0.235 [Verified]
A13: 10-Q 未起租租賃（未折現） | E13: 35.5 | K13: 2026–2029 起租、7–16 年 [Verified]
A14: 10-Q 單站按造價計租上限 | E14: 14.7 | K14: 即 Helios 未交付 393 MW [Verified]
A15: 10-Q 已揭露租賃承諾合計 | E15: =SUM(E12:E14) -> 79.57 | K15: 另有 355 MW 按造價計租，金額未定，未含
A16: 減：具名站點合約總值 | E16: =-E9 -> -36.2
A17: ＝ 未具名站點（殘差） | E17: =E15+E16 -> 43.37 | K17: 43 座以上資料中心中未具名者（Equinix、Switch 等託管，以及其他房東）。殘差大是必然——公司不揭露逐站
A18: 殘差占 10-Q 總額 | E18: =E17/E15 -> 0.54505467
A20: 檢驗：模型租金路徑 ÷ 在役 MW vs 市場基準
A21: 項目 | B21: 單位 | C21: FY26 | D21: FY27 | E21: FY28 | F21: FY29 | G21: FY30
A22: 模型租金（在帳＋表外） | B22: US$bn | C22: =各期收支!C12 -> 1.34 | D22: =各期收支!D12 -> 3.939 | E22: =各期收支!E12 -> 4.7253548 | F22: =各期收支!F12 -> 5.123 | G22: =各期收支!G12 -> 5.1905385
A23: 平均在役 MW（Accepted） | B23: MW | C23: =(輸入與假設!C$65+輸入與假設!C$26)/2 -> 1350 | D23: =(輸入與假設!D$65+輸入與假設!D$26)/2 -> 2475 | E23: =(輸入與假設!E$65+輸入與假設!E$26)/2 -> 3550 | F23: =(輸入與假設!F$65+輸入與假設!F$26)/2 -> 4400 | G23: =(輸入與假設!G$65+輸入與假設!G$26)/2 -> 5200
A24: 模型期長度（年） | B24: 年 | C24: =輸入與假設!C$24 -> 0.5 | D24: =輸入與假設!D$24 -> 1 | E24: =輸入與假設!E$24 -> 1 | F24: =輸入與假設!F$24 -> 1 | G24: =輸入與假設!G$24 -> 1
A25: 模型每 MW 年租金 | B25: US$m/MW | C25: =C22/C24/C23*1000 -> 1.9851852 | D25: =D22/D24/D23*1000 -> 1.5915152 | E25: =E22/E24/E23*1000 -> 1.3310859 | F25: =F22/F24/F23*1000 -> 1.1643182 | G25: =G22/G24/G23*1000 -> 0.99818047 | K25: FY26 欄只含下半年租金、MW 取全年平均，略有低估
A26: 第三方租賃占比 | C26: 0.85 | K26: 其餘為自建／JV（Kenilworth、Lancaster），成本走 CapEx 或 JV 出資 [Assumed]
A27: 基準租金（MW×市場基準×占比） | B27: US$bn | C27: =C23*運營_站點!$H$9/1000*$C$26*C24 -> 0.97769624 | D27: =D23*運營_站點!$H$9/1000*$C$26*D24 -> 3.5848862 | E27: =E23*運營_站點!$H$9/1000*$C$26*E24 -> 5.141958 | F27: =F23*運營_站點!$H$9/1000*$C$26*F24 -> 6.373131 | G27: =G23*運營_站點!$H$9/1000*$C$26*G24 -> 7.5318821 | K27: 若 8 GW 多數比照 Helios／APLD／CORZ 的租金水準
A28: 差額（基準 − 模型） | B28: US$bn | C28: =C27-C22 -> -0.36230376 | D28: =D27-D22 -> -0.35411379 | E28: =E27-E22 -> 0.41660316 | F28: =F27-F22 -> 1.250131 | G28: =G27-G22 -> 2.3413437 | K28: 正值＝模型租金可能低估的金額
A29: 五期差額合計 | C29: =SUM(C28:G28) -> 3.2916603

Sheet 資產負債_既有債務
A1: 債務明細 — 10-Q Note 10（2026-06-30）逐筆＋存量利息推導
A2: 有效利率為 10-Q 揭露值（含折價攤銷，四捨五入至整數 %）。本頁算出的存量利息連回『輸入』頁，再進入支出與資金頁
A4: 工具 | B4: 類別 | C4: 到期 | D4: 有效利率 | E4: 6/30 本金 | F4: 年化利息 | I4: 備註
A5: DDTL 1.0 | B5: 追索 | C5: 2028-03 | D5: 0.15 | E5: 1.3 | F5: =D5*E5 -> 0.195 | I5: 資產層、隨客戶付款攤還 [Verified]
A6: DDTL 2.0 | B6: 追索 | C6: 2030-08 | D6: 0.11 | E6: 3.19 | F6: =D6*E6 -> 0.3509 | I6: [Verified]
A7: DDTL 2.1 | B7: 追索 | C7: 2031-03 | D7: 0.09 | E7: 3 | F7: =D7*E7 -> 0.27 | I7: [Verified]
A8: DDTL 3.0 | B8: 追索 | C8: 2030-08 | D8: 0.09 | E8: 2.215 | F8: =D8*E8 -> 0.19935 | I8: [Verified]
A9: DDTL 5.0 | B9: 追索 | C9: 2031-11 | D9: 0.09 | E9: 1.101 | F9: =D9*E9 -> 0.09909 | I9: SOFR+4.50%；額度 3.1 [Verified]
A10: 2030 Senior Notes | B10: 追索 | C10: 2030-06 | D10: 0.1 | E10: 2 | F10: =D10*E10 -> 0.2 | I10: 到期一次還本 [Verified]
A11: 2031 9.00% Senior Notes | B11: 追索 | C11: 2031-02 | D11: 0.1 | E11: 1.75 | F11: =D11*E11 -> 0.175 | I11: [Verified]
A12: 2031 9.75% Senior Notes | B12: 追索 | C12: 2031-10 | D12: 0.1 | E12: 2.75 | F12: =D12*E12 -> 0.275 | I12: 2026-04 發行 [Verified]
A13: 2032 9.625% Senior Notes | B13: 追索 | C13: 2032-07 | D13: 0.1 | E13: 1.25 | F13: =D13*E13 -> 0.125 | I13: 2026-06 發行 [Verified]
A14: 2032 EUR Senior Notes（€2.0bn） | B14: 追索 | C14: 2032-07 | D14: 0.09 | E14: 2.279 | F14: =D14*E14 -> 0.20511 | I14: 票面 8.50%；已做換匯換利避險 [Verified]
A15: 2031 可轉債 | B15: 追索 | C15: 2031-12 | D15: 0.02 | E15: 2.588 | F15: =D15*E15 -> 0.05176 | I15: [Verified]
A16: 2032 可轉債 | B16: 追索 | C16: 2032-10 | D16: 0.02 | E16: 4 | F16: =D16*E16 -> 0.08 | I16: 票面 1.75%；2026-04 發行 [Verified]
... A20: OEM 融資（非追索） | B20: 非追索 | C20: 2026-08～2028-08 | D20: 0.09 | E20: 0.882 | F20: =D20*E20 -> 0.07938 | I20: [Verified]
A21: 合計（6/30） | E21: =SUM(E5:E20) -> 35.551 | F21: =SUM(F5:F20) -> 2.99106 | I21: 應等於 10-Q 本金合計 35.551
A22: 加權有效利率 | D22: =F21/E21 -> 0.084134342 | I22: 公司 9/17 簡報：Q2 加權 8.3%、含新可轉債 pro forma 7.8%（該口徑用票面，本頁用有效利率）
A24: 9/17 期後：2033 可轉債 | D24: 0.02875 | E24: 3.7 | F24: =D24*E24 -> 0.106375 | I24: 轉換價 $97.85；2033 到期，不在五期還本表內 [Verified]
A26: 存量利息推導（本金依 10-Q 到期表遞減）
A27: 項目 | B27: 單位 | C27: FY26 | D27: FY27 | E27: FY28 | F27: FY29 | G27: FY30 | I27: 公式／來源說明
A28: 期初本金 | B28: US$bn | C28: =E21 -> 35.551 | D28: =C30 -> 31.138 | E28: =D30 -> 24.954 | F28: =E30 -> 20.538 | G28: =F30 -> 18.117 | I28: FY26 期初為 6/30 本金（模型期起點）
A29: 排程還本 | B29: US$bn | C29: =輸入與假設!C$93 -> 4.413 | D29: =輸入與假設!D$93 -> 6.184 | E29: =輸入與假設!E$93 -> 4.416 | F29: =輸入與假設!F$93 -> 2.421 | G29: =輸入與假設!G$93 -> 3.221 | I29: 10-Q 到期表
A30: 期末本金 | B30: US$bn | C30: =C28-C29 -> 31.138 | D30: =D28-D29 -> 24.954 | E30: =E28-E29 -> 20.538 | F30: =F28-F29 -> 18.117 | G30: =G28-G29 -> 14.896
A31: 平均本金 | B31: US$bn | C31: =(C28+C30)/2 -> 33.3445 | D31: =(D28+D30)/2 -> 28.046 | E31: =(E28+E30)/2 -> 22.746 | F31: =(F28+F30)/2 -> 19.3275 | G31: =(G28+G30)/2 -> 16.5065
A32: 存量債務利息 | B32: US$bn | C32: =C31*資產負債_既有債務!$D$22*輸入與假設!C$24 -> 1.4027088 | D32: =D31*資產負債_既有債務!$D$22*輸入與假設!D$24 -> 2.3596318 | E32: =E31*資產負債_既有債務!$D$22*輸入與假設!E$24 -> 1.9137197 | F32: =F31*資產負債_既有債務!$D$22*輸入與假設!F$24 -> 1.6261065 | G32: =G31*資產負債_既有債務!$D$22*輸入與假設!G$24 -> 1.3887635 | I32: ＝平均本金×加權有效利率×期間長度。限制：假設利率組合不變（實際上 15% 的 DDTL 1.0 先到期，後期利率會略降）
A33: 9/17 可轉債利息 | B33: US$bn | C33: =資產負債_既有債務!$F$24*輸入與假設!C$24 -> 0.0531875 | D33: =資產負債_既有債務!$F$24*輸入與假設!D$24 -> 0.106375 | E33: =資產負債_既有債務!$F$24*輸入與假設!E$24 -> 0.106375 | F33: =資產負債_既有債務!$F$24*輸入與假設!F$24 -> 0.106375 | G33: =資產負債_既有債務!$F$24*輸入與假設!G$24 -> 0.106375
A34: FY26 新增借款利息校準 | B34: US$bn | C34: =0.35 -> 0.35 | D34: =0 -> 0 | E34: =0 -> 0 | F34: =0 -> 0 | G34: =0 -> 0 | I34: Q3 指引 0.86–0.94／季含 Q3 新動用的 DDTL；存量推算約 0.73／季，差額×2 季≈0.35。FY27 起新增借款改由瀑布新債利息承接 [Derived]
A35: 存量利息合計（連回輸入頁） | B35: US$bn | C35: =C32+C33+C34 -> 1.8058963 | D35: =D32+D33+D34 -> 2.4660068 | E35: =E32+E33+E34 -> 2.0200947 | F35: =F32+F33+F34 -> 1.7324815 | G35: =G32+G33+G34 -> 1.4951385 | I35: v1.4 手動值為 1.8／2.7／2.3／2.0／1.8

Sheet 資產負債_新債與新股
A1: 新債與新股（類資產負債表：現金、債務、股本、槓桿）
A2: 全部為連結公式。FY26 欄的現金自 2026-06-30 起算（模型期），與 HTML『資產與負債 → 新債與新股』同口徑
A4: 項目 | B4: 單位 | C4: FY26 | D4: FY27 | E4: FY28 | F4: FY29 | G4: FY30 | I4: 公式／來源說明
A5: 現金
A6: 期初現金 | B6: US$bn | C6: =輸入與假設!$C$77 -> 5.5 | D6: =各期收支!C41 -> 2 | E6: =各期收支!D41 -> 2 | F6: =各期收支!E41 -> 2 | G6: =各期收支!F41 -> 2 | I6: FY26＝6/30 現金（模型期起點）
A7: 營運收支淨額（含 9/17 可轉債／ATM，不含瀑布） | B7: US$bn | C7: =各期收支!C71-輸入與假設!$C$77 -> -15.489544 | D7: =各期收支!D71-各期收支!C71 -> -28.606021 | E7: =各期收支!E71-各期收支!D71 -> -11.2541 | F7: =各期收支!F71-各期收支!E71 -> -5.9035121 | G7: =各期收支!G71-各期收支!F71 -> -5.9365868 | I7: ＝融資前累積現金的當期變動；負值即當期外部資金需求
A8: ＋ 瀑布：新債（額度＋資產層） | B8: US$bn | C8: =各期收支!C58 -> 12.554496 | D8: =各期收支!D58 -> 32.676842 | E8: =各期收支!E58 -> 16.840572 | F8: =各期收支!F58 -> 3.1393189 | G8: =各期收支!G58 -> 7.1787275
A9: ＋ 瀑布：高息債 | B9: US$bn | C9: =各期收支!C62 -> 0 | D9: =各期收支!D62 -> 0 | E9: =各期收支!E62 -> 0 | F9: =各期收支!F62 -> 0 | G9: =各期收支!G62 -> 0
A10: ＋ 瀑布：股權募資 | B10: US$bn | C10: =各期收支!C61 -> 0 | D10: =各期收支!D61 -> 0 | E10: =各期收支!E61 -> 0 | F10: =各期收支!F61 -> 8.6332038 | G10: =各期收支!G61 -> 5.2729553
A11: − 新融資利息（新債＋高息債） | B11: US$bn | C11: =-各期收支!C63 -> -0.56495231 | D11: =-各期收支!D63 -> -4.0708204 | E11: =-各期收支!E63 -> -5.5864719 | F11: =-各期收支!F63 -> -5.8690106 | G11: =-各期收支!G63 -> -6.515096
A12: 期末現金 | B12: US$bn | C12: =SUM(C6:C11) -> 2 | D12: =SUM(D6:D11) -> 2 | E12: =SUM(E6:E11) -> 2 | F12: =SUM(F6:F11) -> 2 | G12: =SUM(G6:G11) -> 2 | I12: 應等於『各期收支』期末累積現金（見下列驗算）
A13: 驗算：與各期收支期末現金差異 | B13: US$bn | C13: =C12-各期收支!C41 -> 0 | D13: =D12-各期收支!D41 -> 0 | E13: =E12-各期收支!E41 -> 0 | F13: =F12-各期收支!F41 -> 0 | G13: =G12-各期收支!G41 -> 0 | I13: 應為 0
A14: 債務
A15: 既有債務期初（10-Q 本金） | B15: US$bn | C15: =35.551 -> 35.551 | D15: =C17 -> 31.138 | E15: =D17 -> 24.954 | F15: =E17 -> 20.538 | G15: =F17 -> 18.117
A16: − 排程還本（模型期） | B16: US$bn | C16: =-IF(輸入與假設!$C$82=1,輸入與假設!C$93,0) -> -4.413 | D16: =-IF(輸入與假設!$C$82=1,輸入與假設!D$93,0) -> -6.184 | E16: =-IF(輸入與假設!$C$82=1,輸入與假設!E$93,0) -> -4.416 | F16: =-IF(輸入與假設!$C$82=1,輸入與假設!F$93,0) -> -2.421 | G16: =-IF(輸入與假設!$C$82=1,輸入與假設!G$93,0) -> -3.221
A17: 既有債務期末 | B17: US$bn | C17: =各期收支!C54-3.7 -> 31.138 | D17: =各期收支!D54-3.7 -> 24.954 | E17: =各期收支!E54-3.7 -> 20.538 | F17: =各期收支!F54-3.7 -> 18.117 | G17: =各期收支!G54-3.7 -> 14.896 | I17: ＝依到期表遞減（關閉攤還時維持 35.551）
A18: ＋ 9/17 可轉債（2033 到期） | B18: US$bn | C18: =3.7 -> 3.7 | D18: =3.7 -> 3.7 | E18: =3.7 -> 3.7 | F18: =3.7 -> 3.7 | G18: =3.7 -> 3.7
A19: ＋ 瀑布新債餘額 | B19: US$bn | C19: =各期收支!C67 -> 12.554496 | D19: =各期收支!D67 -> 45.231337 | E19: =各期收支!E67 -> 62.07191 | F19: =各期收支!F67 -> 65.211229 | G19: =各期收支!G67 -> 72.389956
A20: ＋ 高息債餘額 | B20: US$bn | C20: =各期收支!C69 -> 0 | D20: =各期收支!D69 -> 0 | E20: =各期收支!E69 -> 0 | F20: =各期收支!F69 -> 0 | G20: =各期收支!G69 -> 0
A21: 總債務 | B21: US$bn | C21: =SUM(C17:C20) -> 47.392496 | D21: =SUM(D17:D20) -> 73.885337 | E21: =SUM(E17:E20) -> 86.30991 | F21: =SUM(F17:F20) -> 87.028228 | G21: =SUM(G17:G20) -> 90.985956 | I21: 應等於『各期收支』期末總債務
A22: 淨負債（總債務 − 期末現金） | B22: US$bn | C22: =C21-C12 -> 45.392496 | D22: =D21-D12 -> 71.885337 | E22: =E21-E12 -> 84.30991 | F22: =F21-F12 -> 85.028228 | G22: =G21-G12 -> 88.985956
A23: 股本
A24: 基礎股數（含 ATM 上限、SBC 稀釋） | B24: bn | C24: =損益!C20 -> 0.587 | D24: =損益!D20 -> 0.59287 | E24: =損益!E20 -> 0.5987987 | F24: =損益!F20 -> 0.60478669 | G24: =損益!G20 -> 0.61083455
A25: ＋ 本期新股 | B25: bn | C25: =各期收支!C65 -> 0 | D25: =各期收支!D65 -> 0 | E25: =各期收支!E65 -> 0 | F25: =各期收支!F65 -> 0.11228431 | G25: =各期收支!G65 -> 0.068580584
A26: 總股數（期末） | B26: bn | C26: =損益!C21 -> 0.587 | D26: =損益!D21 -> 0.59287 | E26: =損益!E21 -> 0.5987987 | F26: =損益!F21 -> 0.717071 | G26: =損益!G21 -> 0.79169945 | I26: ＝基礎股數＋累計新股
A27: 槓桿
A28: 期末 backlog | B28: US$bn | C28: =各期收支!C53 -> 115.50825 | D28: =各期收支!D53 -> 89.12475 | E28: =各期收支!E53 -> 99.902412 | F28: =各期收支!F53 -> 87.028228 | G28: =各期收支!G53 -> 90.985956
A29: 債務上限（債務／backlog × 期末 backlog） | B29: US$bn | C29: =各期收支!C55 -> 115.50825 | D29: =各期收支!D55 -> 89.12475 | E29: =各期收支!E55 -> 99.902412 | F29: =各期收支!F55 -> 87.028228 | G29: =各期收支!G55 -> 90.985956
A30: 總債務 ÷ 期末 backlog | B30: x | C30: =C21/MAX(0.01,C28) -> 0.41029533 | D30: =D21/MAX(0.01,D28) -> 0.82901032 | E30: =E21/MAX(0.01,E28) -> 0.8639422 | F30: =F21/MAX(0.01,F28) -> 1 | G30: =G21/MAX(0.01,G28) -> 1 | I30: 高息債不受 backlog 上限約束
A31: 總債務 ÷ EBITDA（年化） | B31: x | C31: =C21/MAX(0.01,損益!C19/輸入與假設!C$24) -> 4.773937 | D31: =D21/MAX(0.01,損益!D19/輸入與假設!D$24) -> 4.6741757 | E31: =E21/MAX(0.01,損益!E19/輸入與假設!E$24) -> 3.796339 | F31: =F21/MAX(0.01,損益!F19/輸入與假設!F$24) -> 3.2351246 | G31: =G21/MAX(0.01,損益!G19/輸入與假設!G$24) -> 3.1110506 | I31: FY26 模型期 EBITDA 以半年×2 年化

Sheet 資產負債_租賃承諾
A1: 租賃與承諾 — 10-Q（2026-06-30）原始揭露
A2: 本頁為硬編碼的申報數字（藍字），支出與資金頁的租金與還本列由此而來
A4: 在帳租賃到期表（未折現）
A5: 項目 | B5: 單位 | C5: 2026 下半 | D5: 2027 | E5: 2028 | F5: 2029 | G5: 2030 | H5: 其後
A6: 營業租賃付款 | B6: US$bn | C6: 1.028 | D6: 2.116 | E6: 2.306 | F6: 2.373 | G6: 2.289 | H6: 19.023
A7: 融資租賃付款 | B7: US$bn | C7: 0.012 | D7: 0.223 | E7: 0 | F7: 0 | G7: 0 | H7: 0
A8: 合計（＝支出頁「在帳現金租金」） | C8: =SUM(C6:C7) -> 1.04 | D8: =SUM(D6:D7) -> 2.339 | E8: =SUM(E6:E7) -> 2.306 | F8: =SUM(F6:F7) -> 2.373 | G8: =SUM(G6:G7) -> 2.289 | H8: =SUM(H6:H7) -> 19.023 | I8: 營業租賃負債現值 16.319、融資租賃 0.221；加權剩餘租期 12 年、折現率 10% [Verified]
A10: 債務本金到期表
A11: 項目 | B11: 單位 | C11: 2026 下半 | D11: 2027 | E11: 2028 | F11: 2029 | G11: 2030 | H11: 其後
A12: 本金（＝支出頁「排程還本」） | B12: US$bn | C12: 4.413 | D12: 6.184 | E12: 4.416 | F12: 2.421 | G12: 3.221 | H12: 14.896 | I12: 本金合計 35.551（DDTL 13.6、票據 16.6、OEM 5.1 等）[Verified]
A13: 合計 | C13: =SUM(C12:H12) -> 35.551
A15: 表外與契約性承諾（未入表）
A16: 項目 | B16: 單位 | C16: 金額 | D16: 時程 | E16: 入表？ | F16: 模型位置
A17: 未起租租賃（未折現） | B17: US$bn | C17: 35.5 | D17: 2026–2029 起租，7–16 年 | E17: 否 | F17: 表外現金租金
A18: 單站按造價計租，上限 | B18: US$bn | C18: 14.7 | D18: 393 MW 未交付，16 年 | E18: 否 | F18: 表外現金租金
A19: 按造價計租，355 MW | B19: US$bn | C19: 未定 | D19: 2026–2028 分期，金額未定 | E19: 否 | F19: 表外現金租金
A20: 承租人自備設備承諾 | B20: US$bn | C20: 1.2 | D20: 0.5–1.2，分期至 2028 | E20: 否 | F20: 併入毛 CapEx
A21: JV 出資承諾 | B21: US$bn | C21: 1.7 | D21: 已付 0.55 | E21: 否 | F21: JV／策略投資出資
A22: VIE 最大損失暴露 | B22: US$bn | C22: 0.108 | D22: — | E22: 否 | F22: 不另列
A23: 可用信用額度（RCF＋DDTL 未動用） | B23: US$bn | C23: 10.014 | D23: DDTL 4.0 可動用至 2027-06 | E23: 否（來源） | F23: 選用開關
A24: 已揭露金額之承諾合計（未起租＋單站上限） | C24: =C17+C18 -> 50.2
A25: 模型表外租金五期合計 | C25: =SUM(各期收支!C11:G11) -> 9.9708933
A26: 模型表外租金尾端（FY30×12 年） | C26: =各期收支!G11*12 -> 34.818462
A27: 模型路徑合計 ÷ 已承諾（≥0.8 為合理） | C27: =(C25+C26)/C24 -> 0.89221822 | I27: 8 GW 路徑所需新租約多數尚未簽署，路徑高於已承諾屬假設而非錯誤

Sheet 損益
A1: 損益（類損益表）— 與資金模型同一組收入
A2: 算力收入、Cash CapEx、利息皆由前面分頁連結而來；改資金假設，此頁會跟著動
A4: 項目 | B4: 單位 | C4: FY26 | D4: FY27 | E4: FY28 | F4: FY29 | G4: FY30 | I4: 公式／來源說明
A5: 損益表
A6: 算力收入 | B6: US$bn | C6: =運營_產能與收入!C25 -> 8.113 | D6: =運營_產能與收入!D25 -> 25.1275 | E6: =運營_產能與收入!E25 -> 34.869416 | F6: =運營_產能與收入!F25 -> 39.563848 | G6: =運營_產能與收入!G25 -> 41.19393 | I6: ＝RPO 轉換＋新簽約
A7: 非算力服務 | B7: US$bn | C7: =輸入與假設!C$33 -> 0.3 | D7: =輸入與假設!D$33 -> 1 | E7: =輸入與假設!E$33 -> 1.8 | F7: =輸入與假設!F$33 -> 2.8 | G7: =輸入與假設!G$33 -> 3.8
A8: 總營收 | B8: US$bn | C8: =C6+C7 -> 8.413 | D8: =D6+D7 -> 26.1275 | E8: =E6+E7 -> 36.669415 | F8: =F6+F7 -> 42.363849 | G8: =G6+G7 -> 44.99393
A9: EBITDA 率 | B9: % | C9: =輸入與假設!C$39 -> 0.59 | D9: =輸入與假設!D$39 -> 0.605 | E9: =輸入與假設!E$39 -> 0.62 | F9: =輸入與假設!F$39 -> 0.635 | G9: =輸入與假設!G$39 -> 0.65
A10: 營業利益（EBIT） | B10: US$bn | C10: =C8*輸入與假設!C$39-輸入與假設!C$74 -> 0.20083667 | D10: =D8*輸入與假設!D$39-輸入與假設!D$74 -> 1.3505542 | E10: =E8*輸入與假設!E$39-輸入與假設!E$74 -> 2.6330376 | F10: =F8*輸入與假設!F$39-輸入與假設!F$74 -> 2.0815438 | G10: =G8*輸入與假設!G$39-輸入與假設!G$74 -> 0.19072117 | I10: ＝營收×EBITDA 率 − 車隊 D&A
A11: 利息（含瀑布新債） | B11: US$bn | C11: =各期收支!C17 -> 2.3708486 | D11: =各期收支!D17 -> 6.5368271 | E11: =各期收支!E17 -> 7.6065666 | F11: =各期收支!F17 -> 7.6014921 | G11: =各期收支!G17 -> 8.0102346
A12: 稅前損益 | B12: US$bn | C12: =C10-C11 -> -2.1700119 | D12: =D10-D11 -> -5.186273 | E12: =E10-E11 -> -4.973529 | F12: =F10-F11 -> -5.5199483 | G12: =G10-G11 -> -7.8195134
A13: NOL 期初餘額 | B13: US$bn | C13: =輸入與假設!$C$105 -> 4 | D13: =C15 -> 6.1700119 | E13: =D15 -> 11.356285 | F13: =E15 -> 16.329814 | G13: =F15 -> 21.849762 | I13: 6/30 累積虧損約 4.0
A14: 本期動用 NOL | B14: US$bn | C14: =MIN(C13,MAX(0,C12)*0.8) -> 0 | D14: =MIN(D13,MAX(0,D12)*0.8) -> 0 | E14: =MIN(E13,MAX(0,E12)*0.8) -> 0 | F14: =MIN(F13,MAX(0,F12)*0.8) -> 0 | G14: =MIN(G13,MAX(0,G12)*0.8) -> 0 | I14: 美國規定：抵扣上限為應稅所得 80%
A15: NOL 期末餘額 | B15: US$bn | C15: =C13-C14+MAX(0,-C12) -> 6.1700119 | D15: =D13-D14+MAX(0,-D12) -> 11.356285 | E15: =E13-E14+MAX(0,-E12) -> 16.329814 | F15: =F13-F14+MAX(0,-F12) -> 21.849762 | G15: =G13-G14+MAX(0,-G12) -> 29.669276
A16: 所得稅 | B16: US$bn | C16: =MAX(0,C12-C14)*輸入與假設!$C$104 -> 0 | D16: =MAX(0,D12-D14)*輸入與假設!$C$104 -> 0 | E16: =MAX(0,E12-E14)*輸入與假設!$C$104 -> 0 | F16: =MAX(0,F12-F14)*輸入與假設!$C$104 -> 0 | G16: =MAX(0,G12-G14)*輸入與假設!$C$104 -> 0 | I16: 虧損年不認列稅盾（與公司評價備抵一致）
A17: 淨利 | B17: US$bn | C17: =C12-C16 -> -2.1700119 | D17: =D12-D16 -> -5.186273 | E17: =E12-E16 -> -4.973529 | F17: =F12-F16 -> -5.5199483 | G17: =G12-G16 -> -7.8195134
A18: D&A | B18: US$bn | C18: =輸入與假設!C$74 -> 4.7628333 | D18: =輸入與假設!D$74 -> 14.456583 | E18: =輸入與假設!E$74 -> 20.102 | F18: =輸入與假設!F$74 -> 24.8195 | G18: =輸入與假設!G$74 -> 29.055333 | I18: 車隊折舊，見輸入頁
A19: EBITDA | B19: US$bn | C19: =C10+C18 -> 4.96367 | D19: =D10+D18 -> 15.807137 | E19: =E10+E18 -> 22.735038 | F19: =F10+F18 -> 26.901044 | G19: =G10+G18 -> 29.246054
A20: 基礎股數（每年 +SBC 稀釋） | B20: bn | C20: =輸入與假設!$C$99 -> 0.587 | D20: =C20*(1+輸入與假設!$C$112) -> 0.59287 | E20: =D20*(1+輸入與假設!$C$112) -> 0.5987987 | F20: =E20*(1+輸入與假設!$C$112) -> 0.60478669 | G20: =F20*(1+輸入與假設!$C$112) -> 0.61083455 | I20: FY26＝含 ATM 上限 0.587；之後每年 ×(1＋股數年增)
A21: 股數（含瀑布新股） | B21: bn | C21: =C20+各期收支!C66 -> 0.587 | D21: =D20+各期收支!D66 -> 0.59287 | E21: =E20+各期收支!E66 -> 0.5987987 | F21: =F20+各期收支!F66 -> 0.717071 | G21: =G20+各期收支!G66 -> 0.79169945 | I21: ＝基礎股數＋累計瀑布新股
A22: 每股盈餘（EPS，模型期） | B22: US$ | C22: =C17/C21 -> -3.6967835 | D22: =D17/D21 -> -8.7477406 | E22: =E17/E21 -> -8.3058447 | F22: =F17/F21 -> -7.6979104 | G22: =G17/G21 -> -9.8768711 | I22: FY26 欄只含下半年；全年口徑見下方
A24: 損益表（全年口徑；FY26＝1H 實際＋下半年模型；與 HTML 損益簡表一致）
A25: 1H26 實際營收（已實現） | B25: US$bn | C25: =輸入與假設!$C$132 -> 4.653 | D25: =0 -> 0 | E25: =0 -> 0 | F25: =0 -> 0 | G25: =0 -> 0
A26: 全年總營收 | B26: US$bn | C26: =C25+C8 -> 13.066 | D26: =D25+D8 -> 26.1275 | E26: =E25+E8 -> 36.669415 | F26: =F25+F8 -> 42.363849 | G26: =G25+G8 -> 44.99393 | I26: FY26 可對照指引 12.4–13.2
A27: 營收 YoY | B27: % | C27: =C26/5.131-1 -> 1.5464822 | D27: =D26/C26-1 -> 0.99965559 | E27: =E26/D26-1 -> 0.40347969 | F27: =F26/E26-1 -> 0.15529108 | G27: =G26/F26-1 -> 0.062083158 | I27: FY25 實際 5.131
A28: 全年 GAAP 營業利益 | B28: US$bn | C28: =輸入與假設!$C$133+C10 -> 0.0078366667 | D28: =D10 -> 1.3505542 | E28: =E10 -> 2.6330376 | F28: =F10 -> 2.0815438 | G28: =G10 -> 0.19072117
A29: 營利率 | B29: % | C29: =C28/C26 -> 0.0005997755 | D29: =D28/D26 -> 0.051690907 | E29: =E28/E26 -> 0.071804734 | F29: =F28/F26 -> 0.049134908 | G29: =G28/G26 -> 0.0042388199
A30: 全年 D&A | B30: US$bn | C30: =輸入與假設!$C$136+C18 -> 7.3028333 | D30: =D18 -> 14.456583 | E30: =E18 -> 20.102 | F30: =F18 -> 24.8195 | G30: =G18 -> 29.055333 | I30: 1H 實際 2.540
A31: 全年 EBITDA | B31: US$bn | C31: =C28+C30 -> 7.31067 | D31: =D28+D30 -> 15.807137 | E31: =E28+E30 -> 22.735038 | F31: =F28+F30 -> 26.901044 | G31: =G28+G30 -> 29.246054
A32: 全年利息（含瀑布新債） | B32: US$bn | C32: =輸入與假設!$C$130+C11 -> 3.5468486 | D32: =D11 -> 6.5368271 | E32: =E11 -> 7.6065666 | F32: =F11 -> 7.6014921 | G32: =G11 -> 8.0102346 | I32: FY27 起瀑布新債利息（9%）與新股同時影響 EPS
A33: 全年淨利 | B33: US$bn | C33: =輸入與假設!$C$134+C17 -> -3.5360119 | D33: =D17 -> -5.186273 | E33: =E17 -> -4.973529 | F33: =F17 -> -5.5199483 | G33: =G17 -> -7.8195134
A34: 淨利率 | B34: % | C34: =C33/C26 -> -0.27062697 | D34: =D33/D26 -> -0.19849863 | E34: =E33/E26 -> -0.13563153 | F34: =F33/F26 -> -0.13029856 | G34: =G33/G26 -> -0.17379041
A35: 全年 GAAP EPS | B35: US$ | C35: =輸入與假設!$C$138+C17/C21 -> -6.2267835 | D35: =D17/D21 -> -8.7477406 | E35: =E17/E21 -> -8.3058447 | F35: =F17/F21 -> -7.6979104 | G35: =G17/G21 -> -9.8768711 | I35: FY26＝1H 實際 EPS −2.53＋下半年淨利÷股數
A36: 全年 EPS（加回 SBC） | B36: US$ | C36: =輸入與假設!$C$139+(C17+輸入與假設!$C$113*輸入與假設!C$24)/C21 -> -5.0405314 | D36: =(D17+輸入與假設!$C$113*輸入與假設!D$24)/D21 -> -7.5670433 | E36: =(E17+輸入與假設!$C$113*輸入與假設!E$24)/E21 -> -7.1368375 | F36: =(F17+輸入與假設!$C$113*輸入與假設!F$24)/F21 -> -6.7217169 | G36: =(G17+輸入與假設!$C$113*輸入與假設!G$24)/G21 -> -8.9926972 | I36: ＝(淨利＋SBC)÷股數；NOL 狀態無現金稅，SBC 全額加回

Sheet 評價_DCF與目標價
A1: 評價 — DCF、EV/EBITDA、加權目標價
A2: 營收、營業利益、D&A、EBITDA、股數引用『損益』頁；Cash CapEx 與融資引用『各期收支』頁
A4: 項目 | B4: 單位 | C4: FY26 | D4: FY27 | E4: FY28 | F4: FY29 | G4: FY30 | I4: 公式／來源說明
A5: DCF（無槓桿自由現金流；起點為 2026-06-30）
A6: 現金 CapEx（2026-06-30 之後） | B6: US$bn | C6: =輸入與假設!C$73-各期收支!C8 -> 19.16912 | D6: =輸入與假設!D$73-各期收支!D8 -> 35.2682 | E6: =輸入與假設!E$73-各期收支!E8 -> 27.0572 | F6: =輸入與假設!F$73-各期收支!F8 -> 28.152 | G6: =輸入與假設!G$73-各期收支!G8 -> 29.8724 | I6: DCF 起點為 6/30，故 FY26 欄只含 2H 的建置支出，不含 1H 已發生的 14.117
A7: 比較基期營收 | B7: US$bn | C7: =5.131 -> 5.131 | D7: =4.653+損益!C8 -> 13.066 | E7: =損益!D8 -> 26.1275 | F7: =損益!E8 -> 36.669415 | G7: =損益!F8 -> 42.363849 | I7: FY25 實際 5.131；FY27 基期＝1H 實際 4.653＋FY26 模型期營收
A8: 營運資金變動 | B8: US$bn | C8: =0.02*MAX(0,損益!C8-C7) -> 0.06564 | D8: =0.02*MAX(0,損益!D8-D7) -> 0.26123 | E8: =0.02*MAX(0,損益!E8-E7) -> 0.21083831 | F8: =0.02*MAX(0,損益!F8-F7) -> 0.11388866 | G8: =0.02*MAX(0,損益!G8-G7) -> 0.05260163 | I8: 營收增量的 2%
A9: 無槓桿 NOL 期初 | B9: US$bn | C9: =輸入與假設!$C$105 -> 4 | D9: =C11 -> 3.8393307 | E9: =D11 -> 2.7588873 | F9: =E11 -> 0.65245725 | G9: =F11 -> 0 | I9: DCF 用無槓桿稅（利息不可抵稅，否則稅盾被計兩次：一次在 UFCF、一次在 WACC）
A10: 本期動用（無槓桿） | B10: US$bn | C10: =MIN(C9,MAX(0,損益!C10)*0.8) -> 0.16066933 | D10: =MIN(D9,MAX(0,損益!D10)*0.8) -> 1.0804433 | E10: =MIN(E9,MAX(0,損益!E10)*0.8) -> 2.1064301 | F10: =MIN(F9,MAX(0,損益!F10)*0.8) -> 0.65245725 | G10: =MIN(G9,MAX(0,損益!G10)*0.8) -> 0
A11: 無槓桿 NOL 期末 | B11: US$bn | C11: =C9-C10+MAX(0,-損益!C10) -> 3.8393307 | D11: =D9-D10+MAX(0,-損益!D10) -> 2.7588873 | E11: =E9-E10+MAX(0,-損益!E10) -> 0.65245725 | F11: =F9-F10+MAX(0,-損益!F10) -> 0 | G11: =G9-G10+MAX(0,-損益!G10) -> 0
A12: 無槓桿所得稅（DCF 用） | B12: US$bn | C12: =MAX(0,損益!C10-C10)*輸入與假設!$C$104 -> 0.00843514 | D12: =MAX(0,損益!D10-D10)*輸入與假設!$C$104 -> 0.056723275 | E12: =MAX(0,損益!E10-E10)*輸入與假設!$C$104 -> 0.11058758 | F12: =MAX(0,損益!F10-F10)*輸入與假設!$C$104 -> 0.30010818 | G12: =MAX(0,損益!G10-G10)*輸入與假設!$C$104 -> 0.040051445 | I12: 與損益表的所得稅不同：此處不扣利息，數字較高，這是 DCF 的正確口徑
A13: UFCF | B13: US$bn | C13: =損益!C10-C12+損益!C18-C6-C8 -> -14.279525 | D13: =損益!D10-D12+損益!D18-D6-D8 -> -19.779016 | E13: =損益!E10-E12+損益!E18-E6-E8 -> -4.6435883 | F13: =損益!F10-F12+損益!F18-F6-F8 -> -1.664953 | G13: =損益!G10-G12+損益!G18-G6-G8 -> -0.71899857 | I13: ＝EBIT−無槓桿稅＋D&A−現金 CapEx−營運資金。建置期全為負是正常的
A14: 折現期數 | B14: 年 | C14: =0.5 -> 0.5 | D14: =1.5 -> 1.5 | E14: =2.5 -> 2.5 | F14: =3.5 -> 3.5 | G14: =4.5 -> 4.5 | I14: 自 2026-06-30 起算；FY26 模型期（下半年）的現金流平均落在 0.5 年
A15: 折現因子 | C15: =1/(1+輸入與假設!$C$101)^C14 -> 0.949158 | D15: =1/(1+輸入與假設!$C$101)^D14 -> 0.85509729 | E15: =1/(1+輸入與假設!$C$101)^E14 -> 0.77035792 | F15: =1/(1+輸入與假設!$C$101)^F14 -> 0.69401615 | G15: =1/(1+輸入與假設!$C$101)^G14 -> 0.62523977
A16: UFCF 現值 | B16: US$bn | C16: =C13*C15 -> -13.553525 | D16: =D13*D15 -> -16.912983 | E16: =E13*E15 -> -3.577225 | F16: =F13*F15 -> -1.1555043 | G16: =G13*G15 -> -0.4495465
A18: 五期 UFCF 現值合計 | C18: =SUM(C16:G16) -> -35.648784 | I18: 建置期現金流現值
A19: 常態化 FCF（FY30） | C19: =損益!G10*(1-輸入與假設!$C$104)+損益!G18-損益!G18*輸入與假設!$C$103 -> 5.9617364 | I19: ＝EBIT×(1−稅)＋D&A−維持性 CapEx(D&A×比率)。不讓成長性 CapEx 偽裝成永續 FCF
A20: 終值（Gordon） | C20: =IF(C29=1,0,C19*(1+輸入與假設!$C$102)/(輸入與假設!$C$101-輸入與假設!$C$102)) -> 76.757356 | I20: ＝常態化 FCF×(1+g)÷(WACC−g)
A21: 終值現值 | C21: =C20*G15 -> 47.991752
A22: 企業價值 EV | C22: =C18+C21 -> 12.342968
A23: 減：淨負債 | C23: =-輸入與假設!$C$100 -> -30 | I23: 6/30 本金 35.551 − 現金 5.524
A24: 股權價值 | C24: =C22+C23 -> -17.657032
A25: DCF 每股 | C25: =IF(C29=1,0,IF(輸入與假設!$C$115=2,C31,C30)) -> 0 | I25: 採用值：失效時為 0 且權重歸零；否則依「DCF 下限方式」取 0 截斷或選擇權
A26: 終值占 EV 比重 | C26: =C21/C22 -> 3.8881858 | I26: 超過 85% 表示結論由終值假設決定，不由現金流決定
A27: 新股募得現金（現值） | C27: =各期收支!C61/(1+輸入與假設!$C$101)^0+各期收支!D61/(1+輸入與假設!$C$101)^0.5+各期收支!E61/(1+輸入與假設!$C$101)^1.5+各期收支!F61/(1+輸入與假設!$C$101)^2.5+各期收支!G61/(1+輸入與假設!$C$101)^3.5 -> 10.310173 | I27: 期初到位，折現期數 0／0.5／1.5／2.5／3.5 年
A28: 融資後股數（含瀑布新股） | C28: =輸入與假設!$C$99+各期收支!G66 -> 0.76786489
A29: DCF 失效？（WACC ≤ g 或常態化 FCF ≤ 0） | C29: =IF(OR(輸入與假設!$C$101<=輸入與假設!$C$102,C19<=0),1,0) -> 0 | I29: 1＝失效：DCF 權重歸零、EV/EBITDA 100%。股權為負不算失效
A30: DCF 每股：0 截斷 | C30: =MAX(0,(C24+C27)/C28) -> 0
A31: DCF 每股：選擇權（Merton） | C31: =IF((C22+C27)<=0,0,((C22+C27)*NORMSDIST(C32)-輸入與假設!$C$100*EXP(-輸入與假設!$C$117*輸入與假設!$C$118)*NORMSDIST(C33))/C28) -> 11.040469 | I31: Black-Scholes：S＝企業價值＋新股現值、K＝淨負債
A32: d1 | C32: =IF((C22+C27)<=0,0,(LN((C22+C27)/輸入與假設!$C$100)+(輸入與假設!$C$117+輸入與假設!$C$116^2/2)*輸入與假設!$C$118)/(輸入與假設!$C$116*SQRT(輸入與假設!$C$118))) -> 0.43520171
A33: d2 | C33: =C32-輸入與假設!$C$116*SQRT(輸入與假設!$C$118) -> -0.62545846
A35: 倍數法（錨定年度，預設 FY29；FY28 起折回 FY27 末）
A36: 錨定年度 | C36: =CHOOSE(輸入與假設!$C$107,"FY27","FY28","FY29","FY30") -> FY29 | I36: 輸入與假設 F 區可改
A37: 錨定年度 EBITDA | C37: =INDEX(損益!$D$19:$G$19,1,輸入與假設!$C$107) -> 26.901044
A38: 錨定年度企業價值（倍數 × EBITDA） | C38: =C37*輸入與假設!$C$106 -> 161.40626
A39: 錨定年度末淨負債（總債務 − 現金） | C39: =INDEX(各期收支!$D$70:$G$70,1,輸入與假設!$C$107)-INDEX(各期收支!$D$41:$G$41,1,輸入與假設!$C$107) -> 85.028228 | I39: 含瀑布新債
A40: 錨定年度末股數（含瀑布新股） | C40: =INDEX(損益!$D$21:$G$21,1,輸入與假設!$C$107) -> 0.717071 | I40: 損益股數：SBC 逐年稀釋＋瀑布新股
A41: 折回 FY27 末的折現因子 | C41: =1/(1+輸入與假設!$C$101)^(輸入與假設!$C$107-1) -> 0.81162243 | I41: 以 WACC 折現 [Assumed]
A42: EV/EBITDA 每股（融資後） | C42: =MAX(0,(C38-C39)/C40)*C41 -> 86.449077 | I42: 以 0 為下限
A44: 加權目標價
A45: DCF 每股 × 有效權重 | C45: =C25*IF(C29=1,0,輸入與假設!$C$108) -> 0
A46: EV/EBITDA（融資後）× 有效權重 | C46: =C42*IF(C29=1,1,1-輸入與假設!$C$108) -> 47.546992
A47: 加權目標價 | C47: =SUM(C45:C46) -> 47.546992 | I47: 期前融資瀑布：缺口先由額度與資產層新債支應，殘差以股權募足；估值不再扣缺口本金
A48: 現價 | C48: =輸入與假設!$C$98 -> 85.43
A49: 潛在空間 | C49: =C47/C48-1 -> -0.44343916
A50: DCF 權重說明 | C50: =IF(C29=1,"DCF 失效，已以 EV/EBITDA 100% 計。",IF(AND(輸入與假設!$C$115<>2,C65<0),"DCF 為 $0 仍計 "&TEXT(輸入與假設!$C$108,"0%")&" 權重的原因：DCF 沒有失效，而是算出的股權價值為負（每股約 −$"&TEXT(ABS(C65),"0.0")&"），代表自由現金流折現後的企業價值不足以償還淨負債。EV/EBITDA 沒有扣除 GPU 汰換與擴張支出，保留 DCF 權重，是為了讓目標價反映「EBITDA 付不起資本成本」。若不計 DCF，目標價為 $"&TEXT(C42,"0.0")&"（"&CHOOSE(D64+2,"賣出","中立","買進")&"）；"&TEXT(輸入與假設!$C$108,"0%")&"／"&TEXT(1-輸入與假設!$C$108,"0%")&" 為判斷值。","")) -> DCF 為 $0 仍計 45% 權重的原因：DCF 沒有失效，而是算出的股權價值為負（每股約 −$9.6），代表自由現金流折現後的企業價值不足以償還淨負債。EV/EBITDA 沒有扣除 GPU 汰換與擴張支出，保留 DCF 權重，是為了讓目標價反映「EBITDA 付不起資本成本」。若不計 DCF，目標價為 $86.4（中立）；45%／55% 為判斷值。 | I50: 只在 DCF 被 0 截斷時顯示；DCF 失效時改為一句；DCF 為正時空白（與 HTML 同一字串）
A52: 目標價區間（情境區間、方法區間；評等仍依點位）
A53: 目標價區間｜點位（目前輸入的加權目標價） | C53: =C47 -> 47.546992 | I53: 評等規則不變：空間 ≥25% 且終值占比 <90%、股權募資 ≤1.5 倍現市值 → 買進；空間 ≤−15%，或股權募資 >1.5 倍且空間 ≤−8% → 賣出；其餘中立
A54: 目標價區間｜終值占 EV（評等用） | C54: =C21/MAX(ABS(C22),1)*IF(C22=0,1,SIGN(C22)) -> 3.8881858
A55: 目標價區間｜股權募資 ÷ 現市值（評等用） | C55: =SUM(各期收支!C61:G61)/(輸入與假設!$C$98*輸入與假設!$C$99) -> 0.27730563
A56: 目標價區間｜點位評等代碼（1＝買進、0＝中立、−1＝賣出） | C56: =IF(AND((C47/MAX(輸入與假設!$C$98,0.01)-1)>=0.25,$C$54<0.9,$C$55<=1.5),1,IF(OR((C47/MAX(輸入與假設!$C$98,0.01)-1)<=-0.15,AND($C$55>1.5,(C47/MAX(輸入與假設!$C$98,0.01)-1)<=-0.08)),-1,0)) -> -1 | D56: =CHOOSE(C56+2,"賣出","中立","買進") -> 賣出
A57: 目標價區間｜賣出門檻價（現價 × (1 − 15%)） | C57: =輸入與假設!$C$98*(1-0.15) -> 72.6155
A58: 目標價區間｜保守 4.2 GW（加權目標價／評等代碼／距賣出門檻） | C58: =輸入與假設!D143 -> 71.685847 | D58: =輸入與假設!E143 -> -1 | E58: =C58-$C$57 -> -0.92965312 | I58: 引用『輸入與假設』底部模擬運算表（情境選擇 1／2／3），保留其餘手動輸入
A59: 目標價區間｜基準 5.6 GW（加權目標價／評等代碼／距賣出門檻） | C59: =輸入與假設!D144 -> 47.546992 | D59: =輸入與假設!E144 -> -1 | E59: =C59-$C$57 -> -25.068508
A60: 目標價區間｜積極 8 GW（加權目標價／評等代碼／距賣出門檻） | C60: =輸入與假設!D145 -> 32.117817 | D60: =輸入與假設!E145 -> -1 | E60: =C60-$C$57 -> -40.497683
A61: 目標價區間｜情境區間（下緣／上緣） | C61: =MIN(C58,C60) -> 32.117817 | D61: =MAX(C58,C60) -> 71.685847
A62: 目標價區間｜方法區間倍數（下端／上端） | C62: =MIN(輸入與假設!$C$110,輸入與假設!$C$111) -> 5 | D62: =MAX(輸入與假設!$C$110,輸入與假設!$C$111) -> 6
A63: 目標價區間｜方法區間（下緣／上緣） | C63: =MIN(C25*IF(C29=1,0,輸入與假設!$C$108)+MAX(0,(C37*C62-C39)/C40)*C41*IF(C29=1,1,1-輸入與假設!$C$108),C25*IF(C29=1,0,輸入與假設!$C$108)+MAX(0,(C37*D62-C39)/C40)*C41*IF(C29=1,1,1-輸入與假設!$C$108)) -> 30.800506 | D63: =MAX(C25*IF(C29=1,0,輸入與假設!$C$108)+MAX(0,(C37*C62-C39)/C40)*C41*IF(C29=1,1,1-輸入與假設!$C$108),C25*IF(C29=1,0,輸入與假設!$C$108)+MAX(0,(C37*D62-C39)/C40)*C41*IF(C29=1,1,1-輸入與假設!$C$108)) -> 47.546992 | I63: ＝DCF 採用值 × 有效權重 ＋ EV/EBITDA 腿（倍數換成兩端）× 有效權重
A64: 目標價區間｜100% EV/EBITDA 目標價（價位／評等代碼） | C64: =C42 -> 86.449077 | D64: =IF(AND((C42/MAX(輸入與假設!$C$98,0.01)-1)>=0.25,$C$54<0.9,$C$55<=1.5),1,IF(OR((C42/MAX(輸入與假設!$C$98,0.01)-1)<=-0.15,AND($C$55>1.5,(C42/MAX(輸入與假設!$C$98,0.01)-1)<=-0.08)),-1,0)) -> 0 | E64: =CHOOSE(D64+2,"賣出","中立","買進") -> 中立
A65: 目標價區間｜未截斷 DCF 每股 | C65: =(C24+C27)/C28 -> -9.5679063
A66: 目標價區間｜點位摘要 | C66: ="目標價 $"&TEXT(C47,"0.0")&"（情境區間 $"&TEXT(C61,"0.0")&"–$"&TEXT(D61,"0.0")&"）" -> 目標價 $47.5（情境區間 $32.1–$71.7）
A67: 目標價區間｜方法區間標籤 | C67: ="方法區間（目前情境，"&IF(C62=INT(C62),TEXT(C62,"0"),TEXT(C62,"0.0"))&"–"&IF(D62=INT(D62),TEXT(D62,"0"),TEXT(D62,"0.0"))&"x）" -> 方法區間（目前情境，5–6x）
A68: 目標價區間｜點位位置 | C68: =IF(ABS(輸入與假設!$C$106-D62)<0.000000001,"目前點位位於方法區間上緣（"&IF(D62=INT(D62),TEXT(D62,"0"),TEXT(D62,"0.0"))&"x 為穩態倍數上緣）",IF(ABS(輸入與假設!$C$106-C62)<0.000000001,"目前點位位於方法區間下緣（"&IF(C62=INT(C62),TEXT(C62,"0"),TEXT(C62,"0.0"))&"x）","目前點位"&IF(AND(輸入與假設!$C$106>C62,輸入與假設!$C$106<D62),"位於方法區間內",IF(輸入與假設!$C$106>D62,"高於方法區間上緣","低於方法區間下緣"))&"（目前倍數 "&IF(輸入與假設!$C$106=INT(輸入與假設!$C$106),TEXT(輸入與假設!$C$106,"0"),TEXT(輸入與假設!$C$106,"0.0"))&"x）")) -> 目前點位位於方法區間上緣（6x 為穩態倍數上緣）
A69: 目標價區間｜判斷句 | C69: =IF(D61<輸入與假設!$C$98,"情境區間上緣 $"&TEXT(D61,"0.0")&" 低於現價 $"&TEXT(輸入與假設!$C$98,"0.00")&IF((D58<>-1)+(D59<>-1)+(D60<>-1)>0,"，但"&SUBSTITUTE(TRIM(IF(D58<>-1,"保守","")&" "&IF(D59<>-1,"基準","")&" "&IF(D60<>-1,"積極",""))," ","、")&"情境未達賣出門檻 $"&TEXT($C$57,"0.0"),"：賣出在三個擴張情境下都成立"),"情境區間上緣 $"&TEXT(D61,"0.0")&" 不低於現價 $"&TEXT(輸入與假設!$C$98,"0.00")&"：賣出並非在三個擴張情境下都成立")&"。"&IF(ABS(E58)<0.05*輸入與假設!$C$98,"保守情境 $"&TEXT(C58,"0.0")&"，"&IF(E58<0,"距賣出門檻","高於賣出門檻")&" $"&TEXT($C$57,"0.0")&" 僅 $"&TEXT(ABS(E58),"0.0")&"。","")&IF(ABS(E59)<0.05*輸入與假設!$C$98,"基準情境 $"&TEXT(C59,"0.0")&"，"&IF(E59<0,"距賣出門檻","高於賣出門檻")&" $"&TEXT($C$57,"0.0")&" 僅 $"&TEXT(ABS(E59),"0.0")&"。","")&IF(ABS(E60)<0.05*輸入與假設!$C$98,"積極情境 $"&TEXT(C60,"0.0")&"，"&IF(E60<0,"距賣出門檻","高於賣出門檻")&" $"&TEXT($C$57,"0.0")&" 僅 $"&TEXT(ABS(E60),"0.0")&"。","") -> 情境區間上緣 $71.7 低於現價 $85.43：賣出在三個擴張情境下都成立。保守情境 $71.7，距賣出門檻 $72.6 僅 $0.9。
A71: 錨定年度 × 倍數矩陣（每股；FY28 起以 WACC 折回 FY27 末）
A72: 倍數 ＼ 錨定（EV/EBITDA 腿） | B72: 倍數 | C72: FY27 | D72: FY28 | E72: FY29 | F72: FY30 | I72: EV/EBITDA 腿＝(錨定年 EBITDA × 倍數 − 錨定年末淨負債) ÷ 錨定年末股數 × 折現因子；加權＝DCF 採用值 × 有效權重 ＋ 腿 × 有效權重。綠底＝不低於現價
A73: 錨定×倍數｜EV/EBITDA 腿｜3.4x | B73: 3.4 | C73: =MAX(0,(INDEX(損益!$D$19:$G$19,1,1)*$B73-(INDEX(各期收支!$D$70:$G$70,1,1)-INDEX(各期收支!$D$41:$G$41,1,1)))/INDEX(損益!$D$21:$G$21,1,1))/(1+輸入與假設!$C$101)^(1-1) -> 0 | D73: =MAX(0,(INDEX(損益!$D$19:$G$19,1,2)*$B73-(INDEX(各期收支!$D$70:$G$70,1,2)-INDEX(各期收支!$D$41:$G$41,1,2)))/INDEX(損益!$D$21:$G$21,1,2))/(1+輸入與假設!$C$101)^(2-1) -> 0 | E73: =MAX(0,(INDEX(損益!$D$19:$G$19,1,3)*$B73-(INDEX(各期收支!$D$70:$G$70,1,3)-INDEX(各期收支!$D$41:$G$41,1,3)))/INDEX(損益!$D$21:$G$21,1,3))/(1+輸入與假設!$C$101)^(3-1) -> 7.2838679 | F73: =MAX(0,(INDEX(損益!$D$19:$G$19,1,4)*$B73-(INDEX(各期收支!$D$70:$G$70,1,4)-INDEX(各期收支!$D$41:$G$41,1,4)))/INDEX(損益!$D$21:$G$21,1,4))/(1+輸入與假設!$C$101)^(4-1) -> 9.6519078
A74: 錨定×倍數｜EV/EBITDA 腿｜4.5x | B74: 4.5 | C74: =MAX(0,(INDEX(損益!$D$19:$G$19,1,1)*$B74-(INDEX(各期收支!$D$70:$G$70,1,1)-INDEX(各期收支!$D$41:$G$41,1,1)))/INDEX(損益!$D$21:$G$21,1,1))/(1+輸入與假設!$C$101)^(1-1) -> 0 | D74: =MAX(0,(INDEX(損益!$D$19:$G$19,1,2)*$B74-(INDEX(各期收支!$D$70:$G$70,1,2)-INDEX(各期收支!$D$41:$G$41,1,2)))/INDEX(損益!$D$21:$G$21,1,2))/(1+輸入與假設!$C$101)^(2-1) -> 27.077878 | E74: =MAX(0,(INDEX(損益!$D$19:$G$19,1,3)*$B74-(INDEX(各期收支!$D$70:$G$70,1,3)-INDEX(各期收支!$D$41:$G$41,1,3)))/INDEX(損益!$D$21:$G$21,1,3))/(1+輸入與假設!$C$101)^(3-1) -> 40.776841 | F74: =MAX(0,(INDEX(損益!$D$19:$G$19,1,4)*$B74-(INDEX(各期收支!$D$70:$G$70,1,4)-INDEX(各期收支!$D$41:$G$41,1,4)))/INDEX(損益!$D$21:$G$21,1,4))/(1+輸入與假設!$C$101)^(4-1) -> 39.363826
A75: 錨定×倍數｜EV/EBITDA 腿｜5.0x | B75: 5 | C75: =MAX(0,(INDEX(損益!$D$19:$G$19,1,1)*$B75-(INDEX(各期收支!$D$70:$G$70,1,1)-INDEX(各期收支!$D$41:$G$41,1,1)))/INDEX(損益!$D$21:$G$21,1,1))/(1+輸入與假設!$C$101)^(1-1) -> 12.06057 | D75: =MAX(0,(INDEX(損益!$D$19:$G$19,1,2)*$B75-(INDEX(各期收支!$D$70:$G$70,1,2)-INDEX(各期收支!$D$41:$G$41,1,2)))/INDEX(損益!$D$21:$G$21,1,2))/(1+輸入與假設!$C$101)^(2-1) -> 44.180466 | E75: =MAX(0,(INDEX(損益!$D$19:$G$19,1,3)*$B75-(INDEX(各期收支!$D$70:$G$70,1,3)-INDEX(各期收支!$D$41:$G$41,1,3)))/INDEX(損益!$D$21:$G$21,1,3))/(1+輸入與假設!$C$101)^(3-1) -> 56.00092 | F75: =MAX(0,(INDEX(損益!$D$19:$G$19,1,4)*$B75-(INDEX(各期收支!$D$70:$G$70,1,4)-INDEX(各期收支!$D$41:$G$41,1,4)))/INDEX(損益!$D$21:$G$21,1,4))/(1+輸入與假設!$C$101)^(4-1) -> 52.869243
A76: 錨定×倍數｜EV/EBITDA 腿｜6.0x | B76: 6 | C76: =MAX(0,(INDEX(損益!$D$19:$G$19,1,1)*$B76-(INDEX(各期收支!$D$70:$G$70,1,1)-INDEX(各期收支!$D$41:$G$41,1,1)))/INDEX(損益!$D$21:$G$21,1,1))/(1+輸入與假設!$C$101)^(1-1) -> 38.722633 | D76: =MAX(0,(INDEX(損益!$D$19:$G$19,1,2)*$B76-(INDEX(各期收支!$D$70:$G$70,1,2)-INDEX(各期收支!$D$41:$G$41,1,2)))/INDEX(損益!$D$21:$G$21,1,2))/(1+輸入與假設!$C$101)^(2-1) -> 78.385644 | E76: =MAX(0,(INDEX(損益!$D$19:$G$19,1,3)*$B76-(INDEX(各期收支!$D$70:$G$70,1,3)-INDEX(各期收支!$D$41:$G$41,1,3)))/INDEX(損益!$D$21:$G$21,1,3))/(1+輸入與假設!$C$101)^(3-1) -> 86.449077 | F76: =MAX(0,(INDEX(損益!$D$19:$G$19,1,4)*$B76-(INDEX(各期收支!$D$70:$G$70,1,4)-INDEX(各期收支!$D$41:$G$41,1,4)))/INDEX(損益!$D$21:$G$21,1,4))/(1+輸入與假設!$C$101)^(4-1) -> 79.880078
A77: 錨定×倍數｜EV/EBITDA 腿｜7.0x | B77: 7 | C77: =MAX(0,(INDEX(損益!$D$19:$G$19,1,1)*$B77-(INDEX(各期收支!$D$70:$G$70,1,1)-INDEX(各期收支!$D$41:$G$41,1,1)))/INDEX(損益!$D$21:$G$21,1,1))/(1+輸入與假設!$C$101)^(1-1) -> 65.384697 | D77: =MAX(0,(INDEX(損益!$D$19:$G$19,1,2)*$B77-(INDEX(各期收支!$D$70:$G$70,1,2)-INDEX(各期收支!$D$41:$G$41,1,2)))/INDEX(損益!$D$21:$G$21,1,2))/(1+輸入與假設!$C$101)^(2-1) -> 112.59082 | E77: =MAX(0,(INDEX(損益!$D$19:$G$19,1,3)*$B77-(INDEX(各期收支!$D$70:$G$70,1,3)-INDEX(各期收支!$D$41:$G$41,1,3)))/INDEX(損益!$D$21:$G$21,1,3))/(1+輸入與假設!$C$101)^(3-1) -> 116.89723 | F77: =MAX(0,(INDEX(損益!$D$19:$G$19,1,4)*$B77-(INDEX(各期收支!$D$70:$G$70,1,4)-INDEX(各期收支!$D$41:$G$41,1,4)))/INDEX(損益!$D$21:$G$21,1,4))/(1+輸入與假設!$C$101)^(4-1) -> 106.89091
A79: 倍數 ＼ 錨定（加權目標價） | B79: 倍數 | C79: FY27 | D79: FY28 | E79: FY29 | F79: FY30
A80: 錨定×倍數｜加權目標價｜3.4x | B80: 3.4 | C80: =C25*IF(C29=1,0,輸入與假設!$C$108)+C73*IF(C29=1,1,1-輸入與假設!$C$108) -> 0 | D80: =C25*IF(C29=1,0,輸入與假設!$C$108)+D73*IF(C29=1,1,1-輸入與假設!$C$108) -> 0 | E80: =C25*IF(C29=1,0,輸入與假設!$C$108)+E73*IF(C29=1,1,1-輸入與假設!$C$108) -> 4.0061273 | F80: =C25*IF(C29=1,0,輸入與假設!$C$108)+F73*IF(C29=1,1,1-輸入與假設!$C$108) -> 5.3085493
A81: 錨定×倍數｜加權目標價｜4.5x | B81: 4.5 | C81: =C25*IF(C29=1,0,輸入與假設!$C$108)+C74*IF(C29=1,1,1-輸入與假設!$C$108) -> 0 | D81: =C25*IF(C29=1,0,輸入與假設!$C$108)+D74*IF(C29=1,1,1-輸入與假設!$C$108) -> 14.892833 | E81: =C25*IF(C29=1,0,輸入與假設!$C$108)+E74*IF(C29=1,1,1-輸入與假設!$C$108) -> 22.427263 | F81: =C25*IF(C29=1,0,輸入與假設!$C$108)+F74*IF(C29=1,1,1-輸入與假設!$C$108) -> 21.650104
A82: 錨定×倍數｜加權目標價｜5.0x | B82: 5 | C82: =C25*IF(C29=1,0,輸入與假設!$C$108)+C75*IF(C29=1,1,1-輸入與假設!$C$108) -> 6.6333135 | D82: =C25*IF(C29=1,0,輸入與假設!$C$108)+D75*IF(C29=1,1,1-輸入與假設!$C$108) -> 24.299256 | E82: =C25*IF(C29=1,0,輸入與假設!$C$108)+E75*IF(C29=1,1,1-輸入與假設!$C$108) -> 30.800506 | F82: =C25*IF(C29=1,0,輸入與假設!$C$108)+F75*IF(C29=1,1,1-輸入與假設!$C$108) -> 29.078084
A83: 錨定×倍數｜加權目標價｜6.0x | B83: 6 | C83: =C25*IF(C29=1,0,輸入與假設!$C$108)+C76*IF(C29=1,1,1-輸入與假設!$C$108) -> 21.297448 | D83: =C25*IF(C29=1,0,輸入與假設!$C$108)+D76*IF(C29=1,1,1-輸入與假設!$C$108) -> 43.112104 | E83: =C25*IF(C29=1,0,輸入與假設!$C$108)+E76*IF(C29=1,1,1-輸入與假設!$C$108) -> 47.546992 | F83: =C25*IF(C29=1,0,輸入與假設!$C$108)+F76*IF(C29=1,1,1-輸入與假設!$C$108) -> 43.934043
A84: 錨定×倍數｜加權目標價｜7.0x | B84: 7 | C84: =C25*IF(C29=1,0,輸入與假設!$C$108)+C77*IF(C29=1,1,1-輸入與假設!$C$108) -> 35.961583 | D84: =C25*IF(C29=1,0,輸入與假設!$C$108)+D77*IF(C29=1,1,1-輸入與假設!$C$108) -> 61.924952 | E84: =C25*IF(C29=1,0,輸入與假設!$C$108)+E77*IF(C29=1,1,1-輸入與假設!$C$108) -> 64.293479 | F84: =C25*IF(C29=1,0,輸入與假設!$C$108)+F77*IF(C29=1,1,1-輸入與假設!$C$108) -> 58.790002

Sheet 評價_反向DCF
A1: 反向 DCF — 現價隱含什麼樣的收入與成本
A2: 不是問「值多少」，而是問「要值現價，營運要長什麼樣」。Excel 以『目標搜尋』反解；下方另附 HTML 即時計算結果的快照（v4.0 預設輸入）
A4: 即時：目前 DCF 與現價的差距
A5: 現價 | B5: =輸入與假設!$C$98 -> 85.43
A6: 目前 DCF 每股（依下限方式） | B6: =評價_DCF與目標價!C25 -> 0
A7: 差距（DCF − 現價）＝目標搜尋的『設定儲存格』 | B7: =B6-B5 -> -85.43
A8: 目前每 MW 年收入倍數／建置成本倍數 | B8: =輸入與假設!$C$22 -> 1 | C8: =輸入與假設!$C$55 -> 1
A10: 操作：用『目標搜尋』反解（資料 → 模擬分析 → 目標搜尋）
A11: ① 設定儲存格：本頁 B7；目標值：0
A12: ② 變數儲存格（擇一）：輸入與假設 B 區『每 MW 年收入倍數』→ 市價隱含單價；或 D 區『每 MW 建置成本倍數』→ 市價隱含建置成本；或 C 區『穩態 EBITDA 率』
A13: ③ 解完請記下結果，再把倍數改回 100%（或按 Ctrl+Z）。DCF 以 0 截斷時，負值區域斜率為 0，請從 100% 以上開始搜尋
A14: ④ 組合分析：先把 D 區建置成本倍數與 C 區穩態 EBITDA 率設為想測的值，再對『每 MW 年收入倍數』做目標搜尋，即得下方矩陣中的一格
A16: 快照：單一槓桿（HTML v4.0 預設輸入，DCF 0 截斷）
A17: 單一槓桿（其他不變） | B17: 目前 | C17: 市價隱含 | D17: 變動 | G17: 對照
A18: FY30 每 MW 年收入（US$m） | B18: 10.5 | C18: 13.9581 | D18: 0.3293 | G18: 期末 ARR 指引隱含約 $10.0–10.5m；7 月新約漲價約 25%
A19: 每 MW 建置成本（US$m） | B19: 34 | C19: 20.8596 | D19: -0.3865 | G19: FY26 指引隱含約 $32–37m
A20: 穩態 EBITDA 率（FY30） | B20: 0.65 | C20: 0.8485 | D20: 0.1985 | G20: Q2 實際 59%；由下而上上緣約 67–71%（變動為百分點）
A21: （對照）加權目標價＝現價所需每 MW 年收入 | B21: 10.5 | C21: 12.1568 | D21: 0.1578 | G21: 含 EV/EBITDA 6x（FY29 錨定） 腿；非純反向 DCF
A23: 快照：收入與成本的綜合影響——要值現價，FY30 每 MW 年收入需要多少（US$m）
A24: 建置成本 ＼ 穩態 EBITDA 率 | B24: 0.59 | C24: 0.65 | D24: 0.7 | E24: 0.75
A25: $23.8m（-30%） | B25: 12.45 | C25: 11.24 | D25: 10.38 | E25: 9.62
A26: $27.2m（-20%） | B26: 13.38 | C26: 12.09 | D26: 11.17 | E26: 10.37
A27: $30.6m（-10%） | B27: 14.31 | C27: 12.95 | D27: 11.97 | E27: 11.12
A28: $34.0m（目前） | B28: 15.41 | C28: 13.96 | D28: 12.92 | E28: 12.01
A29: $37.4m（+10%） | B29: 16.67 | C29: 15.11 | D29: 13.99 | E29: 13.01
A30: 快照為靜態數值（HTML 以同一引擎即時計算）；改變輸入後請以目標搜尋重算，或參考 HTML『評價 → 反向 DCF』

Sheet 評價_可比公司
A1: 可比公司 — 以 EV/Sales 為主（市值：2026-09-21 收盤）
A2: EV＝市值＋（有息負債−非受限現金）；含租賃＝EV＋營業租賃負債。EV/EBITDA 僅供參考（同業 GAAP EBITDA 皆為負，顯示 n/m）。此表不進入目標價。與 HTML Comps 分頁同一組數字
A4: 公司 | B4: 市值 | C4: 淨負債 | D4: EV | E4: TTM 營收 | F4: EV/Sales（TTM） | G4: 含租賃 EV/Sales | H4: TTM EBITDA | I4: EV/EBITDA | J4: 資料期 | K4: 備註
A5: NBIS Nebius | B5: 63.81 | C5: 2.16 | D5: =B5+C5 -> 65.97 | E5: 1.36 | F5: =D5/E5 -> 48.507353 | G5: =(D5+0)/E5 -> 48.507353 | H5: =-0.612+0.418 -> -0.194 | I5: =IF(H5>0,D5/H5,"n/m") -> n/m | J5: EBITDA：FY25 20-F | K5: 營業租賃負債 0.0；GAAP 營業損益 -0.612＋D&A 0.418。季報未 XBRL 標註，EBITDA 用 FY2025；營收為 TTM。前瞻 EV/Sales 約 9.3x（由 9/18 forward PS 8.46 推算 [Derived]）
A6: IREN | B6: 18.61 | C6: 1.7 | D6: =B6+C6 -> 20.31 | E6: 0.707 | F6: =D6/E6 -> 28.727016 | G6: =(D6+0.003)/E6 -> 28.731259 | H6: =-1.047+0.418 -> -0.629 | I6: =IF(H6>0,D6/H6,"n/m") -> n/m | J6: FY26 10-K（6/30） | K6: 營業租賃負債 0.003；GAAP 營業損益 -1.047＋D&A 0.418。自有電廠、營業租賃負債僅 0.003bn；FY26 合約 ARR 4.0bn
A7: APLD Applied Digital | B7: 8.22 | C7: 3.37 | D7: =B7+C7 -> 11.59 | E7: 0.6113 | F7: =D7/E7 -> 18.959594 | G7: =(D7+0.066)/E7 -> 19.067561 | H7: =-0.236+0.067 -> -0.169 | I7: =IF(H7>0,D7/H7,"n/m") -> n/m | J7: FY26 10-K（5/31） | K7: 營業租賃負債 0.066；GAAP 營業損益 -0.236＋D&A 0.067。租約多未起租，營收尚未反映約 36bn 合約
A8: CORZ Core Scientific | B8: 5.9 | C8: 2.53 | D8: =B8+C8 -> 8.43 | E8: 0.4403 | F8: =D8/E8 -> 19.146037 | G8: =(D8+0.109)/E8 -> 19.393595 | H8: =-0.561+0.063 -> -0.498 | I8: =IF(H8>0,D8/H8,"n/m") -> n/m | J8: TTM 至 Q2（6/30） | K8: 營業租賃負債 0.109；GAAP 營業損益 -0.561＋D&A 0.063。託管轉型期
A9: 同業中位數 | F9: =MEDIAN(F5:F8) -> 23.936526 | G9: =MEDIAN(G5:G8) -> 24.062427
A10: CRWV（TTM 至 Q2） | B10: 47.12 | C10: =輸入與假設!$C$100 -> 30 | D10: =B10+C10 -> 77.12 | E10: 7.59 | F10: =D10/E10 -> 10.160738 | G10: =(D10+16.319)/E10 -> 12.310804 | H10: =-0.231+3.991 -> 3.76 | I10: =IF(H10>0,D10/H10,"n/m") -> 20.510638 | J10: TTM 至 Q2 | K10: EV 用 9/21 市值與 6/30 淨負債；含租賃再加營業租賃負債 16.319
A11: CRWV 模型 FY27E | B11: =輸入與假設!$C$98*輸入與假設!$C$99 -> 50.14741 | C11: =輸入與假設!$C$100 -> 30 | D11: =B11+C11 -> 80.14741 | E11: =損益!D8 -> 26.1275 | F11: =D11/E11 -> 3.0675499 | G11: =(D11+16.319)/E11 -> 3.6921408 | H11: =損益!D19 -> 15.807137 | I11: =D11/H11 -> 5.0703304 | K11: 市值用模型股數（含 ATM 上限）；分母為模型 FY27 營收
A13: 讀法：CRWV 的 TTM EV/Sales 約為同業中位數的四成。折價來源有三，不能全部解讀為便宜：(1) 同業仍在爬坡，TTM 營收遠小於已簽約規模，TTM 倍數偏高；
A14: (2) CRWV 用租約取得機房，加入營業租賃負債後倍數升至約 12x，同業加與不加差別很小；(3) 客戶集中（前三大 72%）與五期外部資金需求。
A15: 前瞻：NBIS 前瞻 EV/Sales 約 9.3x（由 9/18 forward PS 推算 [Derived]），CRWV 模型 FY27E 約 3x。此表為市場比較用，不進入目標價（DCF 45%＋EV/EBITDA 55%）。

Sheet 檢查_連動
A1: 連動檢查 — 恆等式與口徑
A3: 檢查項目 | B3: 實際值 | C3: 標準 | D3: 結果 | E3: 說明
A4: RPO 桶權重合計 | B4: =SUM(輸入與假設!C25:G25) -> 0.84 | C4: =輸入與假設!$C$18 -> 0.84 | D4: =IF(ABS(B4-C4)<0.0001,"通過","不一致") -> 通過 | E4: 10-Q 桶 41／39／20 線性分攤後應為 84%
A5: 現金橋差異 | B5: =各期收支!C84 -> -2.5757174e-14 | C5: =0 -> 0 | D5: =IF(ABS(B5)<0.01,"通過","不一致") -> 通過 | E5: 期初＋營運缺口＋股權＋額度−還本 ＝ 期末
A6: Billable ≤ Accepted（FY30） | B6: =運營_產能與收入!G9-運營_產能與收入!G10 -> 350 | C6: ≥0 | D6: =IF(B6>=0,"通過","不一致") -> 通過 | E6: 引擎已以 MIN 截斷；此列驗證截斷有效
A7: FY26 CapEx 認列 vs 指引 | B7: =各期收支!C88 -> 36.975 | C7: 35–39 | D7: =IF(AND(B7>=35,B7<=39),"通過","觀察") -> 通過 | E7: 1H 實際認列 16.139＋2H 模型；公司 8/11 上修全年 35–39
A8: FY26 營收 vs 指引 | B8: =各期收支!C87 -> 13.066 | C8: 12.4–13.2 | D8: =IF(AND(B8>=12.4,B8<=13.2),"通過","觀察") -> 通過 | E8: 1H 實際 4.653＋2H 模型（算力＋非算力服務）
A9: CapEx 強度（模型期合計） | B9: =SUM(各期收支!C6:G6)/((運營_產能與收入!G9-輸入與假設!$C$20)/1000)/1000*1000 -> 39.48 | C9: $28–34m/MW | D9: =IF(AND(B9>=20,B9<=45),"通過","觀察") -> 通過 | E9: 公司自身比率：2026 CapEx 35–39bn 對應約 +1.25 GW ＝ $28–34m/MW
A10: 表外租金路徑 ÷ 已承諾 | B10: =資產負債_租賃承諾!C27 -> 0.89221822 | C10: ≥0.8x | D10: =IF(B10>=0.8,"通過","不一致") -> 通過 | E10: 8 GW 路徑所需新租約多數未簽，路徑高於承諾屬假設
A11: FY26 利息（1H 實際＋2H） | B11: =各期收支!C89 -> 3.5468486 | C11: ≥2.9 | D11: =IF(B11>=2.9,"通過","觀察") -> 通過 | E11: 1H 實際 1.176＋2H 模型 1.8；Q3 指引 0.86–0.94／季
A12: FY28 起收入是否依賴未簽約 | B12: =SUM(運營_產能與收入!E23:G23)/SUM(運營_產能與收入!E25:G25) -> 0.40729557 | C12: <50% 較穩健 | D12: =IF(B12<0.5,"通過","觀察") -> 通過 | E12: FY28–30 新簽約收入 ÷ 同期總算力收入。高＝8 GW 敘事的風險集中點
A13: 損益營收＝資金營收 | B13: =損益!D6-運營_產能與收入!D25 -> 0 | C13: =0 -> 0 | D13: =IF(ABS(B13)<0.001,"通過","不一致") -> 通過 | E13: FY27 損益算力收入 − 產能頁 isRev。兩邊必須同一組數字
A14: 終值占 EV 比重 | B14: =評價_DCF與目標價!C26 -> 3.8881858 | C14: <85% | D14: =IF(B14<0.85,"通過","觀察") -> 觀察 | E14: 過高表示結論由終值假設決定
A15: EBITDA 單一來源（FY27 損益 EBITDA÷營收 − 輸入 EBITDA 率） | B15: =損益!D19/損益!D8-輸入與假設!D39 -> 0 | C15: =0 -> 0 | D15: =IF(ABS(B15)<0.0001,"通過","不一致") -> 通過 | E15: 損益與資金引用同一列 EBITDA 率
A16: 現金 EBITDA ＋ 信用調整 − 損益 EBITDA（FY27） | B16: =(運營_產能與收入!D36+運營_產能與收入!D37+輸入與假設!D40-各期收支!D12)+(運營_產能與收入!D31+運營_產能與收入!D23*輸入與假設!D31*(1-輸入與假設!D32))*運營_產能與收入!D35-損益!D19 -> 0 | C16: =0 -> 0 | D16: =IF(ABS(B16)<0.001,"通過","不一致") -> 通過 | E16: 現金 EBITDA＝RPO 現金＋新簽約現金＋服務現金−租金；信用調整＝信用損失×EBITDAR 率
A17: DCF 有效性（1＝失效） | B17: =評價_DCF與目標價!C29 -> 0 | C17: 0 | D17: =IF(B17=0,"通過","觀察") -> 通過 | E17: 失效只定義為 WACC ≤ g 或常態化 FCF ≤ 0；股權為負不算失效
A18: 期末現金 ≥ 最低現金（期前融資） | B18: =MIN(各期收支!C41:G41) -> 2 | C18: ≥2.0 | D18: =IF(B18>=1.999,"通過","不一致") -> 通過 | E18: 瀑布每期補足至最低現金；最小值應等於最低現金
A19: 股權募資 ÷ 現市值 | B19: =SUM(各期收支!C61:G61)/(輸入與假設!$C$98*輸入與假設!$C$99) -> 0.27730563 | C19: ≤1.5x | D19: =IF(B19<=1.5,"通過","觀察") -> 通過 | E19: 超過 1.5 倍：市場吸收能力存疑，結論不得為買進
A20: 債務明細合計 = 10-Q 本金 35.551 | B20: =資產負債_既有債務!E21 -> 35.551 | C20: 35.551 | D20: =IF(ABS(B20-35.551)<0.01,"通過","不一致") -> 通過 | E20: 16 筆工具逐筆加總
A21: FY26 全年 CapEx（MW 公式） | B21: =輸入與假設!C68 -> 36.975 | C21: 35–39 | D21: =IF(AND(B21>=35,B21<=39),"通過","觀察") -> 通過 | E21: 由 YE25 850→YE26 1,850 MW 與預建 FY27 推得；應重現公司全年指引
A22: JV 已承諾餘額於 2026 年內履行 | B22: =SUM(輸入與假設!C61:G61) -> 1.15 | C22: =1.15 -> 1.15 | D22: =IF(ABS(B22-1.15)<0.01,"通過","不一致") -> 通過 | E22: 10-Q：1.7 承諾預計 2026 年內履行，H1 已付 0.55
A23: 模型每 MW 年租金（FY30） | B23: =運營_站點!G25 -> 0.99818047 | C23: ≥ 市場基準×占比 | D23: =IF(B23>=運營_站點!$H$9*運營_站點!$C$26*0.8,"通過","觀察") -> 觀察 | E23: 低於基準×占比的八成即標示：模型租金路徑可能低估
A24: 站點租賃：五期租金可能低估 | B24: =運營_站點!$C$29 -> 3.2916603 | C24: <10 | D24: =IF(B24<10,"通過","觀察") -> 通過 | E24: ＝Σ(在役 MW×市場基準×第三方占比 − 模型租金)
A26: 關鍵輸出（快照；「模型期」＝2026-07-01～2030，與 HTML 頂部 KPI 同口徑）
A27: 模型期排程 RPO | B27: =SUM(運營_產能與收入!C17:G17) -> 108.108
A28: 模型期產能瓶頸 | B28: =SUM(運營_產能與收入!C19:G19) -> 6.33475
A29: 模型期新簽約收入 | B29: =SUM(運營_產能與收入!C23:G23) -> 47.094444
A30: 模型期毛 CapEx（6/30 起） | B30: =SUM(輸入與假設!C73:G73) -> 151.651
A31: 模型期租金（6/30 起） | B31: =SUM(各期收支!C12:G12) -> 20.317893
A32: 模型期利息（6/30 起，含瀑布新債） | B32: =SUM(各期收支!C17:G17) -> 32.125969
A33: 模型期排程還本（6/30 起） | B33: =SUM(輸入與假設!C93:G93)*輸入與假設!$C$82 -> 20.655
A34: 模型期營運缺口（6/30 起） | B34: =SUM(各期收支!C39:G39)-(輸入與假設!$C$122-輸入與假設!$C$123-輸入與假設!$C$125) -> -75.341115
A35: FY26 全年口徑營運缺口（含 1H 實際） | B35: =SUM(各期收支!C39:G39) -> -86.483115
A36: 期末現金 | B36: =各期收支!G41 -> 2
A37: DCF 每股 | B37: =評價_DCF與目標價!C25 -> 0
A38: 加權目標價 | B38: =評價_DCF與目標價!C47 -> 47.546992

Sheet 檢查_版本紀錄
A1: 版本紀錄（基準情境目標價變化與原因）
A2: v2.9 以前檔名日期統一沿用 20260918，此處日期為實際修改日。v1.7 以前基準為 8 GW、v1.7 為 5 GW、v1.8 起為 5.6 GW；情境定義改變的版本不可直接比較。目標價以當版預設輸入計算（DCF 0 截斷）
A4: 版本 | B4: 日期 | C4: 主要變更 | D4: 基準目標價 | E4: 變動原因
A5: v4.1 | B5: 09-25 | C5: 目標價改為區間呈現：情境區間（保守與積極情境，保留手動調整）與方法區間（目前情境，EV/EBITDA 5–6x）；判斷句揭露與賣出門檻的餘裕；DCF 權重說明；刪除評價頁舊的下檔／上檔與操作區間；Excel 情境區間以模擬運算表計算（活公式） | D5: $47.5 | E5: 點位無變動；情境區間 $32.1–$71.7、方法區間 $30.8–$47.5
A6: v4.0 | B6: 09-24 | C6: 結構重整：公司資料集中到 company.json（HTML 與 Excel 共用，Excel 75 項輸入改讀此檔）；資料常數與引擎主函式改為可讀名稱；數字與畫面與 v3.6 完全相同 | D6: $47.5 | E6: 無變動（純結構）
A7: v3.6 | B7: 09-24 | C7: EV/EBITDA 錨定年度預設改為 FY29（接近穩態利潤率，與 6x 穩態倍數一致） | D7: $47.5 | E7: 錨定 FY27→FY29：EV/EBITDA 腿 $38.7→$86.4；保守情境 $71.7（−16%）接近賣出門檻
A8: v3.5 | B8: 09-24 | C8: EV/EBITDA 錨定年度可選（FY27–FY30，FY28 起以 WACC 折回 FY27 末）；評價頁與總結頁新增「錨定年度 × 倍數」矩陣；總結頁新增評價方法頁（9 頁） | D8: $21.3 | E8: 預設仍錨定 FY27，無變動；FY29 × 6x 為 $47.5
A9: v3.4 | B9: 09-24 | C9: 新增「總結」簡報頁（8 頁、即時連動、簡報模式、列印 16:9）；股權敏感度表加註融資組合與自動說明；更正融資瀑布說明的股權年度；修正 Excel 無法開啟（sheetPr 子元素順序，v3.3 起即存在） | D9: $21.3 | E9: 無變動
A10: v3.3 | B10: 09-23 | C10: 反向 DCF（收入 × 成本組合）；版本變更紀錄；每 MW 年收入／建置成本倍數 | D10: $21.3 | E10: 倍數預設 100%，無變動
A11: v3.2 | B11: 09-23 | C11: 切換情境時保留手動調整的數字 | D11: $21.3 | E11: 無變動
A12: v3.1 | B12: 09-23 | C12: 模組化（輸入與假設／各期收支／運營活動／資產與負債／損益／評價）；新債與新股；Excel 分頁改名與拆分 | D12: $21.3 | E12: 無變動
A13: v3.0 | B13: 09-23 | C13: DCF 失效條件；DCF 下限方式切換（0／選擇權）；HTML 左欄分類選單；日期與版本同步 | D13: $21.3 | E13: 選擇權模式為 $26.3
A14: v2.9 | B14: 09-23 | C14: Excel 依類別排序並可收合；原生併入 Copilot 改動 | D14: $21.3 | E14: 無變動
A15: v2.6–2.8 | B15: 09-23 | C15: 外部（Copilot）版面調整與每 MW 年收入敏感性 | D15: $21.3 | E15: 於 v2.9 併入
... A31: v1.0 | B31: 09-18 | C31: Oracle 模板改寫為 CoreWeave：2H26–FY30、10-Q／法說／8-K 數據 | D31: $19 | E31: 基準當時為 8 GW

Sheet 來源
A1: 來源與標籤
A3: 標籤 | B3: 內容
A4: Verified | B4: Q2 2026 10-Q（期末 2026-06-30，2026-08-12 申報，Non-accelerated filer，Q3 期限 11/16）：營收 2.575bn +112%（H1 4.653）；GAAP 營損 −0.049；利息費用 0.640（H1 1.176，現金 0.806、資本化 0.176）；淨損 −0.626；Adj. EBITDA 1.510（59%）；SBC 0.165；D&A 1.393；營業租賃成本 0.500、變動租賃 0.150。
A5: Verified | B5: 資產負債：現金 5.524、受限 1.380、有價證券 0.015、可用額度 10.014；PP&E 46.736（CIP 11.9）；營業 ROU 16.595；遞延收入 9.692；債務本金 35.551（追索淨 31.405／非追索 3.663）；股東權益 5.024。
A6: Verified | B6: RPO 103.7bn（backlog 104.2）：41% 於 2028-06 前、39% 於 25–48 月、20% 於 49–78 月。客戶集中：A 36%、B 26%、C 10%；OpenAI 最高 6.5bn 至 2031-05；Meta 最高 21.0bn；Jane Street 約 6.0bn。
A7: Verified | B7: 租賃與承諾：在帳未折現 29.135（營業）＋0.235（融資），2030 後 19.023；未起租租賃 35.5；單站 393 MW 按造價計租上限 14.7／16 年；355 MW 按造價計租（未定）；自備設備 0.5–1.2；JV 承諾 1.7（已付 0.55）；VIE 0.108。
A8: Verified | B8: 現金流（H1）：CFO 3.663；現金購置 PP&E 14.117；借款 16.747、還款 5.219；capped call 0.492；私募股權 2.982。CapEx 認列口徑 Q2 9.352、H1 16.139。
A9: Verified | B9: 9/17 8-K：2033 可轉債 3.7bn、2.875%、轉換價 $97.85、capped call 上限 $199.70；股權分銷最多 35m 股；9/17 收盤 $79.88。
A10: Verified | B10: 市值（2026-09-21 收盤，S&P Global via stockanalysis.com）：CRWV $85.43、47.12bn、流通 551.54m；NBIS 63.81；IREN 18.61；APLD 8.22；CORZ 5.90。淨負債取最新申報：NBIS 2.16、IREN 1.70、APLD 3.37、CORZ 2.53。目標價均值 144.46（38 家）；9/21 Rothschild Redburn 首評 Sell $54、BTG Pactual Buy $125。
A11: Interested-party | B11: 法說（8/11）：主動電力 1.5 GW（Q2 +近 500 MW，6 月 +300 MW）；簽約 4.2 GW；2030 ≥8 GW；近期產能實質售罄；7 月 SKU 漲價約 25%；全年營收 12.4–13.2、調整後營益 0.96–1.15、CapEx 35–39、期末 ARR 18.5–19.5；Q3 營收 3.45–3.6、利息 0.86–0.94、CapEx 11.5–13.5。
A12: Interested-party | B12: 9/17 投資人簡報：Q2 pro forma 總債務 38.6bn；加權利率 FY23 14.9% → Q2 8.3% → pro forma 7.8%；總債務／backlog 0.4x；歷年 backlog 9.9／15.1／66.8／104.2。
A13: User-provided | B13: 5Y CDS（2026-09）：中價 720bps、Bid/Ask 690／750、近期區間 680–855（對照 7/28 峰值 855、6 月低點 452）。
A14: Derived | B14: RPO 桶內線性分攤（41/39/20 → 五期 10.25／20.5／20／19.5／13.75%）；EBITDAR 率＝EBITDA 率＋租金÷營收（v2.3 起與損益連動）；客戶預付率 8.5%；rev/MW 錨 10.0–10.5M/MW。
... A18: 方法 | B18: v2.0 期前融資瀑布：額度→資產層新債（總債務 ≤ 債務/backlog 上限）→股權殘差；舊版假設缺口全額舉債且無上限（透支利息＝利息、扣缺口＝本金），v2.0 改為債務設上限、殘差以股權支應。
